Workbook
Name \0: #REF!
Name \1: #REF!
Name \2: #REF!
Name \a: #REF!
Name \a: #N/A
Name \b: #N/A
Name \c: #N/A
Name \d: #N/A
Name \e: #N/A
Name \f: #N/A
Name \g: #N/A
Name \h: #N/A
Name \i: #N/A
Name \j: #N/A
Name \k: #REF!
Name \l: #REF!
Name \m: #N/A
Name \n: #REF!
Name \O: #REF!
Name \p: #N/A
Name \q: #N/A
Name \r: #N/A
Name \s: #N/A
Name \t: #N/A
Name \u: #N/A
Name \v: #N/A
Name \w: #N/A
Name \x: #N/A
Name \z: #N/A
Name _: #REF!
Name _______F99000: #REF!
Name ______F99000: #REF!
Name ____COD1: #REF!
Name ____COD10: #REF!
Name ____COD11: #REF!
Name ____COD13: #REF!
Name ____COD16: #REF!
Name ____COD17: #REF!
Name ____COD21: #REF!
Name ____COD23: #REF!
Name ____COD24: #REF!
Name ____COD28: #REF!
Name ____COD29: #REF!
Name ____COD32: #REF!
Name ____COD35: #REF!
Name ____COD36: #REF!
Name ____COD37: #REF!
Name ____COD41: #REF!
Name ____COD42: #REF!
Name ____COD43: #REF!
Name ____COD44: #REF!
Name ____COD46: #REF!
Name ____COD47: #REF!
Name ____COD49: #REF!
Name ____COD50: #REF!
Name ____COD55: #REF!
Name ____COD60: #REF!
Name ____COD62: #REF!
Name ____COD65: #REF!
Name ____COD66: #REF!

Sheet PREMISSAS
B2: PREMISSAS CONSIDERADAS - MAIO 2026
D6: A distribuição de quantitativos na linha do tempo foi feita com base nos prazos previstos no cronograma da obra postado na base do Primavera
D11: As SS's em revisão orçamentária e de cronograma não foram consideradas;
D16: As SS's em fase de planejamento no SAMC na data de fechamento 01/05 não foram consideradas
D22: Não foram consideradas retenções ou devoluções por data book
B28: SS-41/2026 | D28: IN-5250-24-092 - PT-200 - Civil e Fundações | J28: Em replanejamento - Revisão de projetos
B29: SS-42/2026 | D29: IN-5250-24-092 - PT-200 - Civil e Arquitetura | J29: =J28 -> Em replanejamento - Revisão de projetos
B30: SS-145/2025 | D30: IN - 5250-24-074 - Adequações para Recebimento de C5+ - Civil | J30: Em replanejamento - Revisão de projetos
B31: SS-146/2025 | D31: IN - 5250-24-074 - Adequações para Recebimento de C5+ - Mecânica | J31: Em replanejamento - Revisão de projetos
B32: SS-147/2025 | D32: IN - 5250-24-074 - Adequações para Recebimento de C5+ - Elétrica | J32: Em replanejamento - Revisão de projetos
B33: SS-125/2026 | D33: U-110 - DEMOLIÇÃO FUNDAÇÃO - 110-R-01 | J33: Foram consideradas, porém na data do fechamento foi enviadas uma revisão dos projetos via SAMC
B34: SS-126/2026 | D34: U-110 - CONSTRUÇÃO FUNDAÇÃO - 110-R-01 | J34: Foram consideradas, porém na data do fechamento foi enviadas uma revisão dos projetos via SAMC

Sheet RESUMO CRON FINANC
B4: TIME LINE - OBRAS SERVIÇOS | F4: MAIO | G4: JUNHO | H4: JULHO | I4: AGOSTO | J4: SETEMBRO | K4: OUTUBRO | L4: NOVEMBRO | M4: DEZEMBRO | N4: TOTAL MAIO A DEZ/2026
B5: ITEM | D5: DESCRIÇÃO | E5: DISCIPLINA
B6: 1 | C6: SS-1/2026 | D6: Adequação Escadas de Marinheiro - Execução - UN 01,102,108,109,209 - UDAV 01/02 | E6: Civil | F6: ='CRONO SERV'!X7 -> 8448.9511 | G6: ='CRONO SERV'!Y7 -> 22525.794 | H6: ='CRONO SERV'!Z7 -> 22525.794 | I6: ='CRONO SERV'!AA7 -> 27860.851 | J6: ='CRONO SERV'!AB7 -> 26675.282 | K6: ='CRONO SERV'!AC7 -> 26400.231 | L6: ='CRONO SERV'!AD7 -> 0 | M6: ='CRONO SERV'!AE7 -> 0 | N6: =SUM(F6:M6) -> 134436.9
B7: 2 | C7: SS-2/2026 | D7: IN-5250-24-092 - PT-200 - Escavação Manual para Pré Furos e Fundação | E7: Civil | F7: ='CRONO SERV'!X12 -> 86040.747 | G7: ='CRONO SERV'!Y12 -> 47782.443 | H7: ='CRONO SERV'!Z12 -> 0 | I7: ='CRONO SERV'!AA12 -> 0 | J7: ='CRONO SERV'!AB12 -> 0 | K7: ='CRONO SERV'!AC12 -> 0 | L7: ='CRONO SERV'!AD12 -> 0 | M7: ='CRONO SERV'!AE12 -> 0 | N7: =SUM(F7:M7) -> 133823.19
B8: 3 | C8: SS-14/2026 | D8: PMBC - 5250-26-100 - ALTERAÇÕES - HAZOP DA U-001 E U-101 | E8: Mecânica | F8: ='CRONO SERV'!X24 -> 7793.8298 | G8: ='CRONO SERV'!Y24 -> 11371.202 | H8: ='CRONO SERV'!Z24 -> 0 | I8: ='CRONO SERV'!AA24 -> 0 | J8: ='CRONO SERV'!AB24 -> 0 | K8: ='CRONO SERV'!AC24 -> 0 | L8: ='CRONO SERV'!AD24 -> 0 | M8: ='CRONO SERV'!AE24 -> 0 | N8: =SUM(F8:M8) -> 19165.032
B9: 4 | C9: SS-36/2026 | D9: Manutenção Civil - Linha do Flare na Av. 8 | E9: Civil | F9: ='CRONO SERV'!X31 -> 117974.19 | G9: ='CRONO SERV'!Y31 -> 73101.436 | H9: ='CRONO SERV'!Z31 -> 89929.793 | I9: ='CRONO SERV'!AA31 -> 0 | J9: ='CRONO SERV'!AB31 -> 0 | K9: ='CRONO SERV'!AC31 -> 0 | L9: ='CRONO SERV'!AD31 -> 0 | M9: ='CRONO SERV'!AE31 -> 0 | N9: =SUM(F9:M9) -> 281005.42
B10: 5 | C10: SS-39/2026 | D10: IN-5250-24-092 - PT-200 - Estrutura Metálica - Fabricação | E10: Mecânica | F10: ='CRONO SERV'!X37 -> 522626.67 | G10: ='CRONO SERV'!Y37 -> 2891867.6 | H10: ='CRONO SERV'!Z37 -> 3553861.4 | I10: ='CRONO SERV'!AA37 -> 592310.23 | J10: ='CRONO SERV'!AB37 -> 0 | K10: ='CRONO SERV'!AC37 -> 0 | L10: ='CRONO SERV'!AD37 -> 0 | M10: ='CRONO SERV'!AE37 -> 0 | N10: =SUM(F10:M10) -> 7560665.9
B11: 6 | C11: SS-44/2026 | D11: IN - 5250-24-085 - Phase-Out do Diesel S500 - Mudança 2.1 - Fabricação (Tubovias) | E11: Mecânica | F11: ='CRONO SERV'!X39 -> 383499.72 | G11: ='CRONO SERV'!Y39 -> 161818.85 | H11: ='CRONO SERV'!Z39 -> 0 | I11: ='CRONO SERV'!AA39 -> 0 | J11: ='CRONO SERV'!AB39 -> 0 | K11: ='CRONO SERV'!AC39 -> 0 | L11: ='CRONO SERV'!AD39 -> 0 | M11: ='CRONO SERV'!AE39 -> 0 | N11: =SUM(F11:M11) -> 545318.56
B12: 7 | C12: SS-45/2026 | D12: IN - 5250-24-085 - Phase-Out do Diesel S500 - Mudança 2.1 - Montagem (Tubovias) | E12: Mecânica | F12: ='CRONO SERV'!X43 -> 128043.83 | G12: ='CRONO SERV'!Y43 -> 161833.33 | H12: ='CRONO SERV'!Z43 -> 679455.25 | I12: ='CRONO SERV'!AA43 -> 853.59637 | J12: ='CRONO SERV'!AB43 -> 0 | K12: ='CRONO SERV'!AC43 -> 0 | L12: ='CRONO SERV'!AD43 -> 0 | M12: ='CRONO SERV'!AE43 -> 0 | N12: =SUM(F12:M12) -> 970186
B13: 8 | C13: SS-60/2025 | D13: IN-5250-25-014 - ETDI - DESARENADOR | E13: Civil | F13: ='CRONO SERV'!X47 -> 81934.92 | G13: ='CRONO SERV'!Y47 -> 0 | H13: ='CRONO SERV'!Z47 -> 0 | I13: ='CRONO SERV'!AA47 -> 0 | J13: ='CRONO SERV'!AB47 -> 0 | K13: ='CRONO SERV'!AC47 -> 0 | L13: ='CRONO SERV'!AD47 -> 0 | M13: ='CRONO SERV'!AE47 -> 0 | N13: =SUM(F13:M13) -> 81934.92
B14: 9 | C14: SS-61/2025 | D14: IN-5250-20-001 - ETDI - REDE CONTAMINADA | E14: Civil | F14: ='CRONO SERV'!X71 -> 1040.7412 | G14: ='CRONO SERV'!Y71 -> 0 | H14: ='CRONO SERV'!Z71 -> 0 | I14: ='CRONO SERV'!AA71 -> 0 | J14: ='CRONO SERV'!AB71 -> 0 | K14: ='CRONO SERV'!AC71 -> 0 | L14: ='CRONO SERV'!AD71 -> 0 | M14: ='CRONO SERV'!AE71 -> 0 | N14: =SUM(F14:M14) -> 1040.7412
B15: 10 | C15: SS-62/2025 | D15: IN - 5250-25-005 - ETDI - FRENTE 01 - BOMBAS DO PPI - ELÉTRICA | E15: Elétrica | F15: ='CRONO SERV'!X89 -> 0 | G15: ='CRONO SERV'!Y89 -> 73329.335 | H15: ='CRONO SERV'!Z89 -> 0 | I15: ='CRONO SERV'!AA89 -> 0 | J15: ='CRONO SERV'!AB89 -> 0 | K15: ='CRONO SERV'!AC89 -> 0 | L15: ='CRONO SERV'!AD89 -> 0 | M15: ='CRONO SERV'!AE89 -> 0 | N15: =SUM(F15:M15) -> 73329.335
B16: 11 | C16: SS-63/2026 | D16: Rede Envelopada - Armazéns S5 x S6 | E16: Civil | F16: ='CRONO SERV'!X121 -> 3242.5638 | G16: ='CRONO SERV'!Y121 -> 112386.9 | H16: ='CRONO SERV'!Z121 -> 83276.543 | I16: ='CRONO SERV'!AA121 -> 97700.247 | J16: ='CRONO SERV'!AB121 -> 0 | K16: ='CRONO SERV'!AC121 -> 0 | L16: ='CRONO SERV'!AD121 -> 0 | M16: ='CRONO SERV'!AE121 -> 0 | N16: =SUM(F16:M16) -> 296606.26
B17: 12 | C17: SS-65/2026 | D17: ATIVIDADE HS - LIMPEZA DE ROTA - ÁREA ETE | E17: Civil | F17: ='CRONO SERV'!X136 -> 0 | G17: ='CRONO SERV'!Y136 -> 0 | H17: ='CRONO SERV'!Z136 -> 0 | I17: ='CRONO SERV'!AA136 -> 179307.06 | J17: ='CRONO SERV'!AB136 -> 44826.766 | K17: ='CRONO SERV'!AC136 -> 0 | L17: ='CRONO SERV'!AD136 -> 0 | M17: ='CRONO SERV'!AE136 -> 0 | N17: =SUM(F17:M17) -> 224133.83
B18: 13 | C18: SS-66/2026 | D18: CALDEIRAS 0121-F-001 ABC - FUNDAÇÃO PARA GRUA | E18: Civil | F18: ='CRONO SERV'!X138 -> 714181.15 | G18: ='CRONO SERV'!Y138 -> 375135.62 | H18: ='CRONO SERV'!Z138 -> 40076.069 | I18: ='CRONO SERV'!AA138 -> 0 | J18: ='CRONO SERV'!AB138 -> 0 | K18: ='CRONO SERV'!AC138 -> 0 | L18: ='CRONO SERV'!AD138 -> 0 | M18: ='CRONO SERV'!AE138 -> 0 | N18: =SUM(F18:M18) -> 1129392.8
B19: 14 | C19: SS-67/2026 | D19: IN-5250-24-062 - Adequações CEM´s - Mudança 1 - U-003 (Instrumentação) | E19: Elétrica | F19: ='CRONO SERV'!X156 -> 14097.133 | G19: ='CRONO SERV'!Y156 -> 0 | H19: ='CRONO SERV'!Z156 -> 0 | I19: ='CRONO SERV'!AA156 -> 0 | J19: ='CRONO SERV'!AB156 -> 0 | K19: ='CRONO SERV'!AC156 -> 0 | L19: ='CRONO SERV'!AD156 -> 0 | M19: ='CRONO SERV'!AE156 -> 0 | N19: =SUM(F19:M19) -> 14097.133
B20: 15 | C20: SS-68 69/2026 | D20: IN-5250-24-062 - Adequações CEM´s - Mudança 2 - U-103 (Elétrica e Instrumentação ) | E20: Elétrica | F20: ='CRONO SERV'!X162 -> 0 | G20: ='CRONO SERV'!Y162 -> 13706.927 | H20: ='CRONO SERV'!Z162 -> 4781.6844 | I20: ='CRONO SERV'!AA162 -> 0 | J20: ='CRONO SERV'!AB162 -> 0 | K20: ='CRONO SERV'!AC162 -> 0 | L20: ='CRONO SERV'!AD162 -> 0 | M20: ='CRONO SERV'!AE162 -> 0 | N20: =SUM(F20:M20) -> 18488.612
B21: 16 | C21: SS-70 71/2026 | D21: IN-5250-24-062 - Adequações CEM´s - Mudança 3 - U-114 (Elétrica e Instrumentação) | E21: Elétrica | F21: ='CRONO SERV'!X171 -> 29525.834 | G21: ='CRONO SERV'!Y171 -> 0 | H21: ='CRONO SERV'!Z171 -> 0 | I21: ='CRONO SERV'!AA171 -> 0 | J21: ='CRONO SERV'!AB171 -> 0 | K21: ='CRONO SERV'!AC171 -> 0 | L21: ='CRONO SERV'!AD171 -> 0 | M21: ='CRONO SERV'!AE171 -> 0 | N21: =SUM(F21:M21) -> 29525.834
B22: 17 | C22: SS-72/2026 | D22: IN-5250-24-062 - Adequações CEM´s - Mudança 4 - U-121 (Instrumentação) | E22: Elétrica | F22: ='CRONO SERV'!X181 -> 0 | G22: ='CRONO SERV'!Y181 -> 0 | H22: ='CRONO SERV'!Z181 -> 30130.966 | I22: ='CRONO SERV'!AA181 -> 0 | J22: ='CRONO SERV'!AB181 -> 0 | K22: ='CRONO SERV'!AC181 -> 0 | L22: ='CRONO SERV'!AD181 -> 0 | M22: ='CRONO SERV'!AE181 -> 0 | N22: =SUM(F22:M22) -> 30130.966
B23: 18 | C23: SS-73/2025 | D23: IN - 5250-20-001 - ETDI - BOMBAS DO PPI - CIVIL | E23: Civil | F23: ='CRONO SERV'!X190 -> 0 | G23: ='CRONO SERV'!Y190 -> 0 | H23: ='CRONO SERV'!Z190 -> 0 | I23: ='CRONO SERV'!AA190 -> 0 | J23: ='CRONO SERV'!AB190 -> 0 | K23: ='CRONO SERV'!AC190 -> 0 | L23: ='CRONO SERV'!AD190 -> 0 | M23: ='CRONO SERV'!AE190 -> 0 | N23: =SUM(F23:M23) -> 0
B24: 19 | C24: SS-74/2025 | D24: IN-5250-25-015 - ETDI - CONTAMINADA FASE 2 - CIVIL | E24: Civil | F24: ='CRONO SERV'!X208 -> 387702.51 | G24: ='CRONO SERV'!Y208 -> 131277.49 | H24: ='CRONO SERV'!Z208 -> 137786.13 | I24: ='CRONO SERV'!AA208 -> 0 | J24: ='CRONO SERV'!AB208 -> 0 | K24: ='CRONO SERV'!AC208 -> 0 | L24: ='CRONO SERV'!AD208 -> 0 | M24: ='CRONO SERV'!AE208 -> 0 | N24: =SUM(F24:M24) -> 656766.13
B25: 20 | C25: SS-79/2026 | D25: UNIDADE 47 - TANQUE DE ÁGUA ÁCIDA | E25: Civil | F25: ='CRONO SERV'!X238 -> 0 | G25: ='CRONO SERV'!Y238 -> 135876.68 | H25: ='CRONO SERV'!Z238 -> 95896.971 | I25: ='CRONO SERV'!AA238 -> 0 | J25: ='CRONO SERV'!AB238 -> 0 | K25: ='CRONO SERV'!AC238 -> 0 | L25: ='CRONO SERV'!AD238 -> 0 | M25: ='CRONO SERV'!AE238 -> 0 | N25: =SUM(F25:M25) -> 231773.66
B26: 21 | C26: SS-80/2026 | D26: FURO DE SONDAGEM - REATOR 110-R-01 | E26: Civil | F26: ='CRONO SERV'!X247 -> 8280.3072 | G26: ='CRONO SERV'!Y247 -> 0 | H26: ='CRONO SERV'!Z247 -> 0 | I26: ='CRONO SERV'!AA247 -> 0 | J26: ='CRONO SERV'!AB247 -> 0 | K26: ='CRONO SERV'!AC247 -> 0 | L26: ='CRONO SERV'!AD247 -> 0 | M26: ='CRONO SERV'!AE247 -> 0 | N26: =SUM(F26:M26) -> 8280.3072
B27: 22 | C27: SS-89/2026 | D27: Manutenção Civil - PÁTIO DE ENXOFRE | E27: Civil | F27: ='CRONO SERV'!X250 -> 0 | G27: ='CRONO SERV'!Y250 -> 116700.07 | H27: ='CRONO SERV'!Z250 -> 277162.67 | I27: ='CRONO SERV'!AA250 -> 320925.2 | J27: ='CRONO SERV'!AB250 -> 364687.72 | K27: ='CRONO SERV'!AC250 -> 379275.23 | L27: ='CRONO SERV'!AD250 -> 0 | M27: ='CRONO SERV'!AE250 -> 0 | N27: =SUM(F27:M27) -> 1458750.9
B28: 23 | C28: SS-90/2026 | D28: Manutenção Civil - CANAL DE PINTADOS | E28: Civil | F28: ='CRONO SERV'!X264 -> 0 | G28: ='CRONO SERV'!Y264 -> 48571.587 | H28: ='CRONO SERV'!Z264 -> 73462.333 | I28: ='CRONO SERV'!AA264 -> 73462.333 | J28: ='CRONO SERV'!AB264 -> 163165.63 | K28: ='CRONO SERV'!AC264 -> 180615.52 | L28: ='CRONO SERV'!AD264 -> 170662.9 | M28: ='CRONO SERV'!AE264 -> 241392.09 | N28: =SUM(F28:M28) -> 951332.39
B29: 24 | C29: SS-94/2025 | D29: IN - 5250-20-001 - ETDI - BOMBAS DO PPI - MECANICA | E29: Mecânica | F29: ='CRONO SERV'!X273 -> 66546.757 | G29: ='CRONO SERV'!Y273 -> 412396.24 | H29: ='CRONO SERV'!Z273 -> 0 | I29: ='CRONO SERV'!AA273 -> 0 | J29: ='CRONO SERV'!AB273 -> 0 | K29: ='CRONO SERV'!AC273 -> 0 | L29: ='CRONO SERV'!AD273 -> 0 | M29: ='CRONO SERV'!AE273 -> 0 | N29: =SUM(F29:M29) -> 478942.99
B30: 25 | C30: SS-96/2026 | D30: CFTV U-47 | E30: Elétrica | F30: ='CRONO SERV'!X288 -> 0 | G30: ='CRONO SERV'!Y288 -> 68735.865 | H30: ='CRONO SERV'!Z288 -> 0 | I30: ='CRONO SERV'!AA288 -> 0 | J30: ='CRONO SERV'!AB288 -> 0 | K30: ='CRONO SERV'!AC288 -> 0 | L30: ='CRONO SERV'!AD288 -> 0 | M30: ='CRONO SERV'!AE288 -> 0 | N30: =SUM(F30:M30) -> 68735.865
B31: 26 | C31: SS-96/2025 | D31: IN - 5250-25-010 - Melhoria acesso bloco K 27-TQ-01 C e D - Montagem | E31: Mecânica | F31: ='CRONO SERV'!X292 -> 0 | G31: ='CRONO SERV'!Y292 -> 116485.25 | H31: ='CRONO SERV'!Z292 -> 275195.52 | I31: ='CRONO SERV'!AA292 -> 112286.56 | J31: ='CRONO SERV'!AB292 -> 95380.335 | K31: ='CRONO SERV'!AC292 -> 0 | L31: ='CRONO SERV'!AD292 -> 0 | M31: ='CRONO SERV'!AE292 -> 0 | N31: =SUM(F31:M31) -> 599347.67
B32: 27 | C32: SS-97/2025 | D32: IN - 5250-25-011 - Melhoria acesso bloco P 27-TQ-01 K e M - Montagem | E32: Mecânica | F32: ='CRONO SERV'!X316 -> 0 | G32: ='CRONO SERV'!Y316 -> 24765.26 | H32: ='CRONO SERV'!Z316 -> 134793.79 | I32: ='CRONO SERV'!AA316 -> 459613.19 | J32: ='CRONO SERV'!AB316 -> 383545.18 | K32: ='CRONO SERV'!AC316 -> 0 | L32: ='CRONO SERV'!AD316 -> 0 | M32: ='CRONO SERV'!AE316 -> 0 | N32: =SUM(F32:M32) -> 1002717.4
B33: 28 | C33: SS-98/2025 | D33: IN - 5250-25-011 - Melhoria acesso bloco P 27-TQ-01 K e M - Montagem | E33: Mecânica | F33: ='CRONO SERV'!X340 -> 0 | G33: ='CRONO SERV'!Y340 -> 16780.5 | H33: ='CRONO SERV'!Z340 -> 53447.384 | I33: ='CRONO SERV'!AA340 -> 328544.1 | J33: ='CRONO SERV'!AB340 -> 341309.25 | K33: ='CRONO SERV'!AC340 -> 0 | L33: ='CRONO SERV'!AD340 -> 0 | M33: ='CRONO SERV'!AE340 -> 0 | N33: =SUM(F33:M33) -> 740081.24
B34: 29 | C34: SS-166/2025 | D34: IN - 5250-25-010 - Melhoria acesso bloco K 27-TQ-01 E - Montagem | E34: Mecânica | F34: ='CRONO SERV'!X363 -> 13537.891 | G34: ='CRONO SERV'!Y363 -> 128622.07 | H34: ='CRONO SERV'!Z363 -> 63410.07 | I34: ='CRONO SERV'!AA363 -> 90250.366 | J34: ='CRONO SERV'!AB363 -> 104792.77 | K34: ='CRONO SERV'!AC363 -> 0 | L34: ='CRONO SERV'!AD363 -> 0 | M34: ='CRONO SERV'!AE363 -> 0 | N34: =SUM(F34:M34) -> 400613.17
B35: 30 | C35: SS-100/2025 | D35: IN - 5250-24-051 - Melhoria do Acesso aos TQ´s de Escuros 27-TQ-116-A/B - Montagem | E35: Mecânica | F35: ='CRONO SERV'!X386 -> 4200.906 | G35: ='CRONO SERV'!Y386 -> 128688.32 | H35: ='CRONO SERV'!Z386 -> 148091.72 | I35: ='CRONO SERV'!AA386 -> 19342.555 | J35: ='CRONO SERV'!AB386 -> 0 | K35: ='CRONO SERV'!AC386 -> 0 | L35: ='CRONO SERV'!AD386 -> 0 | M35: ='CRONO SERV'!AE386 -> 0 | N35: =SUM(F35:M35) -> 300323.5
B36: 31 | C36: SS-171/2025 | D36: IN - 5250-24-051 - Melhoria do Acesso aos TQ´s de Escuros 27-TQ-116-D/F - Montagem | E36: Mecânica | F36: ='CRONO SERV'!X407 -> 0 | G36: ='CRONO SERV'!Y407 -> 8229.0379 | H36: ='CRONO SERV'!Z407 -> 96757.408 | I36: ='CRONO SERV'!AA407 -> 188266.34 | J36: ='CRONO SERV'!AB407 -> 14727.931 | K36: ='CRONO SERV'!AC407 -> 0 | L36: ='CRONO SERV'!AD407 -> 0 | M36: ='CRONO SERV'!AE407 -> 0 | N36: =SUM(F36:M36) -> 307980.72
B37: 32 | C37: SS-172/2025 | D37: IN - 5250-24-051 - Melhoria do Acesso aos TQ´s de Escuros 27-TQ-116-D/F - Montagem | E37: Mecânica | F37: ='CRONO SERV'!X429 -> 0 | G37: ='CRONO SERV'!Y429 -> 6398.3081 | H37: ='CRONO SERV'!Z429 -> 72918.187 | I37: ='CRONO SERV'!AA429 -> 220615.3 | J37: ='CRONO SERV'!AB429 -> 26144.015 | K37: ='CRONO SERV'!AC429 -> 19085.006 | L37: ='CRONO SERV'!AD429 -> 0 | M37: ='CRONO SERV'!AE429 -> 0 | N37: =SUM(F37:M37) -> 345160.82
B38: 33 | C38: SS-103/2026 | D38: PMBC MIGRAÇÃO DAS BOMBAS DA U-0047 PARA O SDCD | E38: Elétrica | F38: ='CRONO SERV'!X451 -> 17135.817 | G38: ='CRONO SERV'!Y451 -> 23779.132 | H38: ='CRONO SERV'!Z451 -> 0 | I38: ='CRONO SERV'!AA451 -> 0 | J38: ='CRONO SERV'!AB451 -> 0 | K38: ='CRONO SERV'!AC451 -> 0 | L38: ='CRONO SERV'!AD451 -> 0 | M38: ='CRONO SERV'!AE451 -> 0 | N38: =SUM(F38:M38) -> 40914.949
B39: 34 | C39: SS-109/2026 | D39: IN - 5250-24-085 - Phase-Out do Diesel S500 - Mudança 4.1 - Fabricação (Tubovias) | E39: Mecânica | F39: ='CRONO SERV'!X459 -> 103605.84 | G39: ='CRONO SERV'!Y459 -> 309293.64 | H39: ='CRONO SERV'!Z459 -> 161818.85 | I39: ='CRONO SERV'!AA459 -> 0 | J39: ='CRONO SERV'!AB459 -> 0 | K39: ='CRONO SERV'!AC459 -> 0 | L39: ='CRONO SERV'!AD459 -> 0 | M39: ='CRONO SERV'!AE459 -> 0 | N39: =SUM(F39:M39) -> 574718.32
B40: 35 | C40: SS-110/2026 | D40: IN - 5250-24-085 - Phase-Out do Diesel S500 - Mudança 4.1 - Montagem (Tubovias) | E40: Mecânica | F40: ='CRONO SERV'!X463 -> 153566.31 | G40: ='CRONO SERV'!Y463 -> 429735.64 | H40: ='CRONO SERV'!Z463 -> 447774.83 | I40: ='CRONO SERV'!AA463 -> 117679.34 | J40: ='CRONO SERV'!AB463 -> 0 | K40: ='CRONO SERV'!AC463 -> 18924.675 | L40: ='CRONO SERV'!AD463 -> 0 | M40: ='CRONO SERV'!AE463 -> 0 | N40: =SUM(F40:M40) -> 1167680.8
B41: 36 | C41: SS-123/2026 | D41: IN-5250-23-017 - TERRAPLANAGEM U-623 | E41: Civil | F41: ='CRONO SERV'!X468 -> 0 | G41: ='CRONO SERV'!Y468 -> 354277.69 | H41: ='CRONO SERV'!Z468 -> 0 | I41: ='CRONO SERV'!AA468 -> 0 | J41: ='CRONO SERV'!AB468 -> 0 | K41: ='CRONO SERV'!AC468 -> 0 | L41: ='CRONO SERV'!AD468 -> 0 | M41: ='CRONO SERV'!AE468 -> 0 | N41: =SUM(F41:M41) -> 354277.69
B42: 37 | C42: SS-125/2026 | D42: U-110 - DEMOLIÇÃO FUNDAÇÃO - 110-R-01 | E42: Civil | F42: ='CRONO SERV'!X473 -> 4245.9956 | G42: ='CRONO SERV'!Y473 -> 0 | H42: ='CRONO SERV'!Z473 -> 0 | I42: ='CRONO SERV'!AA473 -> 0 | J42: ='CRONO SERV'!AB473 -> 0 | K42: ='CRONO SERV'!AC473 -> 0 | L42: ='CRONO SERV'!AD473 -> 0 | M42: ='CRONO SERV'!AE473 -> 0 | N42: =SUM(F42:M42) -> 4245.9956
B43: 38 | C43: SS-126/2026 | D43: U-110 - CONSTRUÇÃO FUNDAÇÃO - 110-R-01 | E43: Civil | F43: ='CRONO SERV'!X477 -> 125265.09 | G43: ='CRONO SERV'!Y477 -> 67761.412 | H43: ='CRONO SERV'!Z477 -> 89289.226 | I43: ='CRONO SERV'!AA477 -> 0 | J43: ='CRONO SERV'!AB477 -> 0 | K43: ='CRONO SERV'!AC477 -> 0 | L43: ='CRONO SERV'!AD477 -> 0 | M43: ='CRONO SERV'!AE477 -> 0 | N43: =SUM(F43:M43) -> 282315.73
B44: 39 | C44: SS-130/2026 | D44: U-623 - RELOCAÇÃO TUBULAÇÃO SELAGEM - FABRICAÇÃO | E44: Mecânica | F44: ='CRONO SERV'!X495 -> 0 | G44: ='CRONO SERV'!Y495 -> 61003.157 | H44: ='CRONO SERV'!Z495 -> 0 | I44: ='CRONO SERV'!AA495 -> 0 | J44: ='CRONO SERV'!AB495 -> 0 | K44: ='CRONO SERV'!AC495 -> 0 | L44: ='CRONO SERV'!AD495 -> 0 | M44: ='CRONO SERV'!AE495 -> 0 | N44: =SUM(F44:M44) -> 61003.157
B45: 40 | C45: SS-131/2026 | D45: U-623 - RELOCAÇÃO TUBULAÇÃO SELAGEM - MONTAGEM | E45: Mecânica | F45: ='CRONO SERV'!X498 -> 0 | G45: ='CRONO SERV'!Y498 -> 0 | H45: ='CRONO SERV'!Z498 -> 157888.59 | I45: ='CRONO SERV'!AA498 -> 0 | J45: ='CRONO SERV'!AB498 -> 0 | K45: ='CRONO SERV'!AC498 -> 0 | L45: ='CRONO SERV'!AD498 -> 0 | M45: ='CRONO SERV'!AE498 -> 0 | N45: =SUM(F45:M45) -> 157888.59
B46: 41 | C46: SS-132/2025 | D46: Envelope Elétrico GPI | E46: Elétrica | F46: ='CRONO SERV'!X503 -> 72499.594 | G46: ='CRONO SERV'!Y503 -> 115455.84 | H46: ='CRONO SERV'!Z503 -> 250544.18 | I46: ='CRONO SERV'!AA503 -> 383268.83 | J46: ='CRONO SERV'!AB503 -> 30010.34 | K46: ='CRONO SERV'!AC503 -> 0 | L46: ='CRONO SERV'!AD503 -> 0 | M46: ='CRONO SERV'!AE503 -> 0 | N46: =SUM(F46:M46) -> 851778.79
B47: 42 | C47: SS-132/2026 | D47: U-623 - RELOCAÇÃO TUBULAÇÃO RACE - FABRICAÇÃO | E47: Mecânica | F47: ='CRONO SERV'!X534 -> 0 | G47: ='CRONO SERV'!Y534 -> 0 | H47: ='CRONO SERV'!Z534 -> 150194.52 | I47: ='CRONO SERV'!AA534 -> 55809.037 | J47: ='CRONO SERV'!AB534 -> 0 | K47: ='CRONO SERV'!AC534 -> 0 | L47: ='CRONO SERV'!AD534 -> 0 | M47: ='CRONO SERV'!AE534 -> 0 | N47: =SUM(F47:M47) -> 206003.56
B48: 43 | C48: SS-133/2026 | D48: U-623 - RELOCAÇÃO TUBULAÇÃO RACE - MONTAGEM | E48: Mecânica | F48: ='CRONO SERV'!X539 -> 0 | G48: ='CRONO SERV'!Y539 -> 0 | H48: ='CRONO SERV'!Z539 -> 0 | I48: ='CRONO SERV'!AA539 -> 0 | J48: ='CRONO SERV'!AB539 -> 486430.25 | K48: ='CRONO SERV'!AC539 -> 201977.77 | L48: ='CRONO SERV'!AD539 -> 0 | M48: ='CRONO SERV'!AE539 -> 0 | N48: =SUM(F48:M48) -> 688408.02
B49: 44 | C49: SS-135/2026 | D49: UN-623 - PONTILHÃO (AVENIDA "D") - CIVIL | E49: Civil | F49: ='CRONO SERV'!X549 -> 0 | G49: ='CRONO SERV'!Y549 -> 4465.5768 | H49: ='CRONO SERV'!Z549 -> 162607.83 | I49: ='CRONO SERV'!AA549 -> 237979.12 | J49: ='CRONO SERV'!AB549 -> 4533.2862 | K49: ='CRONO SERV'!AC549 -> 0 | L49: ='CRONO SERV'!AD549 -> 0 | M49: ='CRONO SERV'!AE549 -> 0 | N49: =SUM(F49:M49) -> 409585.81
B50: 45 | C50: SS-136/2026 | D50: UN-623 - CASA DE QUÍMICOS - CIVIL | E50: Civil | F50: ='CRONO SERV'!X564 -> 0 | G50: ='CRONO SERV'!Y564 -> 0 | H50: ='CRONO SERV'!Z564 -> 0 | I50: ='CRONO SERV'!AA564 -> 16016.43 | J50: ='CRONO SERV'!AB564 -> 44189.939 | K50: ='CRONO SERV'!AC564 -> 109176.05 | L50: ='CRONO SERV'!AD564 -> 7214.5899 | M50: ='CRONO SERV'!AE564 -> 0 | N50: =SUM(F50:M50) -> 176597
B51: 46 | C51: SS-137/2026 | D51: UN-623 - CASA DE QUÍMICOS - ESTRUTURA METÁLICA | E51: Mecânica | F51: ='CRONO SERV'!X577 -> 0 | G51: ='CRONO SERV'!Y577 -> 0 | H51: ='CRONO SERV'!Z577 -> 0 | I51: ='CRONO SERV'!AA577 -> 168655.11 | J51: ='CRONO SERV'!AB577 -> 0 | K51: ='CRONO SERV'!AC577 -> 0 | L51: ='CRONO SERV'!AD577 -> 118287.94 | M51: ='CRONO SERV'!AE577 -> 0 | N51: =SUM(F51:M51) -> 286943.05
B52: 47 | C52: SS-138/2026 | D52: UN-623 - PONTILHÃO (AVENIDA "D") - MECÂNICA | E52: Civil | F52: ='CRONO SERV'!X580 -> 0 | G52: ='CRONO SERV'!Y580 -> 100855.09 | H52: ='CRONO SERV'!Z580 -> 0 | I52: ='CRONO SERV'!AA580 -> 0 | J52: ='CRONO SERV'!AB580 -> 0 | K52: ='CRONO SERV'!AC580 -> 0 | L52: ='CRONO SERV'!AD580 -> 0 | M52: ='CRONO SERV'!AE580 -> 0 | N52: =SUM(F52:M52) -> 100855.09
B53: 48 | C53: SS-148/2025 | D53: IN - 5250-24-075 - Substituição PLC ALTUS CP4 | E53: Elétrica | F53: ='CRONO SERV'!X583 -> 19753.104 | G53: ='CRONO SERV'!Y583 -> 35281.44 | H53: ='CRONO SERV'!Z583 -> 0 | I53: ='CRONO SERV'!AA583 -> 0 | J53: ='CRONO SERV'!AB583 -> 0 | K53: ='CRONO SERV'!AC583 -> 0 | L53: ='CRONO SERV'!AD583 -> 0 | M53: ='CRONO SERV'!AE583 -> 0 | N53: =SUM(F53:M53) -> 55034.544
B54: 49 | C54: SS-157/2026 | D54: IN-5250-23-014 - Novo Laboratório de Integridade da IE - Elétrica | E54: Elétrica | F54: ='CRONO SERV'!X621 -> 0 | G54: ='CRONO SERV'!Y621 -> 141473.59 | H54: ='CRONO SERV'!Z621 -> 0 | I54: ='CRONO SERV'!AA621 -> 0 | J54: ='CRONO SERV'!AB621 -> 0 | K54: ='CRONO SERV'!AC621 -> 0 | L54: ='CRONO SERV'!AD621 -> 0 | M54: ='CRONO SERV'!AE621 -> 0 | N54: =SUM(F54:M54) -> 141473.59
B55: 50 | C55: SS-154/2026 | D55: Escaneamento Laser U-0047 | E55: Civil | F55: ='CRONO SERV'!X633 -> 351728.06 | G55: ='CRONO SERV'!Y633 -> 0 | H55: ='CRONO SERV'!Z633 -> 0 | I55: ='CRONO SERV'!AA633 -> 0 | J55: ='CRONO SERV'!AB633 -> 0 | K55: ='CRONO SERV'!AC633 -> 0 | L55: ='CRONO SERV'!AD633 -> 0 | M55: ='CRONO SERV'!AE633 -> 0 | N55: =SUM(F55:M55) -> 351728.06
B56: 51 | C56: SS-158/2026 | D56: IN-5250-23-014 - Novo Laboratório de Integridade da IE - Civil - Hidrossanitário | E56: Civil | F56: ='CRONO SERV'!X636 -> 27782.308 | G56: ='CRONO SERV'!Y636 -> 0 | H56: ='CRONO SERV'!Z636 -> 0 | I56: ='CRONO SERV'!AA636 -> 851.93412 | J56: ='CRONO SERV'!AB636 -> 8564.2755 | K56: ='CRONO SERV'!AC636 -> 0 | L56: ='CRONO SERV'!AD636 -> 0 | M56: ='CRONO SERV'!AE636 -> 0 | N56: =SUM(F56:M56) -> 37198.518
B57: 52 | C57: SS-160/2026 | D57: IN-5250-23-014 - Novo Laboratório de Integridade da IE -Arquitetura e SPCI | E57: Civil | F57: ='CRONO SERV'!X647 -> 0 | G57: ='CRONO SERV'!Y647 -> 0 | H57: ='CRONO SERV'!Z647 -> 2182.3557 | I57: ='CRONO SERV'!AA647 -> 500292.81 | J57: ='CRONO SERV'!AB647 -> 84852.378 | K57: ='CRONO SERV'!AC647 -> 0 | L57: ='CRONO SERV'!AD647 -> 0 | M57: ='CRONO SERV'!AE647 -> 0 | N57: =SUM(F57:M57) -> 587327.54
B58: 53 | C58: SS-162/2026 | D58: DRENAGEM - ESCADA ADUTORA UFV | E58: Civil | F58: ='CRONO SERV'!X663 -> 0 | G58: ='CRONO SERV'!Y663 -> 0 | H58: ='CRONO SERV'!Z663 -> 3357.2636 | I58: ='CRONO SERV'!AA663 -> 99333.096 | J58: ='CRONO SERV'!AB663 -> 1093.9921 | K58: ='CRONO SERV'!AC663 -> 0 | L58: ='CRONO SERV'!AD663 -> 0 | M58: ='CRONO SERV'!AE663 -> 0 | N58: =SUM(F58:M58) -> 103784.35
B59: 54 | C59: SS-163/2026 | D59: OFICINA ED - BASE MANDRILHADORA | E59: Civil | F59: ='CRONO SERV'!X679 -> 0 | G59: ='CRONO SERV'!Y679 -> 0 | H59: ='CRONO SERV'!Z679 -> 88306.27 | I59: ='CRONO SERV'!AA679 -> 8268.6433 | J59: ='CRONO SERV'!AB679 -> 0 | K59: ='CRONO SERV'!AC679 -> 0 | L59: ='CRONO SERV'!AD679 -> 0 | M59: ='CRONO SERV'!AE679 -> 0 | N59: =SUM(F59:M59) -> 96574.914
B60: 55 | C60: SS-187/2026 | D60: SIT EBD - PRÉ FUROS - FUNDAÇÃO DO PIPE-RAK | E60: Civil | F60: ='CRONO SERV'!X718 -> 0 | G60: ='CRONO SERV'!Y718 -> 11348.22 | H60: ='CRONO SERV'!Z718 -> 0 | I60: ='CRONO SERV'!AA718 -> 0 | J60: ='CRONO SERV'!AB718 -> 0 | K60: ='CRONO SERV'!AC718 -> 0 | L60: ='CRONO SERV'!AD718 -> 0 | M60: ='CRONO SERV'!AE718 -> 0 | N60: =SUM(F60:M60) -> 11348.22
B61: 56 | C61: SS-198/2026 | D61: SIT EBD - PRÉ FUROS - FUNDAÇÃO DO CABLE-RACK | E61: Civil | F61: ='CRONO SERV'!X724 -> 15293.915 | G61: ='CRONO SERV'!Y724 -> 0 | H61: ='CRONO SERV'!Z724 -> 0 | I61: ='CRONO SERV'!AA724 -> 0 | J61: ='CRONO SERV'!AB724 -> 0 | K61: ='CRONO SERV'!AC724 -> 0 | L61: ='CRONO SERV'!AD724 -> 0 | M61: ='CRONO SERV'!AE724 -> 0 | N61: =SUM(F61:M61) -> 15293.915
B62: 57 | C62: SS-199/2026 | D62: SIT EBD - PRÉ FUROS - PLATAFORMAS PERMUTADORES | E62: Civil | F62: ='CRONO SERV'!X730 -> 0 | G62: ='CRONO SERV'!Y730 -> 16742.406 | H62: ='CRONO SERV'!Z730 -> 0 | I62: ='CRONO SERV'!AA730 -> 0 | J62: ='CRONO SERV'!AB730 -> 0 | K62: ='CRONO SERV'!AC730 -> 0 | L62: ='CRONO SERV'!AD730 -> 0 | M62: ='CRONO SERV'!AE730 -> 0 | N62: =SUM(F62:M62) -> 16742.406
B63: 58 | C63: SS-228/2025 | D63: IN - 5250-17-007 - MODERNIZAÇÃO TURBO EXPANSOR 103-TG-01 - ELÉTRICA | E63: Elétrica | F63: ='CRONO SERV'!X736 -> 0 | G63: ='CRONO SERV'!Y736 -> 169819 | H63: ='CRONO SERV'!Z736 -> 157850.89 | I63: ='CRONO SERV'!AA736 -> 0 | J63: ='CRONO SERV'!AB736 -> 0 | K63: ='CRONO SERV'!AC736 -> 0 | L63: ='CRONO SERV'!AD736 -> 0 | M63: ='CRONO SERV'!AE736 -> 0 | N63: =SUM(F63:M63) -> 327669.89
D64: TOTAL OBRAS - SERVIÇOS | F64: =SUM(F6:F63) -> 3469594.7 | G64: =SUM(G6:G63) -> 7129677.9 | H64: =SUM(H6:H63) -> 7604774.5 | I64: =SUM(I6:I63) -> 4299492.3 | J64: =SUM(J6:J63) -> 2224929.3 | K64: =SUM(K6:K63) -> 935454.48 | L64: =SUM(L6:L63) -> 296165.43 | M64: =SUM(M6:M63) -> 241392.09 | N64: =SUBTOTAL(9,N6:N63) -> 26201481
B65: 1 | C65: - | D65: Manutenção Civil - Rotina | E65: Civil | F65: 350000 | G65: 350000 | H65: 350000 | I65: 350000 | J65: 350000 | K65: 350000 | L65: 350000 | M65: 350000 | N65: =SUM(F65:M65) -> 2800000
B66: 2 | C66: - | D66: Parcela Fixa Gestão | E66: Gestão | F66: 1198056 | G66: 1198056 | H66: 1198056 | I66: 1198056 | J66: 1198056 | K66: 1198056 | L66: 1198056 | M66: 1198056 | N66: =SUM(F66:M66) -> 9584448
B67: 3 | C67: - | D67: Serviços De Apoio E Movimentação De Carga | E67: Equipamentos | F67: ='PREV. MENSAL MAIO26'!$AK$3 -> 2120004.8 | G67: ='PREV. MENSAL MAIO26'!$AK$3 -> 2120004.8 | H67: ='PREV. MENSAL MAIO26'!$AK$3 -> 2120004.8 | I67: ='PREV. MENSAL MAIO26'!$AK$3 -> 2120004.8 | J67: ='PREV. MENSAL MAIO26'!$AK$3 -> 2120004.8 | K67: ='PREV. MENSAL MAIO26'!$AK$3 -> 2120004.8 | L67: ='PREV. MENSAL MAIO26'!$AK$3 -> 2120004.8 | M67: ='PREV. MENSAL MAIO26'!$AK$3 -> 2120004.8 | N67: =SUM(F67:M67) -> 16960038
B68: 4 | C68: - | D68: Projetistas | E68: Projestos | F68: 43402.17 | G68: 43402.17 | H68: 43402.17 | I68: 43402.17 | J68: 43402.17 | K68: 43402.17 | L68: 43402.17 | M68: 43402.17 | N68: =SUM(F68:M68) -> 347217.36
B69: 5 | C69: - | D69: Monitoramento de barragens | E69: Civil | F69: 63562.188 | G69: 63562.188 | H69: 63562.188 | I69: 63562.188 | J69: 63562.188 | K69: 63562.188 | L69: 63562.188 | M69: 63562.188 | N69: =SUM(F69:M69) -> 508497.5
D71: TOTAL ROTINAS | F71: =SUM(F65:F70) -> 3775025.1 | G71: =SUM(G65:G70) -> 3775025.1 | H71: =SUM(H65:H70) -> 3775025.1 | I71: =SUM(I65:I70) -> 3775025.1 | J71: =SUM(J65:J70) -> 3775025.1 | K71: =SUM(K65:K70) -> 3775025.1 | L71: =SUM(L65:L70) -> 3775025.1 | M71: =SUM(M65:M70) -> 3775025.1 | N71: =SUBTOTAL(9,N8:N69) -> 56133422
B72: 1 | C72: SS-111/2026 | D72: IN - 5250-24-051 - Melhoria do Acesso aos TQ´s de Escuros 27-TQ-116-A/B/C/D/E/F - Detalhamento - Projeto Mecânica | E72: Projetos | F72: =SUMIF('CRONO PROJETOS_TOPO'!$B:$B,'RESUMO CRON FINANC'!$C72,'CRONO PROJETOS_TOPO'!Z:Z) -> 0 | G72: =SUMIF('CRONO PROJETOS_TOPO'!$B:$B,'RESUMO CRON FINANC'!$C72,'CRONO PROJETOS_TOPO'!AA:AA) -> 0 | H72: =SUMIF('CRONO PROJETOS_TOPO'!$B:$B,'RESUMO CRON FINANC'!$C72,'CRONO PROJETOS_TOPO'!AB:AB) -> 207705.3 | I72: =SUMIF('CRONO PROJETOS_TOPO'!$B:$B,'RESUMO CRON FINANC'!$C72,'CRONO PROJETOS_TOPO'!AC:AC) -> 0 | J72: =SUMIF('CRONO PROJETOS_TOPO'!$B:$B,'RESUMO CRON FINANC'!$C72,'CRONO PROJETOS_TOPO'!AD:AD) -> 0 | K72: =SUMIF('CRONO PROJETOS_TOPO'!$B:$B,'RESUMO CRON FINANC'!$C72,'CRONO PROJETOS_TOPO'!AE:AE) -> 0 | L72: =SUMIF('CRONO PROJETOS_TOPO'!$B:$B,'RESUMO CRON FINANC'!$C72,'CRONO PROJETOS_TOPO'!AF:AF) -> 0 | M72: =SUMIF('CRONO PROJETOS_TOPO'!$B:$B,'RESUMO CRON FINANC'!$C72,'CRONO PROJETOS_TOPO'!AG:AG) -> 0 | N72: =SUM(F72:M72) -> 207705.3
B73: 2 | C73: SS-112/2026 | D73: IN - 5250-24-051 - Melhoria do Acesso aos TQ´s de Escuros 27-TQ-116-A/B/C/D/E/F - Detalhamento - Projeto Civil | E73: Projetos | F73: =SUMIF('CRONO PROJETOS_TOPO'!$B:$B,'RESUMO CRON FINANC'!$C73,'CRONO PROJETOS_TOPO'!Z:Z) -> 22374 | G73: =SUMIF('CRONO PROJETOS_TOPO'!$B:$B,'RESUMO CRON FINANC'!$C73,'CRONO PROJETOS_TOPO'!AA:AA) -> 37290 | H73: =SUMIF('CRONO PROJETOS_TOPO'!$B:$B,'RESUMO CRON FINANC'!$C73,'CRONO PROJETOS_TOPO'!AB:AB) -> 38781.6 | I73: =SUMIF('CRONO PROJETOS_TOPO'!$B:$B,'RESUMO CRON FINANC'!$C73,'CRONO PROJETOS_TOPO'!AC:AC) -> 0 | J73: =SUMIF('CRONO PROJETOS_TOPO'!$B:$B,'RESUMO CRON FINANC'!$C73,'CRONO PROJETOS_TOPO'!AD:AD) -> 0 | K73: =SUMIF('CRONO PROJETOS_TOPO'!$B:$B,'RESUMO CRON FINANC'!$C73,'CRONO PROJETOS_TOPO'!AE:AE) -> 0 | L73: =SUMIF('CRONO PROJETOS_TOPO'!$B:$B,'RESUMO CRON FINANC'!$C73,'CRONO PROJETOS_TOPO'!AF:AF) -> 0 | M73: =SUMIF('CRONO PROJETOS_TOPO'!$B:$B,'RESUMO CRON FINANC'!$C73,'CRONO PROJETOS_TOPO'!AG:AG) -> 0 | N73: =SUM(F73:M73) -> 98445.6
B74: 3 | C74: SS-113/2026 | D74: IN - 5250-24-051 - Melhoria do Acesso aos TQ´s de Escuros 27-TQ-116-A/B/C/D/E/F - Detalhamento - Projeto Elétrica | E74: Projetos | F74: =SUMIF('CRONO PROJETOS_TOPO'!$B:$B,'RESUMO CRON FINANC'!$C74,'CRONO PROJETOS_TOPO'!Z:Z) -> 0 | G74: =SUMIF('CRONO PROJETOS_TOPO'!$B:$B,'RESUMO CRON FINANC'!$C74,'CRONO PROJETOS_TOPO'!AA:AA) -> 0 | H74: =SUMIF('CRONO PROJETOS_TOPO'!$B:$B,'RESUMO CRON FINANC'!$C74,'CRONO PROJETOS_TOPO'!AB:AB) -> 56755.38 | I74: =SUMIF('CRONO PROJETOS_TOPO'!$B:$B,'RESUMO CRON FINANC'!$C74,'CRONO PROJETOS_TOPO'!AC:AC) -> 0 | J74: =SUMIF('CRONO PROJETOS_TOPO'!$B:$B,'RESUMO CRON FINANC'!$C74,'CRONO PROJETOS_TOPO'!AD:AD) -> 0 | K74: =SUMIF('CRONO PROJETOS_TOPO'!$B:$B,'RESUMO CRON FINANC'!$C74,'CRONO PROJETOS_TOPO'!AE:AE) -> 0 | L74: =SUMIF('CRONO PROJETOS_TOPO'!$B:$B,'RESUMO CRON FINANC'!$C74,'CRONO PROJETOS_TOPO'!AF:AF) -> 0 | M74: =SUMIF('CRONO PROJETOS_TOPO'!$B:$B,'RESUMO CRON FINANC'!$C74,'CRONO PROJETOS_TOPO'!AG:AG) -> 0 | N74: =SUM(F74:M74) -> 56755.38
B75: 4 | C75: SS-114/2026 | D75: IN - 5250-25-010 - Melhoria acesso bloco K 27-TQ-01C, D e E - Detalhamento - Projeto Mecânica | E75: Projetos | F75: =SUMIF('CRONO PROJETOS_TOPO'!$B:$B,'RESUMO CRON FINANC'!$C75,'CRONO PROJETOS_TOPO'!Z:Z) -> 0 | G75: =SUMIF('CRONO PROJETOS_TOPO'!$B:$B,'RESUMO CRON FINANC'!$C75,'CRONO PROJETOS_TOPO'!AA:AA) -> 0 | H75: =SUMIF('CRONO PROJETOS_TOPO'!$B:$B,'RESUMO CRON FINANC'!$C75,'CRONO PROJETOS_TOPO'!AB:AB) -> 0 | I75: =SUMIF('CRONO PROJETOS_TOPO'!$B:$B,'RESUMO CRON FINANC'!$C75,'CRONO PROJETOS_TOPO'!AC:AC) -> 208824 | J75: =SUMIF('CRONO PROJETOS_TOPO'!$B:$B,'RESUMO CRON FINANC'!$C75,'CRONO PROJETOS_TOPO'!AD:AD) -> 0 | K75: =SUMIF('CRONO PROJETOS_TOPO'!$B:$B,'RESUMO CRON FINANC'!$C75,'CRONO PROJETOS_TOPO'!AE:AE) -> 0 | L75: =SUMIF('CRONO PROJETOS_TOPO'!$B:$B,'RESUMO CRON FINANC'!$C75,'CRONO PROJETOS_TOPO'!AF:AF) -> 0 | M75: =SUMIF('CRONO PROJETOS_TOPO'!$B:$B,'RESUMO CRON FINANC'!$C75,'CRONO PROJETOS_TOPO'!AG:AG) -> 0 | N75: =SUM(F75:M75) -> 208824
B76: 5 | C76: SS-115/2026 | D76: IN - 5250-25-010 - Melhoria acesso bloco K 27-TQ-01C, D e E - Detalhamento - Projeto Civil | E76: Projetos | F76: =SUMIF('CRONO PROJETOS_TOPO'!$B:$B,'RESUMO CRON FINANC'!$C76,'CRONO PROJETOS_TOPO'!Z:Z) -> 14916 | G76: =SUMIF('CRONO PROJETOS_TOPO'!$B:$B,'RESUMO CRON FINANC'!$C76,'CRONO PROJETOS_TOPO'!AA:AA) -> 34306.8 | H76: =SUMIF('CRONO PROJETOS_TOPO'!$B:$B,'RESUMO CRON FINANC'!$C76,'CRONO PROJETOS_TOPO'!AB:AB) -> 0 | I76: =SUMIF('CRONO PROJETOS_TOPO'!$B:$B,'RESUMO CRON FINANC'!$C76,'CRONO PROJETOS_TOPO'!AC:AC) -> 0 | J76: =SUMIF('CRONO PROJETOS_TOPO'!$B:$B,'RESUMO CRON FINANC'!$C76,'CRONO PROJETOS_TOPO'!AD:AD) -> 0 | K76: =SUMIF('CRONO PROJETOS_TOPO'!$B:$B,'RESUMO CRON FINANC'!$C76,'CRONO PROJETOS_TOPO'!AE:AE) -> 0 | L76: =SUMIF('CRONO PROJETOS_TOPO'!$B:$B,'RESUMO CRON FINANC'!$C76,'CRONO PROJETOS_TOPO'!AF:AF) -> 0 | M76: =SUMIF('CRONO PROJETOS_TOPO'!$B:$B,'RESUMO CRON FINANC'!$C76,'CRONO PROJETOS_TOPO'!AG:AG) -> 0 | N76: =SUM(F76:M76) -> 49222.8
B77: 6 | C77: SS-116/2026 | D77: IN - 5250-25-010 - Melhoria acesso bloco K 27-TQ-01C, D e E - Detalhamento - Projeto Elétrica | E77: Projetos | F77: =SUMIF('CRONO PROJETOS_TOPO'!$B:$B,'RESUMO CRON FINANC'!$C77,'CRONO PROJETOS_TOPO'!Z:Z) -> 0 | G77: =SUMIF('CRONO PROJETOS_TOPO'!$B:$B,'RESUMO CRON FINANC'!$C77,'CRONO PROJETOS_TOPO'!AA:AA) -> 0 | H77: =SUMIF('CRONO PROJETOS_TOPO'!$B:$B,'RESUMO CRON FINANC'!$C77,'CRONO PROJETOS_TOPO'!AB:AB) -> 0 | I77: =SUMIF('CRONO PROJETOS_TOPO'!$B:$B,'RESUMO CRON FINANC'!$C77,'CRONO PROJETOS_TOPO'!AC:AC) -> 28340.4 | J77: =SUMIF('CRONO PROJETOS_TOPO'!$B:$B,'RESUMO CRON FINANC'!$C77,'CRONO PROJETOS_TOPO'!AD:AD) -> 0 | K77: =SUMIF('CRONO PROJETOS_TOPO'!$B:$B,'RESUMO CRON FINANC'!$C77,'CRONO PROJETOS_TOPO'!AE:AE) -> 0 | L77: =SUMIF('CRONO PROJETOS_TOPO'!$B:$B,'RESUMO CRON FINANC'!$C77,'CRONO PROJETOS_TOPO'!AF:AF) -> 0 | M77: =SUMIF('CRONO PROJETOS_TOPO'!$B:$B,'RESUMO CRON FINANC'!$C77,'CRONO PROJETOS_TOPO'!AG:AG) -> 0 | N77: =SUM(F77:M77) -> 28340.4
B78: 7 | C78: SS-117/2026 | D78: IN - 5250-25-011 - Melhoria acesso bloco P 27-TQ-01 K e M - Detalhamento - Projeto Mecânica | E78: Projetos | F78: =SUMIF('CRONO PROJETOS_TOPO'!$B:$B,'RESUMO CRON FINANC'!$C78,'CRONO PROJETOS_TOPO'!Z:Z) -> 0 | G78: =SUMIF('CRONO PROJETOS_TOPO'!$B:$B,'RESUMO CRON FINANC'!$C78,'CRONO PROJETOS_TOPO'!AA:AA) -> 0 | H78: =SUMIF('CRONO PROJETOS_TOPO'!$B:$B,'RESUMO CRON FINANC'!$C78,'CRONO PROJETOS_TOPO'!AB:AB) -> 117836.4 | I78: =SUMIF('CRONO PROJETOS_TOPO'!$B:$B,'RESUMO CRON FINANC'!$C78,'CRONO PROJETOS_TOPO'!AC:AC) -> 0 | J78: =SUMIF('CRONO PROJETOS_TOPO'!$B:$B,'RESUMO CRON FINANC'!$C78,'CRONO PROJETOS_TOPO'!AD:AD) -> 0 | K78: =SUMIF('CRONO PROJETOS_TOPO'!$B:$B,'RESUMO CRON FINANC'!$C78,'CRONO PROJETOS_TOPO'!AE:AE) -> 0 | L78: =SUMIF('CRONO PROJETOS_TOPO'!$B:$B,'RESUMO CRON FINANC'!$C78,'CRONO PROJETOS_TOPO'!AF:AF) -> 0 | M78: =SUMIF('CRONO PROJETOS_TOPO'!$B:$B,'RESUMO CRON FINANC'!$C78,'CRONO PROJETOS_TOPO'!AG:AG) -> 0 | N78: =SUM(F78:M78) -> 117836.4
B79: 8 | C79: SS-118/2026 | D79: IN - 5250-25-011 - Melhoria acesso bloco P 27-TQ-01 K e M - Detalhamento - Projeto Civil | E79: Projetos | F79: =SUMIF('CRONO PROJETOS_TOPO'!$B:$B,'RESUMO CRON FINANC'!$C79,'CRONO PROJETOS_TOPO'!Z:Z) -> 32815.2 | G79: =SUMIF('CRONO PROJETOS_TOPO'!$B:$B,'RESUMO CRON FINANC'!$C79,'CRONO PROJETOS_TOPO'!AA:AA) -> 0 | H79: =SUMIF('CRONO PROJETOS_TOPO'!$B:$B,'RESUMO CRON FINANC'!$C79,'CRONO PROJETOS_TOPO'!AB:AB) -> 0 | I79: =SUMIF('CRONO PROJETOS_TOPO'!$B:$B,'RESUMO CRON FINANC'!$C79,'CRONO PROJETOS_TOPO'!AC:AC) -> 0 | J79: =SUMIF('CRONO PROJETOS_TOPO'!$B:$B,'RESUMO CRON FINANC'!$C79,'CRONO PROJETOS_TOPO'!AD:AD) -> 0 | K79: =SUMIF('CRONO PROJETOS_TOPO'!$B:$B,'RESUMO CRON FINANC'!$C79,'CRONO PROJETOS_TOPO'!AE:AE) -> 0 | L79: =SUMIF('CRONO PROJETOS_TOPO'!$B:$B,'RESUMO CRON FINANC'!$C79,'CRONO PROJETOS_TOPO'!AF:AF) -> 0 | M79: =SUMIF('CRONO PROJETOS_TOPO'!$B:$B,'RESUMO CRON FINANC'!$C79,'CRONO PROJETOS_TOPO'!AG:AG) -> 0 | N79: =SUM(F79:M79) -> 32815.2
B80: 9 | C80: SS-119/2026 | D80: IN - 5250-25-011 - Melhoria acesso bloco P 27-TQ-01 K e M - Detalhamento - Projeto Elétrica | E80: Projetos | F80: =SUMIF('CRONO PROJETOS_TOPO'!$B:$B,'RESUMO CRON FINANC'!$C80,'CRONO PROJETOS_TOPO'!Z:Z) -> 0 | G80: =SUMIF('CRONO PROJETOS_TOPO'!$B:$B,'RESUMO CRON FINANC'!$C80,'CRONO PROJETOS_TOPO'!AA:AA) -> 0 | H80: =SUMIF('CRONO PROJETOS_TOPO'!$B:$B,'RESUMO CRON FINANC'!$C80,'CRONO PROJETOS_TOPO'!AB:AB) -> 0 | I80: =SUMIF('CRONO PROJETOS_TOPO'!$B:$B,'RESUMO CRON FINANC'!$C80,'CRONO PROJETOS_TOPO'!AC:AC) -> 0 | J80: =SUMIF('CRONO PROJETOS_TOPO'!$B:$B,'RESUMO CRON FINANC'!$C80,'CRONO PROJETOS_TOPO'!AD:AD) -> 18924.675 | K80: =SUMIF('CRONO PROJETOS_TOPO'!$B:$B,'RESUMO CRON FINANC'!$C80,'CRONO PROJETOS_TOPO'!AE:AE) -> 0 | L80: =SUMIF('CRONO PROJETOS_TOPO'!$B:$B,'RESUMO CRON FINANC'!$C80,'CRONO PROJETOS_TOPO'!AF:AF) -> 0 | M80: =SUMIF('CRONO PROJETOS_TOPO'!$B:$B,'RESUMO CRON FINANC'!$C80,'CRONO PROJETOS_TOPO'!AG:AG) -> 0 | N80: =SUM(F80:M80) -> 18924.675
B81: 10 | C81: SS-120/2026 | D81: IN - 5250-25-012 - Melhoria acesso bloco P 27-TQ-01 L e N - Detalhamento - Projeto Mecânica | E81: Projetos | F81: =SUMIF('CRONO PROJETOS_TOPO'!$B:$B,'RESUMO CRON FINANC'!$C81,'CRONO PROJETOS_TOPO'!Z:Z) -> 0 | G81: =SUMIF('CRONO PROJETOS_TOPO'!$B:$B,'RESUMO CRON FINANC'!$C81,'CRONO PROJETOS_TOPO'!AA:AA) -> 0 | H81: =SUMIF('CRONO PROJETOS_TOPO'!$B:$B,'RESUMO CRON FINANC'!$C81,'CRONO PROJETOS_TOPO'!AB:AB) -> 154380.6 | I81: =SUMIF('CRONO PROJETOS_TOPO'!$B:$B,'RESUMO CRON FINANC'!$C81,'CRONO PROJETOS_TOPO'!AC:AC) -> 0 | J81: =SUMIF('CRONO PROJETOS_TOPO'!$B:$B,'RESUMO CRON FINANC'!$C81,'CRONO PROJETOS_TOPO'!AD:AD) -> 0 | K81: =SUMIF('CRONO PROJETOS_TOPO'!$B:$B,'RESUMO CRON FINANC'!$C81,'CRONO PROJETOS_TOPO'!AE:AE) -> 0 | L81: =SUMIF('CRONO PROJETOS_TOPO'!$B:$B,'RESUMO CRON FINANC'!$C81,'CRONO PROJETOS_TOPO'!AF:AF) -> 0 | M81: =SUMIF('CRONO PROJETOS_TOPO'!$B:$B,'RESUMO CRON FINANC'!$C81,'CRONO PROJETOS_TOPO'!AG:AG) -> 0 | N81: =SUM(F81:M81) -> 154380.6
B82: 11 | C82: SS-121/2026 | D82: IN - 5250-25-012 - Melhoria acesso bloco P 27-TQ-01 L e N - Detalhamento - Projeto Civil | E82: Projetos | F82: =SUMIF('CRONO PROJETOS_TOPO'!$B:$B,'RESUMO CRON FINANC'!$C82,'CRONO PROJETOS_TOPO'!Z:Z) -> 32815.2 | G82: =SUMIF('CRONO PROJETOS_TOPO'!$B:$B,'RESUMO CRON FINANC'!$C82,'CRONO PROJETOS_TOPO'!AA:AA) -> 0 | H82: =SUMIF('CRONO PROJETOS_TOPO'!$B:$B,'RESUMO CRON FINANC'!$C82,'CRONO PROJETOS_TOPO'!AB:AB) -> 0 | I82: =SUMIF('CRONO PROJETOS_TOPO'!$B:$B,'RESUMO CRON FINANC'!$C82,'CRONO PROJETOS_TOPO'!AC:AC) -> 0 | J82: =SUMIF('CRONO PROJETOS_TOPO'!$B:$B,'RESUMO CRON FINANC'!$C82,'CRONO PROJETOS_TOPO'!AD:AD) -> 0 | K82: =SUMIF('CRONO PROJETOS_TOPO'!$B:$B,'RESUMO CRON FINANC'!$C82,'CRONO PROJETOS_TOPO'!AE:AE) -> 0 | L82: =SUMIF('CRONO PROJETOS_TOPO'!$B:$B,'RESUMO CRON FINANC'!$C82,'CRONO PROJETOS_TOPO'!AF:AF) -> 0 | M82: =SUMIF('CRONO PROJETOS_TOPO'!$B:$B,'RESUMO CRON FINANC'!$C82,'CRONO PROJETOS_TOPO'!AG:AG) -> 0 | N82: =SUM(F82:M82) -> 32815.2
B83: 12 | C83: SS-122/2026 | D83: IN - 5250-25-012 - Melhoria acesso bloco P 27-TQ-01 L e N - Detalhamento - Projeto Elétrica | E83: Projetos | F83: =SUMIF('CRONO PROJETOS_TOPO'!$B:$B,'RESUMO CRON FINANC'!$C83,'CRONO PROJETOS_TOPO'!Z:Z) -> 0 | G83: =SUMIF('CRONO PROJETOS_TOPO'!$B:$B,'RESUMO CRON FINANC'!$C83,'CRONO PROJETOS_TOPO'!AA:AA) -> 0 | H83: =SUMIF('CRONO PROJETOS_TOPO'!$B:$B,'RESUMO CRON FINANC'!$C83,'CRONO PROJETOS_TOPO'!AB:AB) -> 0 | I83: =SUMIF('CRONO PROJETOS_TOPO'!$B:$B,'RESUMO CRON FINANC'!$C83,'CRONO PROJETOS_TOPO'!AC:AC) -> 0 | J83: =SUMIF('CRONO PROJETOS_TOPO'!$B:$B,'RESUMO CRON FINANC'!$C83,'CRONO PROJETOS_TOPO'!AD:AD) -> 0 | K83: =SUMIF('CRONO PROJETOS_TOPO'!$B:$B,'RESUMO CRON FINANC'!$C83,'CRONO PROJETOS_TOPO'!AE:AE) -> 18924.675 | L83: =SUMIF('CRONO PROJETOS_TOPO'!$B:$B,'RESUMO CRON FINANC'!$C83,'CRONO PROJETOS_TOPO'!AF:AF) -> 0 | M83: =SUMIF('CRONO PROJETOS_TOPO'!$B:$B,'RESUMO CRON FINANC'!$C83,'CRONO PROJETOS_TOPO'!AG:AG) -> 0 | N83: =SUM(F83:M83) -> 18924.675
... B85: 14 | C85: SS-133/2025 | D85: IN - 5250-24-085 - Phase-Out do Diesel S500 - Projeto | E85: Projetos | F85: =SUMIF('CRONO PROJETOS_TOPO'!$B:$B,'RESUMO CRON FINANC'!$C85,'CRONO PROJETOS_TOPO'!Z:Z) -> 22374 | G85: =SUMIF('CRONO PROJETOS_TOPO'!$B:$B,'RESUMO CRON FINANC'!$C85,'CRONO PROJETOS_TOPO'!AA:AA) -> 60323.016 | H85: =SUMIF('CRONO PROJETOS_TOPO'!$B:$B,'RESUMO CRON FINANC'!$C85,'CRONO PROJETOS_TOPO'!AB:AB) -> 0 | I85: =SUMIF('CRONO PROJETOS_TOPO'!$B:$B,'RESUMO CRON FINANC'!$C85,'CRONO PROJETOS_TOPO'!AC:AC) -> 0 | J85: =SUMIF('CRONO PROJETOS_TOPO'!$B:$B,'RESUMO CRON FINANC'!$C85,'CRONO PROJETOS_TOPO'!AD:AD) -> 0 | K85: =SUMIF('CRONO PROJETOS_TOPO'!$B:$B,'RESUMO CRON FINANC'!$C85,'CRONO PROJETOS_TOPO'!AE:AE) -> 0 | L85: =SUMIF('CRONO PROJETOS_TOPO'!$B:$B,'RESUMO CRON FINANC'!$C85,'CRONO PROJETOS_TOPO'!AF:AF) -> 0 | M85: =SUMIF('CRONO PROJETOS_TOPO'!$B:$B,'RESUMO CRON FINANC'!$C85,'CRONO PROJETOS_TOPO'!AG:AG) -> 0 | N85: =SUM(F85:M85) -> 82697.016
B86: 15 | C86: SS-191/2026 | D86: PMBC - REATIVAÇÃO DE BANHEIRO SANITÁRIO - 6° ANDAR REATORES 52-R-01 ABCD - ELABORAÇÃO DE PROJETOS | F86: =SUMIF('CRONO PROJETOS_TOPO'!$B:$B,'RESUMO CRON FINANC'!$C86,'CRONO PROJETOS_TOPO'!Z:Z) -> 0 | G86: =SUMIF('CRONO PROJETOS_TOPO'!$B:$B,'RESUMO CRON FINANC'!$C86,'CRONO PROJETOS_TOPO'!AA:AA) -> 16482.18 | H86: =SUMIF('CRONO PROJETOS_TOPO'!$B:$B,'RESUMO CRON FINANC'!$C86,'CRONO PROJETOS_TOPO'!AB:AB) -> 0 | I86: =SUMIF('CRONO PROJETOS_TOPO'!$B:$B,'RESUMO CRON FINANC'!$C86,'CRONO PROJETOS_TOPO'!AC:AC) -> 0 | J86: =SUMIF('CRONO PROJETOS_TOPO'!$B:$B,'RESUMO CRON FINANC'!$C86,'CRONO PROJETOS_TOPO'!AD:AD) -> 0 | K86: =SUMIF('CRONO PROJETOS_TOPO'!$B:$B,'RESUMO CRON FINANC'!$C86,'CRONO PROJETOS_TOPO'!AE:AE) -> 0 | L86: =SUMIF('CRONO PROJETOS_TOPO'!$B:$B,'RESUMO CRON FINANC'!$C86,'CRONO PROJETOS_TOPO'!AF:AF) -> 0 | M86: =SUMIF('CRONO PROJETOS_TOPO'!$B:$B,'RESUMO CRON FINANC'!$C86,'CRONO PROJETOS_TOPO'!AG:AG) -> 0 | N86: =SUM(F86:M86) -> 16482.18
B87: 16 | C87: SS-75/2026 | D87: TOPOGRAFIA - 0027-TQ-0037B | E87: Topografia | F87: =SUMIF('CRONO PROJETOS_TOPO'!$B:$B,'RESUMO CRON FINANC'!$C87,'CRONO PROJETOS_TOPO'!Z:Z) -> 6102.4326 | G87: =SUMIF('CRONO PROJETOS_TOPO'!$B:$B,'RESUMO CRON FINANC'!$C87,'CRONO PROJETOS_TOPO'!AA:AA) -> 0 | H87: =SUMIF('CRONO PROJETOS_TOPO'!$B:$B,'RESUMO CRON FINANC'!$C87,'CRONO PROJETOS_TOPO'!AB:AB) -> 0 | I87: =SUMIF('CRONO PROJETOS_TOPO'!$B:$B,'RESUMO CRON FINANC'!$C87,'CRONO PROJETOS_TOPO'!AC:AC) -> 0 | J87: =SUMIF('CRONO PROJETOS_TOPO'!$B:$B,'RESUMO CRON FINANC'!$C87,'CRONO PROJETOS_TOPO'!AD:AD) -> 0 | K87: =SUMIF('CRONO PROJETOS_TOPO'!$B:$B,'RESUMO CRON FINANC'!$C87,'CRONO PROJETOS_TOPO'!AE:AE) -> 0 | L87: =SUMIF('CRONO PROJETOS_TOPO'!$B:$B,'RESUMO CRON FINANC'!$C87,'CRONO PROJETOS_TOPO'!AF:AF) -> 0 | M87: =SUMIF('CRONO PROJETOS_TOPO'!$B:$B,'RESUMO CRON FINANC'!$C87,'CRONO PROJETOS_TOPO'!AG:AG) -> 0 | N87: =SUM(F87:M87) -> 6102.4326
B88: 17 | C88: SS-76/2026 | D88: TOPOGRAFIA - 0027-TQ-0001N | E88: Topografia | F88: =SUMIF('CRONO PROJETOS_TOPO'!$B:$B,'RESUMO CRON FINANC'!$C88,'CRONO PROJETOS_TOPO'!Z:Z) -> 8136.5768 | G88: =SUMIF('CRONO PROJETOS_TOPO'!$B:$B,'RESUMO CRON FINANC'!$C88,'CRONO PROJETOS_TOPO'!AA:AA) -> 0 | H88: =SUMIF('CRONO PROJETOS_TOPO'!$B:$B,'RESUMO CRON FINANC'!$C88,'CRONO PROJETOS_TOPO'!AB:AB) -> 0 | I88: =SUMIF('CRONO PROJETOS_TOPO'!$B:$B,'RESUMO CRON FINANC'!$C88,'CRONO PROJETOS_TOPO'!AC:AC) -> 0 | J88: =SUMIF('CRONO PROJETOS_TOPO'!$B:$B,'RESUMO CRON FINANC'!$C88,'CRONO PROJETOS_TOPO'!AD:AD) -> 0 | K88: =SUMIF('CRONO PROJETOS_TOPO'!$B:$B,'RESUMO CRON FINANC'!$C88,'CRONO PROJETOS_TOPO'!AE:AE) -> 0 | L88: =SUMIF('CRONO PROJETOS_TOPO'!$B:$B,'RESUMO CRON FINANC'!$C88,'CRONO PROJETOS_TOPO'!AF:AF) -> 0 | M88: =SUMIF('CRONO PROJETOS_TOPO'!$B:$B,'RESUMO CRON FINANC'!$C88,'CRONO PROJETOS_TOPO'!AG:AG) -> 0 | N88: =SUM(F88:M88) -> 8136.5768
B89: 18 | C89: SS-77/2026 | D89: TOPOGRAFIA - 0027-TQ-0001E | E89: Topografia | F89: =SUMIF('CRONO PROJETOS_TOPO'!$B:$B,'RESUMO CRON FINANC'!$C89,'CRONO PROJETOS_TOPO'!Z:Z) -> 6102.4326 | G89: =SUMIF('CRONO PROJETOS_TOPO'!$B:$B,'RESUMO CRON FINANC'!$C89,'CRONO PROJETOS_TOPO'!AA:AA) -> 0 | H89: =SUMIF('CRONO PROJETOS_TOPO'!$B:$B,'RESUMO CRON FINANC'!$C89,'CRONO PROJETOS_TOPO'!AB:AB) -> 0 | I89: =SUMIF('CRONO PROJETOS_TOPO'!$B:$B,'RESUMO CRON FINANC'!$C89,'CRONO PROJETOS_TOPO'!AC:AC) -> 0 | J89: =SUMIF('CRONO PROJETOS_TOPO'!$B:$B,'RESUMO CRON FINANC'!$C89,'CRONO PROJETOS_TOPO'!AD:AD) -> 0 | K89: =SUMIF('CRONO PROJETOS_TOPO'!$B:$B,'RESUMO CRON FINANC'!$C89,'CRONO PROJETOS_TOPO'!AE:AE) -> 0 | L89: =SUMIF('CRONO PROJETOS_TOPO'!$B:$B,'RESUMO CRON FINANC'!$C89,'CRONO PROJETOS_TOPO'!AF:AF) -> 0 | M89: =SUMIF('CRONO PROJETOS_TOPO'!$B:$B,'RESUMO CRON FINANC'!$C89,'CRONO PROJETOS_TOPO'!AG:AG) -> 0 | N89: =SUM(F89:M89) -> 6102.4326
B90: 19 | C90: SS-81/2026 | D90: TOPOGRAFIA U-623 / DRENAGEM PLUVIAL - BLOCO L | E90: Topografia | F90: =SUMIF('CRONO PROJETOS_TOPO'!$B:$B,'RESUMO CRON FINANC'!$C90,'CRONO PROJETOS_TOPO'!Z:Z) -> 0 | G90: =SUMIF('CRONO PROJETOS_TOPO'!$B:$B,'RESUMO CRON FINANC'!$C90,'CRONO PROJETOS_TOPO'!AA:AA) -> 21358.514 | H90: =SUMIF('CRONO PROJETOS_TOPO'!$B:$B,'RESUMO CRON FINANC'!$C90,'CRONO PROJETOS_TOPO'!AB:AB) -> 0 | I90: =SUMIF('CRONO PROJETOS_TOPO'!$B:$B,'RESUMO CRON FINANC'!$C90,'CRONO PROJETOS_TOPO'!AC:AC) -> 0 | J90: =SUMIF('CRONO PROJETOS_TOPO'!$B:$B,'RESUMO CRON FINANC'!$C90,'CRONO PROJETOS_TOPO'!AD:AD) -> 0 | K90: =SUMIF('CRONO PROJETOS_TOPO'!$B:$B,'RESUMO CRON FINANC'!$C90,'CRONO PROJETOS_TOPO'!AE:AE) -> 0 | L90: =SUMIF('CRONO PROJETOS_TOPO'!$B:$B,'RESUMO CRON FINANC'!$C90,'CRONO PROJETOS_TOPO'!AF:AF) -> 0 | M90: =SUMIF('CRONO PROJETOS_TOPO'!$B:$B,'RESUMO CRON FINANC'!$C90,'CRONO PROJETOS_TOPO'!AG:AG) -> 0 | N90: =SUM(F90:M90) -> 21358.514
B91: 20 | C91: SS-82/2026 | D91: TOPOGRAFIA - DRENAGEM CONTAMINADA BLOCO G | E91: Topografia | F91: =SUMIF('CRONO PROJETOS_TOPO'!$B:$B,'RESUMO CRON FINANC'!$C91,'CRONO PROJETOS_TOPO'!Z:Z) -> 0 | G91: =SUMIF('CRONO PROJETOS_TOPO'!$B:$B,'RESUMO CRON FINANC'!$C91,'CRONO PROJETOS_TOPO'!AA:AA) -> 14239.009 | H91: =SUMIF('CRONO PROJETOS_TOPO'!$B:$B,'RESUMO CRON FINANC'!$C91,'CRONO PROJETOS_TOPO'!AB:AB) -> 0 | I91: =SUMIF('CRONO PROJETOS_TOPO'!$B:$B,'RESUMO CRON FINANC'!$C91,'CRONO PROJETOS_TOPO'!AC:AC) -> 0 | J91: =SUMIF('CRONO PROJETOS_TOPO'!$B:$B,'RESUMO CRON FINANC'!$C91,'CRONO PROJETOS_TOPO'!AD:AD) -> 0 | K91: =SUMIF('CRONO PROJETOS_TOPO'!$B:$B,'RESUMO CRON FINANC'!$C91,'CRONO PROJETOS_TOPO'!AE:AE) -> 0 | L91: =SUMIF('CRONO PROJETOS_TOPO'!$B:$B,'RESUMO CRON FINANC'!$C91,'CRONO PROJETOS_TOPO'!AF:AF) -> 0 | M91: =SUMIF('CRONO PROJETOS_TOPO'!$B:$B,'RESUMO CRON FINANC'!$C91,'CRONO PROJETOS_TOPO'!AG:AG) -> 0 | N91: =SUM(F91:M91) -> 14239.009
B92: 21 | C92: SS-83/2026 | D92: TOPOGRAFIA - ESTRUTURA PLATAFORMA PERMUTADORES | E92: Topografia | F92: =SUMIF('CRONO PROJETOS_TOPO'!$B:$B,'RESUMO CRON FINANC'!$C92,'CRONO PROJETOS_TOPO'!Z:Z) -> 0 | G92: =SUMIF('CRONO PROJETOS_TOPO'!$B:$B,'RESUMO CRON FINANC'!$C92,'CRONO PROJETOS_TOPO'!AA:AA) -> 30512.163 | H92: =SUMIF('CRONO PROJETOS_TOPO'!$B:$B,'RESUMO CRON FINANC'!$C92,'CRONO PROJETOS_TOPO'!AB:AB) -> 0 | I92: =SUMIF('CRONO PROJETOS_TOPO'!$B:$B,'RESUMO CRON FINANC'!$C92,'CRONO PROJETOS_TOPO'!AC:AC) -> 0 | J92: =SUMIF('CRONO PROJETOS_TOPO'!$B:$B,'RESUMO CRON FINANC'!$C92,'CRONO PROJETOS_TOPO'!AD:AD) -> 0 | K92: =SUMIF('CRONO PROJETOS_TOPO'!$B:$B,'RESUMO CRON FINANC'!$C92,'CRONO PROJETOS_TOPO'!AE:AE) -> 0 | L92: =SUMIF('CRONO PROJETOS_TOPO'!$B:$B,'RESUMO CRON FINANC'!$C92,'CRONO PROJETOS_TOPO'!AF:AF) -> 0 | M92: =SUMIF('CRONO PROJETOS_TOPO'!$B:$B,'RESUMO CRON FINANC'!$C92,'CRONO PROJETOS_TOPO'!AG:AG) -> 0 | N92: =SUM(F92:M92) -> 30512.163
D94: TOTAL PROJETOS E TOPOGRAFIA | F94: =SUM(F72:F93) -> 145635.84 | G94: =SUM(G72:G93) -> 222808.71 | H94: =SUM(H72:H93) -> 583663.08 | I94: =SUM(I72:I93) -> 245368.2 | J94: =SUM(J72:J93) -> 27128.475 | K94: =SUM(K72:K93) -> 27128.475 | L94: =SUM(L72:L93) -> 11932.8 | M94: =SUM(M72:M93) -> 0 | N94: =SUBTOTAL(9,N72:N92) -> 1263665.6
D96: TOTAL GERAL SERVIÇOS + ROTINAS + PROJETOS + TOPOGRAFIA | F96: =SUM(F71,F64,F94) -> 7390255.7 | G96: =SUM(G71,G64,G94) -> 11127512 | H96: =SUM(H71,H64,H94) -> 11963463 | I96: =SUM(I71,I64,I94) -> 8319885.6 | J96: =SUM(J71,J64,J94) -> 6027083 | K96: =SUM(K71,K64,K94) -> 4737608.1 | L96: =SUM(L71,L64,L94) -> 4083123.4 | M96: =SUM(M71,M64,M94) -> 4016417.2 | N96: =SUM(N71,N64,N94) -> 83598568
D99: REVENDA | F99: ='CRONO BENS'!Y6 -> 566418.96
D100: TOTAL GERAL | F100: =F96+F99 -> 7956674.6

Sheet CRONO SERV
K2: FISICO_QUANTIDADES | V2: FINANCEIRO_VALOR (R$)
K3: Medido | L3: Saldo | M3: 46143 | N3: 46174 | O3: 46204 | P3: 46235 | Q3: 46266 | R3: 46296 | S3: 46327 | T3: 46357 | V3: Acum | W3: Saldo | X3: 46143 | Y3: 46174 | Z3: 46204 | AA3: 46235 | AB3: 46266 | AC3: 46296 | AD3: 46327 | AE3: 46357 | AF3: TOTAL MAIO A DEZ/2026 | AH3: CONF.FIS | AI3: CONF.R$
B4: SS | C4: DESCRIÇÃO-SS | D4: ITEM | E4: DESCRIÇÃO-ITEM | F4: UN | G4: Qtd | H4: PREÇO UNITÁRIO (R$) | I4: PREÇO TOTAL (R$)
V6: =SUM(V7,V12,V24,V31,V37,V39,V43,V47,V71,V89,V121,V136,V138,V156,V162,V171,V181,V190,V208,V238,V247,V250,V264,V273,V288,V292,V316,V340,V363,V386,V407,V429,V451,V459,V463,V468,V473,V477,V495,V498,V503,V534,V539,V549,V564,V577,V580,V583,V621,V633,V636,V647,V663,V679,V718,V724,V730,V736) -> 13013393 | W6: =SUM(W7,W12,W24,W31,W37,W39,W43,W47,W71,W89,W121,W136,W138,W156,W162,W171,W181,W190,W208,W238,W247,W250,W264,W273,W288,W292,W316,W340,W363,W386,W407,W429,W451,W459,W463,W468,W473,W477,W495,W498,W503,W534,W539,W549,W564,W577,W580,W583,W621,W633,W636,W647,W663,W679,W718,W724,W730,W736) -> 28192829 | X6: =SUM(X7,X12,X24,X31,X37,X39,X43,X47,X71,X89,X121,X136,X138,X156,X162,X171,X181,X190,X208,X238,X247,X250,X264,X273,X288,X292,X316,X340,X363,X386,X407,X429,X451,X459,X463,X468,X473,X477,X495,X498,X503,X534,X539,X549,X564,X577,X580,X583,X621,X633,X636,X647,X663,X679,X718,X724,X730,X736) -> 3469594.7 | Y6: =SUM(Y7,Y12,Y24,Y31,Y37,Y39,Y43,Y47,Y71,Y89,Y121,Y136,Y138,Y156,Y162,Y171,Y181,Y190,Y208,Y238,Y247,Y250,Y264,Y273,Y288,Y292,Y316,Y340,Y363,Y386,Y407,Y429,Y451,Y459,Y463,Y468,Y473,Y477,Y495,Y498,Y503,Y534,Y539,Y549,Y564,Y577,Y580,Y583,Y621,Y633,Y636,Y647,Y663,Y679,Y718,Y724,Y730,Y736) -> 7129677.9 | Z6: =SUM(Z7,Z12,Z24,Z31,Z37,Z39,Z43,Z47,Z71,Z89,Z121,Z136,Z138,Z156,Z162,Z171,Z181,Z190,Z208,Z238,Z247,Z250,Z264,Z273,Z288,Z292,Z316,Z340,Z363,Z386,Z407,Z429,Z451,Z459,Z463,Z468,Z473,Z477,Z495,Z498,Z503,Z534,Z539,Z549,Z564,Z577,Z580,Z583,Z621,Z633,Z636,Z647,Z663,Z679,Z718,Z724,Z730,Z736) -> 7604774.5 | AA6: =SUM(AA7,AA12,AA24,AA31,AA37,AA39,AA43,AA47,AA71,AA89,AA121,AA136,AA138,AA156,AA162,AA171,AA181,AA190,AA208,AA238,AA247,AA250,AA264,AA273,AA288,AA292,AA316,AA340,AA363,AA386,AA407,AA429,AA451,AA459,AA463,AA468,AA473,AA477,AA495,AA498,AA503,AA534,AA539,AA549,AA564,AA577,AA580,AA583,AA621,AA633,AA636,AA647,AA663,AA679,AA718,AA724,AA730,AA736) -> 4299492.3 | AB6: =SUM(AB7,AB12,AB24,AB31,AB37,AB39,AB43,AB47,AB71,AB89,AB121,AB136,AB138,AB156,AB162,AB171,AB181,AB190,AB208,AB238,AB247,AB250,AB264,AB273,AB288,AB292,AB316,AB340,AB363,AB386,AB407,AB429,AB451,AB459,AB463,AB468,AB473,AB477,AB495,AB498,AB503,AB534,AB539,AB549,AB564,AB577,AB580,AB583,AB621,AB633,AB636,AB647,AB663,AB679,AB718,AB724,AB730,AB736) -> 2224929.3 | AC6: =SUM(AC7,AC12,AC24,AC31,AC37,AC39,AC43,AC47,AC71,AC89,AC121,AC136,AC138,AC156,AC162,AC171,AC181,AC190,AC208,AC238,AC247,AC250,AC264,AC273,AC288,AC292,AC316,AC340,AC363,AC386,AC407,AC429,AC451,AC459,AC463,AC468,AC473,AC477,AC495,AC498,AC503,AC534,AC539,AC549,AC564,AC577,AC580,AC583,AC621,AC633,AC636,AC647,AC663,AC679,AC718,AC724,AC730,AC736) -> 935454.48 | ... AF6: =SUM(AF7,AF12,AF24,AF31,AF37,AF39,AF43,AF47,AF71,AF89,AF121,AF136,AF138,AF156,AF162,AF171,AF181,AF190,AF208,AF238,AF247,AF250,AF264,AF273,AF288,AF292,AF316,AF340,AF363,AF386,AF407,AF429,AF451,AF459,AF463,AF468,AF473,AF477,AF495,AF498,AF503,AF534,AF539,AF549,AF564,AF577,AF580,AF583,AF621,AF633,AF636,AF647,AF663,AF679,AF718,AF724,AF730,AF736) -> 26201481
B7: SS-1/2026 | C7: Adequação Escadas de Marinheiro - Execução - UN 01,102,108,109,209 - UDAV 01/02 | I7: =SUM(I8:I11) -> 173199.53 | V7: =SUM(V8:V11) -> 38762.624 | W7: =SUM(W8:W11) -> 134436.9 | X7: =SUM(X8:X11) -> 8448.9511 | Y7: =SUM(Y8:Y11) -> 22525.794 | Z7: =SUM(Z8:Z11) -> 22525.794 | AA7: =SUM(AA8:AA11) -> 27860.851 | AB7: =SUM(AB8:AB11) -> 26675.282 | AC7: =SUM(AC8:AC11) -> 26400.231 | ... AF7: =SUM(AF8:AF11) -> 134436.9
B8: SS-1/2026 | C8: Adequação Escadas de Marinheiro - Execução - UN 01,102,108,109,209 | D8: 1.2.22.1 | E8: Fabricação de estrutura | F8: kg | G8: 796.438 | H8: 34.841778 | I8: =H8*G8 -> 27749.316 | K8: 653.908 | L8: =G8-K8 -> 142.53 | M8: =L8 -> 142.53 | V8: =$H8*K8 -> 22783.317 | W8: =$H8*L8 -> 4965.9986 | X8: =$H8*M8 -> 4965.9986 | Y8: =$H8*N8 -> 0 | Z8: =$H8*O8 -> 0 | AA8: =$H8*P8 -> 0 | AB8: =$H8*Q8 -> 0 | AC8: =$H8*R8 -> 0 | ... AE8: =$H8*T8 -> 0 | AF8: =SUM(X8:AE8) -> 4965.9986 | AH8: =L8-SUM(M8:T8) -> 0 | AI8: =W8-SUM(X8:AE8) -> 0
B9: SS-1/2026 | C9: Adequação Escadas de Marinheiro - Execução - UN 01,102,108,109,209 | D9: 1.2.23.1 | E9: Serviço de montagem de estrutura | F9: kg | G9: 796.438 | H9: 24.436627 | I9: =H9*G9 -> 19462.259 | K9: 653.908 | L9: =G9-K9 -> 142.53 | M9: =L9 -> 142.53 | V9: =$H9*K9 -> 15979.306 | W9: =$H9*L9 -> 3482.9525 | X9: =$H9*M9 -> 3482.9525 | Y9: =$H9*N9 -> 0 | Z9: =$H9*O9 -> 0 | AA9: =$H9*P9 -> 0 | AB9: =$H9*Q9 -> 0 | AC9: =$H9*R9 -> 0 | ... AE9: =$H9*T9 -> 0 | AF9: =SUM(X9:AE9) -> 3482.9525 | AH9: =L9-SUM(M9:T9) -> 0 | AI9: =W9-SUM(X9:AE9) -> 0
B10: SS-8/2026 | C10: Adequação Escadas de Marinheiro - Execução - UDAV 01/02 | D10: 1.2.22.1 | E10: Fabricação de estrutura | F10: kg | G10: 2125.36 | H10: 34.841778 | I10: =H10*G10 -> 74051.322 | L10: =G10-K10 -> 2125.36 | N10: 380 | O10: 380 | P10: 470 | Q10: 450 | R10: =L10-N10-O10-P10-Q10 -> 445.36 | V10: =$H10*K10 -> 0 | W10: =$H10*L10 -> 74051.322 | X10: =$H10*M10 -> 0 | Y10: =$H10*N10 -> 13239.876 | Z10: =$H10*O10 -> 13239.876 | AA10: =$H10*P10 -> 16375.636 | AB10: =$H10*Q10 -> 15678.8 | AC10: =$H10*R10 -> 15517.134 | ... AE10: =$H10*T10 -> 0 | AF10: =SUM(X10:AE10) -> 74051.322 | AH10: =L10-SUM(M10:T10) -> 0 | AI10: =W10-SUM(X10:AE10) -> 0
B11: SS-8/2026 | C11: Adequação Escadas de Marinheiro - Execução - UDAV 01/02 | D11: 1.2.23.1 | E11: Serviço de montagem de estrutura | F11: kg | G11: 2125.36 | H11: 24.436627 | I11: =H11*G11 -> 51936.63 | L11: =G11-K11 -> 2125.36 | N11: 380 | O11: 380 | P11: 470 | Q11: 450 | R11: =L11-N11-O11-P11-Q11 -> 445.36 | V11: =$H11*K11 -> 0 | W11: =$H11*L11 -> 51936.63 | X11: =$H11*M11 -> 0 | Y11: =$H11*N11 -> 9285.9183 | Z11: =$H11*O11 -> 9285.9183 | AA11: =$H11*P11 -> 11485.215 | AB11: =$H11*Q11 -> 10996.482 | AC11: =$H11*R11 -> 10883.096 | ... AE11: =$H11*T11 -> 0 | AF11: =SUM(X11:AE11) -> 51936.63 | AH11: =L11-SUM(M11:T11) -> 0 | AI11: =W11-SUM(X11:AE11) -> 0
B12: SS-2/2026 | C12: IN-5250-24-092 - PT-200 - Escavação Manual para Pré Furos e Fundação | I12: =SUM(I13:I23) -> 266884.66 | V12: =SUM(V13:V23) -> 82951.949 | W12: =SUM(W13:W23) -> 182638.26 | X12: =SUM(X13:X23) -> 86040.747 | Y12: =SUM(Y13:Y23) -> 47782.443 | Z12: =SUM(Z13:Z23) -> 0 | AA12: =SUM(AA13:AA23) -> 0 | AB12: =SUM(AB13:AB23) -> 0 | AC12: =SUM(AC13:AC23) -> 0 | ... AF12: =SUM(AF13:AF23) -> 133823.19
B13: SS-2/2026 | C13: IN-5250-24-092 - PT-200 - Escavação Manual para Pré Furos e Fundação | D13: 1.1.1.2 | E13: Demolição de concreto simples, armado ou refratários | F13: m³ | G13: 36.18 | H13: 584.29184 | I13: =H13*G13 -> 21139.679 | K13: 5.929 | L13: =G13-K13 -> 30.251 | M13: =L13 -> 30.251 | V13: =$H13*K13 -> 3464.2663 | W13: =$H13*L13 -> 17675.412 | X13: =$H13*M13 -> 17675.412 | Y13: =$H13*N13 -> 0 | Z13: =$H13*O13 -> 0 | AA13: =$H13*P13 -> 0 | AB13: =$H13*Q13 -> 0 | AC13: =$H13*R13 -> 0 | ... AE13: =$H13*T13 -> 0 | AF13: =SUM(X13:AE13) -> 17675.412 | AH13: =L13-SUM(M13:T13) -> 0 | AI13: =W13-SUM(X13:AE13) -> 0
B14: SS-2/2026 | C14: IN-5250-24-092 - PT-200 - Escavação Manual para Pré Furos e Fundação | D14: 1.1.1.3 | E14: Demolição controlada de concreto | F14: m³ | G14: 52.26 | H14: 973.81973 | I14: =H14*G14 -> 50891.819 | L14: =G14-K14 -> 52.26 | M14: =L14 -> 52.26 | V14: =$H14*K14 -> 0 | W14: =$H14*L14 -> 50891.819 | X14: =$H14*M14 -> 50891.819 | Y14: =$H14*N14 -> 0 | Z14: =$H14*O14 -> 0 | AA14: =$H14*P14 -> 0 | AB14: =$H14*Q14 -> 0 | AC14: =$H14*R14 -> 0 | ... AE14: =$H14*T14 -> 0 | AF14: =SUM(X14:AE14) -> 50891.819 | AH14: =L14-SUM(M14:T14) -> 0 | AI14: =W14-SUM(X14:AE14) -> 0
B15: SS-2/2026 | C15: IN-5250-24-092 - PT-200 - Escavação Manual para Pré Furos e Fundação | D15: 1.1.1.5 | E15: Apicoamento de concreto | F15: m² | G15: 20.1 | H15: 54.601315 | I15: =H15*G15 -> 1097.4864 | L15: =G15-K15 -> 20.1 | M15: =L15 -> 20.1 | V15: =$H15*K15 -> 0 | W15: =$H15*L15 -> 1097.4864 | X15: =$H15*M15 -> 1097.4864 | Y15: =$H15*N15 -> 0 | Z15: =$H15*O15 -> 0 | AA15: =$H15*P15 -> 0 | AB15: =$H15*Q15 -> 0 | AC15: =$H15*R15 -> 0 | ... AE15: =$H15*T15 -> 0 | AF15: =SUM(X15:AE15) -> 1097.4864 | AH15: =L15-SUM(M15:T15) -> 0 | AI15: =W15-SUM(X15:AE15) -> 0
B16: SS-2/2026 | C16: IN-5250-24-092 - PT-200 - Escavação Manual para Pré Furos e Fundação | D16: 1.1.1.6 | E16: Escarificação de concreto | F16: m² | G16: 18.425 | H16: 136.52157 | I16: =H16*G16 -> 2515.41 | L16: =G16-K16 -> 18.425 | M16: =L16 -> 18.425 | V16: =$H16*K16 -> 0 | W16: =$H16*L16 -> 2515.41 | X16: =$H16*M16 -> 2515.41 | Y16: =$H16*N16 -> 0 | Z16: =$H16*O16 -> 0 | AA16: =$H16*P16 -> 0 | AB16: =$H16*Q16 -> 0 | AC16: =$H16*R16 -> 0 | ... AE16: =$H16*T16 -> 0 | AF16: =SUM(X16:AE16) -> 2515.41 | AH16: =L16-SUM(M16:T16) -> 0 | AI16: =W16-SUM(X16:AE16) -> 0
B17: SS-2/2026 | C17: IN-5250-24-092 - PT-200 - Escavação Manual para Pré Furos e Fundação | D17: 1.1.1.16 | E17: Levantamento topográfico | F17: Hs | G17: 32 | H17: 231.15275 | I17: =H17*G17 -> 7396.888 | K17: 26.4 | V17: =$H17*K17 -> 6102.4326 | W17: =$H17*L17 -> 0 | X17: =$H17*M17 -> 0 | Y17: =$H17*N17 -> 0 | Z17: =$H17*O17 -> 0 | AA17: =$H17*P17 -> 0 | AB17: =$H17*Q17 -> 0 | AC17: =$H17*R17 -> 0 | ... AE17: =$H17*T17 -> 0 | AF17: =SUM(X17:AE17) -> 0 | AH17: =L17-SUM(M17:T17) -> 0 | AI17: =W17-SUM(X17:AE17) -> 0
B18: SS-2/2026 | C18: IN-5250-24-092 - PT-200 - Escavação Manual para Pré Furos e Fundação | D18: 1.1.2.1 | E18: Escavação manual em solo | F18: m³ | G18: 93.8 | H18: 199.78886 | I18: =H18*G18 -> 18740.195 | K18: 41.29 | L18: =G18-K18 -> 52.51 | M18: =L18 -> 52.51 | V18: =$H18*K18 -> 8249.2819 | W18: =$H18*L18 -> 10490.913 | X18: =$H18*M18 -> 10490.913 | Y18: =$H18*N18 -> 0 | Z18: =$H18*O18 -> 0 | AA18: =$H18*P18 -> 0 | AB18: =$H18*Q18 -> 0 | AC18: =$H18*R18 -> 0 | ... AE18: =$H18*T18 -> 0 | AF18: =SUM(X18:AE18) -> 10490.913 | AH18: =L18-SUM(M18:T18) -> 0 | AI18: =W18-SUM(X18:AE18) -> 0
B19: SS-2/2026 | C19: IN-5250-24-092 - PT-200 - Escavação Manual para Pré Furos e Fundação | D19: 1.1.2.2 | E19: Escavação mecanizada em solo até 3m | F19: m³ | G19: 76.38 | H19: 44.117647 | I19: =H19*G19 -> 3369.7059 | L19: =G19-K19 -> 76.38 | M19: =L19 -> 76.38 | V19: =$H19*K19 -> 0 | W19: =$H19*L19 -> 3369.7059 | X19: =$H19*M19 -> 3369.7059 | Y19: =$H19*N19 -> 0 | Z19: =$H19*O19 -> 0 | AA19: =$H19*P19 -> 0 | AB19: =$H19*Q19 -> 0 | AC19: =$H19*R19 -> 0 | ... AE19: =$H19*T19 -> 0 | AF19: =SUM(X19:AE19) -> 3369.7059 | AH19: =L19-SUM(M19:T19) -> 0 | AI19: =W19-SUM(X19:AE19) -> 0
B20: SS-2/2026 | C20: IN-5250-24-092 - PT-200 - Escavação Manual para Pré Furos e Fundação | D20: 1.1.2.4 | E20: Escoramento de escavações | F20: m² | G20: 48.24 | H20: 221.1847 | I20: =H20*G20 -> 10669.95 | L20: =G20-K20 -> 48.24 | N20: =L20 -> 48.24 | V20: =$H20*K20 -> 0 | W20: =$H20*L20 -> 10669.95 | X20: =$H20*M20 -> 0 | Y20: =$H20*N20 -> 10669.95 | Z20: =$H20*O20 -> 0 | AA20: =$H20*P20 -> 0 | AB20: =$H20*Q20 -> 0 | AC20: =$H20*R20 -> 0 | ... AE20: =$H20*T20 -> 0 | AF20: =SUM(X20:AE20) -> 10669.95 | AH20: =L20-SUM(M20:T20) -> 0 | AI20: =W20-SUM(X20:AE20) -> 0
B21: SS-2/2026 | C21: IN-5250-24-092 - PT-200 - Escavação Manual para Pré Furos e Fundação | D21: 1.1.2.12 | E21: Transporte de material escavado, incluindo carga e descarga e espalhamento | F21: m³ | G21: 96.48 | H21: 90.646229 | I21: =H21*G21 -> 8745.5482 | K21: 41.29 | L21: =G21-K21 -> 55.19 | N21: =L21 -> 55.19 | V21: =$H21*K21 -> 3742.7828 | W21: =$H21*L21 -> 5002.7654 | X21: =$H21*M21 -> 0 | Y21: =$H21*N21 -> 5002.7654 | Z21: =$H21*O21 -> 0 | AA21: =$H21*P21 -> 0 | AB21: =$H21*Q21 -> 0 | AC21: =$H21*R21 -> 0 | ... AE21: =$H21*T21 -> 0 | AF21: =SUM(X21:AE21) -> 5002.7654 | AH21: =L21-SUM(M21:T21) -> 0 | AI21: =W21-SUM(X21:AE21) -> 0
B22: SS-2/2026 | C22: IN-5250-24-092 - PT-200 - Escavação Manual para Pré Furos e Fundação | D22: 1.2.7.1 | E22: Desmontagem e remoção | F22: kg | G22: 2000 | H22: 46.722364 | I22: =H22*G22 -> 93444.727 | K22: =G22-686 -> 1314 | L22: =G22-K22 -> 686 | V22: =$H22*K22 -> 61393.186 | W22: =$H22*L22 -> 32051.541 | X22: =$H22*M22 -> 0 | Y22: =$H22*N22 -> 0 | Z22: =$H22*O22 -> 0 | AA22: =$H22*P22 -> 0 | AB22: =$H22*Q22 -> 0 | AC22: =$H22*R22 -> 0 | ... AE22: =$H22*T22 -> 0 | AF22: =SUM(X22:AE22) -> 0 | AH22: =L22-SUM(M22:T22) -> 686 | AI22: =W22-SUM(X22:AE22) -> 32051.541
B23: SS-2/2026 | C23: IN-5250-24-092 - PT-200 - Escavação Manual para Pré Furos e Fundação | D23: 1.2.23.1 | E23: Serviço de montagem de estrutura | F23: kg | G23: 2000 | H23: 24.436627 | I23: =H23*G23 -> 48873.254 | L23: =G23-K23 -> 2000 | N23: =1314 -> 1314 | V23: =$H23*K23 -> 0 | W23: =$H23*L23 -> 48873.254 | X23: =$H23*M23 -> 0 | Y23: =$H23*N23 -> 32109.728 | Z23: =$H23*O23 -> 0 | AA23: =$H23*P23 -> 0 | AB23: =$H23*Q23 -> 0 | AC23: =$H23*R23 -> 0 | ... AE23: =$H23*T23 -> 0 | AF23: =SUM(X23:AE23) -> 32109.728 | AH23: =L23-SUM(M23:T23) -> 686 | AI23: =W23-SUM(X23:AE23) -> 16763.526
B24: SS-14/2026 | C24: PMBC - 5250-26-100 - ALTERAÇÕES - HAZOP DA U-001 E U-101 | I24: =SUM(I25:I30) -> 19165.032 | V24: =SUM(V25:V30) -> 0 | W24: =SUM(W25:W30) -> 19165.032 | X24: =SUM(X25:X30) -> 7793.8298 | Y24: =SUM(Y25:Y30) -> 11371.202 | Z24: =SUM(Z25:Z30) -> 0 | AA24: =SUM(AA25:AA30) -> 0 | AB24: =SUM(AB25:AB30) -> 0 | AC24: =SUM(AC25:AC30) -> 0 | ... AF24: =SUM(AF25:AF30) -> 19165.032
B25: SS-14/2026 | C25: PMBC - 5250-26-100 - ALTERAÇÕES - HAZOP DA U-001 E U-101 | D25: 1.2.1.1 | E25: Tubulações (inclui suportes de tubulação) - Diâmetro menor ou igual a 1.1/2" | F25: kg | G25: 42.77996 | H25: 48.374646 | I25: =H25*G25 -> 2069.4654 | L25: =G25-K25 -> 42.77996 | M25: =G25 -> 42.77996 | V25: =$H25*K25 -> 0 | W25: =$H25*L25 -> 2069.4654 | X25: =$H25*M25 -> 2069.4654 | Y25: =$H25*N25 -> 0 | Z25: =$H25*O25 -> 0 | AA25: =$H25*P25 -> 0 | AB25: =$H25*Q25 -> 0 | AC25: =$H25*R25 -> 0 | ... AE25: =$H25*T25 -> 0 | AF25: =SUM(X25:AE25) -> 2069.4654 | AH25: =L25-SUM(M25:T25) -> 0 | AI25: =W25-SUM(X25:AE25) -> 0
B26: SS-14/2026 | C26: PMBC - 5250-26-100 - ALTERAÇÕES - HAZOP DA U-001 E U-101 | D26: 1.2.2.1 | E26: Tubulações (inclui suportes de tubulação) - Diâmetro menor ou igual a 1.1/2" | F26: kg | G26: 71.25858 | H26: 80.332283 | I26: =H26*G26 -> 5724.3644 | L26: =G26-K26 -> 71.25858 | M26: =G26 -> 71.25858 | V26: =$H26*K26 -> 0 | W26: =$H26*L26 -> 5724.3644 | X26: =$H26*M26 -> 5724.3644 | Y26: =$H26*N26 -> 0 | Z26: =$H26*O26 -> 0 | AA26: =$H26*P26 -> 0 | AB26: =$H26*Q26 -> 0 | AC26: =$H26*R26 -> 0 | ... AE26: =$H26*T26 -> 0 | AF26: =SUM(X26:AE26) -> 5724.3644 | AH26: =L26-SUM(M26:T26) -> 0 | AI26: =W26-SUM(X26:AE26) -> 0
B27: SS-14/2026 | C27: PMBC - 5250-26-100 - ALTERAÇÕES - HAZOP DA U-001 E U-101 | D27: 1.2.6.1 | E27: Montagem ou desmontagem - Diâmetro menor ou igual a 4" | F27: m | G27: 9 | H27: 615.87081 | I27: =H27*G27 -> 5542.8373 | L27: =G27-K27 -> 9 | N27: =G27 -> 9 | V27: =$H27*K27 -> 0 | W27: =$H27*L27 -> 5542.8373 | X27: =$H27*M27 -> 0 | Y27: =$H27*N27 -> 5542.8373 | Z27: =$H27*O27 -> 0 | AA27: =$H27*P27 -> 0 | AB27: =$H27*Q27 -> 0 | AC27: =$H27*R27 -> 0 | ... AE27: =$H27*T27 -> 0 | AF27: =SUM(X27:AE27) -> 5542.8373 | AH27: =L27-SUM(M27:T27) -> 0 | AI27: =W27-SUM(X27:AE27) -> 0
B28: SS-14/2026 | C28: PMBC - 5250-26-100 - ALTERAÇÕES - HAZOP DA U-001 E U-101 | D28: 1.2.7.1 | E28: Desmontagem e remoção | F28: kg | G28: 41.3194 | H28: 46.722364 | I28: =H28*G28 -> 1930.54 | L28: =G28-K28 -> 41.3194 | N28: =G28 -> 41.3194 | V28: =$H28*K28 -> 0 | W28: =$H28*L28 -> 1930.54 | X28: =$H28*M28 -> 0 | Y28: =$H28*N28 -> 1930.54 | Z28: =$H28*O28 -> 0 | AA28: =$H28*P28 -> 0 | AB28: =$H28*Q28 -> 0 | AC28: =$H28*R28 -> 0 | ... AE28: =$H28*T28 -> 0 | AF28: =SUM(X28:AE28) -> 1930.54 | AH28: =L28-SUM(M28:T28) -> 0 | AI28: =W28-SUM(X28:AE28) -> 0
B29: SS-14/2026 | C29: PMBC - 5250-26-100 - ALTERAÇÕES - HAZOP DA U-001 E U-101 | D29: 1.4.1.4 | E29: Desligamento e remoção de manômetro, termômetro, termopar ou termoresistência | F29: un | G29: 4 | H29: 159.922 | I29: =H29*G29 -> 639.68799 | L29: =G29-K29 -> 4 | N29: =G29 -> 4 | V29: =$H29*K29 -> 0 | W29: =$H29*L29 -> 639.68799 | X29: =$H29*M29 -> 0 | Y29: =$H29*N29 -> 639.68799 | Z29: =$H29*O29 -> 0 | AA29: =$H29*P29 -> 0 | AB29: =$H29*Q29 -> 0 | AC29: =$H29*R29 -> 0 | ... AE29: =$H29*T29 -> 0 | AF29: =SUM(X29:AE29) -> 639.68799 | AH29: =L29-SUM(M29:T29) -> 0 | AI29: =W29-SUM(X29:AE29) -> 0
B30: SS-14/2026 | C30: PMBC - 5250-26-100 - ALTERAÇÕES - HAZOP DA U-001 E U-101 | D30: 1.4.11.1 | E30: Instalação de manômetro ou termômetro bimetálico | F30: un | G30: 4 | H30: 814.53425 | I30: =H30*G30 -> 3258.137 | L30: =G30-K30 -> 4 | N30: =G30 -> 4 | V30: =$H30*K30 -> 0 | W30: =$H30*L30 -> 3258.137 | X30: =$H30*M30 -> 0 | Y30: =$H30*N30 -> 3258.137 | Z30: =$H30*O30 -> 0 | AA30: =$H30*P30 -> 0 | AB30: =$H30*Q30 -> 0 | AC30: =$H30*R30 -> 0 | ... AE30: =$H30*T30 -> 0 | AF30: =SUM(X30:AE30) -> 3258.137 | AH30: =L30-SUM(M30:T30) -> 0 | AI30: =W30-SUM(X30:AE30) -> 0
B31: SS-36/2026 | C31: Manutenção Civil - Linha do Flare na Av. 8 | I31: =SUM(I32:I36) -> 577840.44 | V31: =SUM(V32:V36) -> 296835.02 | W31: =SUM(W32:W36) -> 281005.42 | X31: =SUM(X32:X36) -> 117974.19 | Y31: =SUM(Y32:Y36) -> 73101.436 | Z31: =SUM(Z32:Z36) -> 89929.793 | AA31: =SUM(AA32:AA36) -> 0 | AB31: =SUM(AB32:AB36) -> 0 | AC31: =SUM(AC32:AC36) -> 0 | ... AF31: =SUM(AF32:AF36) -> 281005.42
B32: SS-36/2026 | C32: Manutenção Civil - Linha do Flare na Av. 8 | D32: 1.1.1.5 | E32: Apicoamento de concreto | F32: m² | G32: 204.312 | H32: 54.601315 | I32: =H32*G32 -> 11155.704 | K32: 6.323 | L32: =G32-K32 -> 197.989 | M32: =SUMIF(MC_SS_36!$A:$A,'CRONO SERV'!$D32,MC_SS_36!E:E) -> 3 | N32: =SUMIF(MC_SS_36!$A:$A,'CRONO SERV'!$D32,MC_SS_36!F:F) -> 87.11516 | O32: =SUMIF(MC_SS_36!$A:$A,'CRONO SERV'!$D32,MC_SS_36!G:G) -> 107.87384 | V32: =$H32*K32 -> 345.24412 | W32: =$H32*L32 -> 10810.46 | X32: =$H32*M32 -> 163.80395 | Y32: =$H32*N32 -> 4756.6023 | Z32: =$H32*O32 -> 5890.0536 | AA32: =$H32*P32 -> 0 | AB32: =$H32*Q32 -> 0 | AC32: =$H32*R32 -> 0 | ... AE32: =$H32*T32 -> 0 | AF32: =SUM(X32:AE32) -> 10810.46 | AH32: =L32-SUM(M32:T32) -> 0 | AI32: =W32-SUM(X32:AE32) -> 0
B33: SS-36/2026 | C33: Manutenção Civil - Linha do Flare na Av. 8 | D33: 1.1.2.14 | E33: Fornecimento, compactação e espalhamento de brita ou bica corrida | F33: m³ | G33: 20 | H33: 217.63088 | I33: =H33*G33 -> 4352.6176 | K33: 17.807 | L33: =G33-K33 -> 2.193 | M33: =SUMIF(MC_SS_36!$A:$A,'CRONO SERV'!$D33,MC_SS_36!E:E) -> 0 | N33: =SUMIF(MC_SS_36!$A:$A,'CRONO SERV'!$D33,MC_SS_36!F:F) -> 2.193 | O33: =SUMIF(MC_SS_36!$A:$A,'CRONO SERV'!$D33,MC_SS_36!G:G) -> 0 | V33: =$H33*K33 -> 3875.3531 | W33: =$H33*L33 -> 477.26452 | X33: =$H33*M33 -> 0 | Y33: =$H33*N33 -> 477.26452 | Z33: =$H33*O33 -> 0 | AA33: =$H33*P33 -> 0 | AB33: =$H33*Q33 -> 0 | AC33: =$H33*R33 -> 0 | ... AE33: =$H33*T33 -> 0 | AF33: =SUM(X33:AE33) -> 477.26452 | AH33: =L33-SUM(M33:T33) -> 0 | AI33: =W33-SUM(X33:AE33) -> 0
B34: SS-36/2026 | C34: Manutenção Civil - Linha do Flare na Av. 8 | D34: 1.1.10.12 | E34: Impermeabilização por cristalização | F34: m² | G34: 681.04 | H34: 196.60862 | I34: =H34*G34 -> 133898.34 | K34: 455.468 | L34: =G34-K34 -> 225.572 | M34: =SUMIF(MC_SS_36!$A:$A,'CRONO SERV'!$D34,MC_SS_36!E:E) -> 225.572 | N34: =SUMIF(MC_SS_36!$A:$A,'CRONO SERV'!$D34,MC_SS_36!F:F) -> 0 | O34: =SUMIF(MC_SS_36!$A:$A,'CRONO SERV'!$D34,MC_SS_36!G:G) -> 0 | V34: =$H34*K34 -> 89548.935 | W34: =$H34*L34 -> 44349.4 | X34: =$H34*M34 -> 44349.4 | Y34: =$H34*N34 -> 0 | Z34: =$H34*O34 -> 0 | AA34: =$H34*P34 -> 0 | AB34: =$H34*Q34 -> 0 | AC34: =$H34*R34 -> 0 | ... AE34: =$H34*T34 -> 0 | AF34: =SUM(X34:AE34) -> 44349.4 | AH34: =L34-SUM(M34:T34) -> 0 | AI34: =W34-SUM(X34:AE34) -> 0
B35: SS-36/2026 | C35: Manutenção Civil - Linha do Flare na Av. 8 | D35: 1.1.15.9 | E35: Reparos rasos (espessuras até 25 mm) | F35: m² | G35: 476.728 | H35: 564.81544 | I35: =H35*G35 -> 269263.34 | K35: 350.804 | L35: =G35-K35 -> 125.924 | M35: =SUMIF(MC_SS_36!$A:$A,'CRONO SERV'!$D35,MC_SS_36!E:E) -> 125.924 | N35: =SUMIF(MC_SS_36!$A:$A,'CRONO SERV'!$D35,MC_SS_36!F:F) -> 0 | O35: =SUMIF(MC_SS_36!$A:$A,'CRONO SERV'!$D35,MC_SS_36!G:G) -> 0 | V35: =$H35*K35 -> 198139.52 | W35: =$H35*L35 -> 71123.82 | X35: =$H35*M35 -> 71123.82 | Y35: =$H35*N35 -> 0 | Z35: =$H35*O35 -> 0 | AA35: =$H35*P35 -> 0 | AB35: =$H35*Q35 -> 0 | AC35: =$H35*R35 -> 0 | ... AE35: =$H35*T35 -> 0 | AF35: =SUM(X35:AE35) -> 71123.82 | AH35: =L35-SUM(M35:T35) -> 0 | AI35: =W35-SUM(X35:AE35) -> 0
B36: SS-36/2026 | C36: Manutenção Civil - Linha do Flare na Av. 8 | D36: 1.1.15.10 | E36: Reparos semi-profundos (espessuras entre 25 mm e 60 mm) | F36: m² | G36: 204.312 | H36: 779.05578 | I36: =H36*G36 -> 159170.45 | K36: 6.323 | L36: =G36-K36 -> 197.989 | M36: =SUMIF(MC_SS_36!$A:$A,'CRONO SERV'!$D36,MC_SS_36!E:E) -> 3 | N36: =SUMIF(MC_SS_36!$A:$A,'CRONO SERV'!$D36,MC_SS_36!F:F) -> 87.11516 | O36: =SUMIF(MC_SS_36!$A:$A,'CRONO SERV'!$D36,MC_SS_36!G:G) -> 107.87384 | V36: =$H36*K36 -> 4925.9697 | W36: =$H36*L36 -> 154244.48 | X36: =$H36*M36 -> 2337.1674 | Y36: =$H36*N36 -> 67867.569 | Z36: =$H36*O36 -> 84039.739 | AA36: =$H36*P36 -> 0 | AB36: =$H36*Q36 -> 0 | AC36: =$H36*R36 -> 0 | ... AE36: =$H36*T36 -> 0 | AF36: =SUM(X36:AE36) -> 154244.48 | AH36: =L36-SUM(M36:T36) -> 0 | AI36: =W36-SUM(X36:AE36) -> 0
B37: SS-39/2026 | C37: IN-5250-24-092 - PT-200 - Estrutura Metálica - Fabricação | I37: =SUM(I38:I38) -> 7289311.6 | V37: =V38 -> 0 | W37: =W38 -> 7289311.6 | X37: =X38 -> 522626.67 | Y37: =Y38 -> 2891867.6 | Z37: =Z38 -> 3553861.4 | AA37: =AA38 -> 592310.23 | AB37: =AB38 -> 0 | AC37: =AC38 -> 0 | ... AF37: =AF38 -> 7560665.9
B38: SS-39/2026 | C38: IN-5250-24-092 - PT-200 - Estrutura Metálica - Fabricação | D38: 1.2.22.1 | E38: Fabricação de estrutura | F38: kg | G38: 209211.81 | H38: 34.841778 | I38: =H38*G38 -> 7289311.6 | L38: =G38-K38 -> 209211.81 | M38: =SUM(MC_SS_39!H3:H15) -> 15000 | N38: =SUM(MC_SS_39!I3:I15) -> 83000 | O38: =SUM(MC_SS_39!J3:J15) -> 102000 | P38: =SUM(MC_SS_39!K3:K15) -> 17000 | Q38: =SUM(MC_SS_39!L3:L15) -> 0 | R38: =SUM(MC_SS_39!M3:M15) -> 0 | V38: =$H38*K38 -> 0 | W38: =$H38*L38 -> 7289311.6 | X38: =$H38*M38 -> 522626.67 | Y38: =$H38*N38 -> 2891867.6 | Z38: =$H38*O38 -> 3553861.4 | AA38: =$H38*P38 -> 592310.23 | AB38: =$H38*Q38 -> 0 | AC38: =$H38*R38 -> 0 | ... AE38: =$H38*T38 -> 0 | AF38: =SUM(X38:AE38) -> 7560665.9 | AH38: =L38-SUM(M38:T38) -> -7788.1868 | AI38: =W38-SUM(X38:AE38) -> -271354.28
B39: SS-44/2026 | C39: IN - 5250-24-085 - Phase-Out do Diesel S500 - Mudança 2.1 - Fabricação (Tubovias) | I39: =SUM(I40:I42) -> 876615.91 | V39: =SUM(V40:V42) -> 331297.35 | W39: =SUM(W40:W42) -> 545318.56 | X39: =SUM(X40:X42) -> 383499.72 | Y39: =SUM(Y40:Y42) -> 161818.85 | Z39: =SUM(Z40:Z42) -> 0 | AA39: =SUM(AA40:AA42) -> 0 | AB39: =SUM(AB40:AB42) -> 0 | AC39: =SUM(AC40:AC42) -> 0 | ... AF39: =SUM(AF40:AF42) -> 545318.56
B40: SS-44/2026 | C40: IN - 5250-24-085 - Phase-Out do Diesel S500 - Mudança 2.1 - Fabricação (Tubovias) | D40: 1.2.1.1 | E40: Tubulações (inclui suportes de tubulação) - Diâmetro menor ou igual a 1.1/2" | F40: kg | G40: 21.11723 | H40: 48.374646 | I40: =H40*G40 -> 1021.5385 | L40: =G40-K40 -> 21.11723 | M40: =SUM(MC_SS_44!N3:N15) -> 21.11723 | N40: =SUM(MC_SS_44!P3:P15) -> 0 | V40: =$H40*K40 -> 0 | W40: =$H40*L40 -> 1021.5385 | X40: =$H40*M40 -> 1021.5385 | Y40: =$H40*N40 -> 0 | Z40: =$H40*O40 -> 0 | AA40: =$H40*P40 -> 0 | AB40: =$H40*Q40 -> 0 | AC40: =$H40*R40 -> 0 | ... AE40: =$H40*T40 -> 0 | AF40: =SUM(X40:AE40) -> 1021.5385 | AH40: =L40-SUM(M40:T40) -> 0 | AI40: =W40-SUM(X40:AE40) -> 0
B41: SS-44/2026 | C41: IN - 5250-24-085 - Phase-Out do Diesel S500 - Mudança 2.1 - Fabricação (Tubovias) | D41: 1.2.1.2 | E41: Tubulações (inclui suportes de tubulação) - Diâmetro maior do que 1.1/2" até 6" | F41: kg | G41: 19706.05 | H41: 36.221137 | I41: =H41*G41 -> 713775.53 | K41: 9146.52 | L41: =G41-K41 -> 10559.53 | M41: =L41 -> 10559.53 | N41: =SUM(MC_SS_44!Q3:Q15) -> 0 | V41: =$H41*K41 -> 331297.35 | W41: =$H41*L41 -> 382478.18 | X41: =$H41*M41 -> 382478.18 | Y41: =$H41*N41 -> 0 | Z41: =$H41*O41 -> 0 | AA41: =$H41*P41 -> 0 | AB41: =$H41*Q41 -> 0 | AC41: =$H41*R41 -> 0 | ... AE41: =$H41*T41 -> 0 | AF41: =SUM(X41:AE41) -> 382478.18 | AH41: =L41-SUM(M41:T41) -> 0 | AI41: =W41-SUM(X41:AE41) -> 0
B42: SS-44/2026 | C42: IN - 5250-24-085 - Phase-Out do Diesel S500 - Mudança 2.1 - Fabricação (Tubovias) | D42: 1.2.8.3 | E42: Radiografia de Juntas | F42: un | G42: 47 | H42: 3442.9542 | I42: =H42*G42 -> 161818.85 | L42: =G42-K42 -> 47 | N42: =G42 -> 47 | V42: =$H42*K42 -> 0 | W42: =$H42*L42 -> 161818.85 | X42: =$H42*M42 -> 0 | Y42: =$H42*N42 -> 161818.85 | Z42: =$H42*O42 -> 0 | AA42: =$H42*P42 -> 0 | AB42: =$H42*Q42 -> 0 | AC42: =$H42*R42 -> 0 | ... AE42: =$H42*T42 -> 0 | AF42: =SUM(X42:AE42) -> 161818.85 | AH42: =L42-SUM(M42:T42) -> 0 | AI42: =W42-SUM(X42:AE42) -> 0
B43: SS-45/2026 | C43: IN - 5250-24-085 - Phase-Out do Diesel S500 - Mudança 2.1 - Montagem (Tubovias) | I43: =SUM(I44:I46) -> 970186 | V43: =SUM(V44:V46) -> 0 | W43: =SUM(W44:W46) -> 970186 | X43: =SUM(X44:X46) -> 128043.83 | Y43: =SUM(Y44:Y46) -> 161833.33 | Z43: =SUM(Z44:Z46) -> 679455.25 | AA43: =SUM(AA44:AA46) -> 853.59637 | AB43: =SUM(AB44:AB46) -> 0 | AC43: =SUM(AC44:AC46) -> 0 | ... AF43: =SUM(AF44:AF46) -> 970186
B44: SS-45/2026 | C44: IN - 5250-24-085 - Phase-Out do Diesel S500 - Mudança 2.1 - Montagem (Tubovias) | D44: 1.2.2.1 | E44: Tubulações (inclui suportes de tubulação) - Diâmetro menor ou igual a 1.1/2" | F44: kg | G44: 21.11723 | H44: 80.332283 | I44: =H44*G44 -> 1696.3953 | L44: =G44-K44 -> 21.11723 | M44: =SUM(MC_SS_45!L3:L15) -> 2.1097 | N44: =SUM(MC_SS_45!N3:N15) -> 6.33777 | O44: =SUM(MC_SS_45!P3:P15) -> 12.66976 | V44: =$H44*K44 -> 0 | W44: =$H44*L44 -> 1696.3953 | X44: =$H44*M44 -> 169.47702 | Y44: =$H44*N44 -> 509.12753 | Z44: =$H44*O44 -> 1017.7907 | AA44: =$H44*P44 -> 0 | AB44: =$H44*Q44 -> 0 | AC44: =$H44*R44 -> 0 | ... AE44: =$H44*T44 -> 0 | AF44: =SUM(X44:AE44) -> 1696.3953 | AH44: =L44-SUM(M44:T44) -> 0 | AI44: =W44-SUM(X44:AE44) -> 0
B45: SS-45/2026 | C45: IN - 5250-24-085 - Phase-Out do Diesel S500 - Mudança 2.1 - Montagem (Tubovias) | D45: 1.2.2.2 | E45: Tubulações (inclui suportes de tubulação) - Diâmetro maior do que 1.1/2" até 6" | F45: kg | G45: 17934.152 | H45: 53.954935 | I45: =H45*G45 -> 967636.01 | L45: =G45-K45 -> 17934.152 | M45: =SUM(MC_SS_45!M3:M15) -> 2370.0214 | N45: =SUM(MC_SS_45!O3:O15) -> 2989.9805 | O45: =SUM(MC_SS_45!Q3:Q15) -> 12574.15 | V45: =$H45*K45 -> 0 | W45: =$H45*L45 -> 967636.01 | X45: =$H45*M45 -> 127874.35 | Y45: =$H45*N45 -> 161324.2 | Z45: =$H45*O45 -> 678437.46 | AA45: =$H45*P45 -> 0 | AB45: =$H45*Q45 -> 0 | AC45: =$H45*R45 -> 0 | ... AE45: =$H45*T45 -> 0 | AF45: =SUM(X45:AE45) -> 967636.01 | AH45: =L45-SUM(M45:T45) -> 0 | AI45: =W45-SUM(X45:AE45) -> 0
B46: SS-45/2026 | C46: IN - 5250-24-085 - Phase-Out do Diesel S500 - Mudança 2.1 - Montagem (Tubovias) | D46: 1.2.6.2 | E46: Montagem ou desmontagem - Diâmetro maior do que 4" e menor ou igual a 12" | F46: un | G46: 1 | H46: 853.59637 | I46: =H46*G46 -> 853.59637 | L46: =G46-K46 -> 1 | P46: =G46 -> 1 | Q46: =N46 -> 0 | V46: =$H46*K46 -> 0 | W46: =$H46*L46 -> 853.59637 | X46: =$H46*M46 -> 0 | Y46: =$H46*N46 -> 0 | Z46: =$H46*O46 -> 0 | AA46: =$H46*P46 -> 853.59637 | AB46: =$H46*Q46 -> 0 | AC46: =$H46*R46 -> 0 | ... AE46: =$H46*T46 -> 0 | AF46: =SUM(X46:AE46) -> 853.59637 | AH46: =L46-SUM(M46:T46) -> 0 | AI46: =W46-SUM(X46:AE46) -> 0
B47: SS-60/2025 | C47: IN-5250-25-014 - ETDI - DESARENADOR | I47: =SUM(I48:I70) -> 727330.43 | V47: =SUM(V48:V70) -> 480419.48 | W47: =SUM(W48:W70) -> 246910.95 | X47: =SUM(X48:X70) -> 81934.92 | Y47: =SUM(Y48:Y70) -> 0 | Z47: =SUM(Z48:Z70) -> 0 | AA47: =SUM(AA48:AA70) -> 0 | AB47: =SUM(AB48:AB70) -> 0 | AC47: =SUM(AC48:AC70) -> 0 | ... AF47: =SUM(AF48:AF70) -> 81934.92
B48: SS-60/2025 | C48: IN-5250-25-014 - ETDI - DESARENADOR | D48: 1.1.1.2 | E48: Demolição de concreto simples, armado ou refratários | F48: m³ | G48: 16.8 | H48: 584.29184 | I48: =H48*G48 -> 9816.1029 | K48: 1.508 | L48: =G48-K48 -> 15.292 | M48: 0.7 | V48: =$H48*K48 -> 881.11209 | W48: =$H48*L48 -> 8934.9908 | X48: =$H48*M48 -> 409.00429 | Y48: =$H48*N48 -> 0 | Z48: =$H48*O48 -> 0 | AA48: =$H48*P48 -> 0 | AB48: =$H48*Q48 -> 0 | AC48: =$H48*R48 -> 0 | ... AE48: =$H48*T48 -> 0 | AF48: =SUM(X48:AE48) -> 409.00429 | AH48: =L48-SUM(M48:T48) -> 14.592 | AI48: =W48-SUM(X48:AE48) -> 8525.9865
B49: SS-60/2025 | C49: IN-5250-25-014 - ETDI - DESARENADOR | D49: 1.1.1.5 | E49: Apicoamento de concreto | F49: m² | G49: 35 | H49: 54.601315 | I49: =H49*G49 -> 1911.046 | K49: 31.28 | L49: =G49-K49 -> 3.72 | V49: =$H49*K49 -> 1707.9291 | W49: =$H49*L49 -> 203.11689 | X49: =$H49*M49 -> 0 | Y49: =$H49*N49 -> 0 | Z49: =$H49*O49 -> 0 | AA49: =$H49*P49 -> 0 | AB49: =$H49*Q49 -> 0 | AC49: =$H49*R49 -> 0 | ... AE49: =$H49*T49 -> 0 | AF49: =SUM(X49:AE49) -> 0 | AH49: =L49-SUM(M49:T49) -> 3.72 | AI49: =W49-SUM(X49:AE49) -> 203.11689
B50: SS-60/2025 | C50: IN-5250-25-014 - ETDI - DESARENADOR | D50: 1.1.1.6 | E50: Escarificação de concreto | F50: m² | G50: 35 | H50: 136.52157 | I50: =H50*G50 -> 4778.2551 | K50: 18.02 | L50: =G50-K50 -> 16.98 | V50: =$H50*K50 -> 2460.1188 | W50: =$H50*L50 -> 2318.1363 | X50: =$H50*M50 -> 0 | Y50: =$H50*N50 -> 0 | Z50: =$H50*O50 -> 0 | AA50: =$H50*P50 -> 0 | AB50: =$H50*Q50 -> 0 | AC50: =$H50*R50 -> 0 | ... AE50: =$H50*T50 -> 0 | AF50: =SUM(X50:AE50) -> 0 | AH50: =L50-SUM(M50:T50) -> 16.98 | AI50: =W50-SUM(X50:AE50) -> 2318.1363
B51: SS-60/2025 | C51: IN-5250-25-014 - ETDI - DESARENADOR | D51: 1.1.1.16 | E51: Levantamento topográfico | F51: Hs | G51: 246.96 | H51: 231.15275 | I51: =H51*G51 -> 57085.483 | K51: 246.4 | L51: =G51-K51 -> 0.56 | V51: =$H51*K51 -> 56956.037 | W51: =$H51*L51 -> 129.44554 | X51: =$H51*M51 -> 0 | Y51: =$H51*N51 -> 0 | Z51: =$H51*O51 -> 0 | AA51: =$H51*P51 -> 0 | AB51: =$H51*Q51 -> 0 | AC51: =$H51*R51 -> 0 | ... AE51: =$H51*T51 -> 0 | AF51: =SUM(X51:AE51) -> 0 | AH51: =L51-SUM(M51:T51) -> 0.56 | AI51: =W51-SUM(X51:AE51) -> 129.44554
B52: SS-60/2025 | C52: IN-5250-25-014 - ETDI - DESARENADOR | D52: 1.1.2.1 | E52: Escavação manual em solo | F52: m³ | G52: 45 | H52: 199.78886 | I52: =H52*G52 -> 8990.4985 | K52: 33.144 | L52: =G52-K52 -> 11.856 | V52: =$H52*K52 -> 6621.8018 | W52: =$H52*L52 -> 2368.6967 | X52: =$H52*M52 -> 0 | Y52: =$H52*N52 -> 0 | Z52: =$H52*O52 -> 0 | AA52: =$H52*P52 -> 0 | AB52: =$H52*Q52 -> 0 | AC52: =$H52*R52 -> 0 | ... AE52: =$H52*T52 -> 0 | AF52: =SUM(X52:AE52) -> 0 | AH52: =L52-SUM(M52:T52) -> 11.856 | AI52: =W52-SUM(X52:AE52) -> 2368.6967
B53: SS-60/2025 | C53: IN-5250-25-014 - ETDI - DESARENADOR | D53: 1.1.2.2 | E53: Escavação mecanizada em solo até 3m | F53: m³ | G53: 382.365 | H53: 44.117647 | I53: =H53*G53 -> 16869.044 | K53: 382.365 | L53: =G53-K53 -> 0 | V53: =$H53*K53 -> 16869.044 | W53: =$H53*L53 -> 0 | X53: =$H53*M53 -> 0 | Y53: =$H53*N53 -> 0 | Z53: =$H53*O53 -> 0 | AA53: =$H53*P53 -> 0 | AB53: =$H53*Q53 -> 0 | AC53: =$H53*R53 -> 0 | ... AE53: =$H53*T53 -> 0 | AF53: =SUM(X53:AE53) -> 0 | AH53: =L53-SUM(M53:T53) -> 0 | AI53: =W53-SUM(X53:AE53) -> 0
B54: SS-60/2025 | C54: IN-5250-25-014 - ETDI - DESARENADOR | D54: 1.1.2.3 | E54: Escavação mecanizada em solo acima de 3m | F54: m³ | G54: 5 | H54: 44.117647 | I54: =H54*G54 -> 220.58824 | K54: 2.66 | L54: =G54-K54 -> 2.34 | V54: =$H54*K54 -> 117.35294 | W54: =$H54*L54 -> 103.23529 | X54: =$H54*M54 -> 0 | Y54: =$H54*N54 -> 0 | Z54: =$H54*O54 -> 0 | AA54: =$H54*P54 -> 0 | AB54: =$H54*Q54 -> 0 | AC54: =$H54*R54 -> 0 | ... AE54: =$H54*T54 -> 0 | AF54: =SUM(X54:AE54) -> 0 | AH54: =L54-SUM(M54:T54) -> 2.34 | AI54: =W54-SUM(X54:AE54) -> 103.23529
B55: SS-60/2025 | C55: IN-5250-25-014 - ETDI - DESARENADOR | D55: 1.1.2.6 | E55: Aterro manual sem fornecimento de solo | F55: m³ | G55: 31.406 | H55: 158.11213 | I55: =H55*G55 -> 4965.6697 | K55: 31.406 | L55: =G55-K55 -> 0 | V55: =$H55*K55 -> 4965.6697 | W55: =$H55*L55 -> 0 | X55: =$H55*M55 -> 0 | Y55: =$H55*N55 -> 0 | Z55: =$H55*O55 -> 0 | AA55: =$H55*P55 -> 0 | AB55: =$H55*Q55 -> 0 | AC55: =$H55*R55 -> 0 | ... AE55: =$H55*T55 -> 0 | AF55: =SUM(X55:AE55) -> 0 | AH55: =L55-SUM(M55:T55) -> 0 | AI55: =W55-SUM(X55:AE55) -> 0
B56: SS-60/2025 | C56: IN-5250-25-014 - ETDI - DESARENADOR | D56: 1.1.2.7 | E56: Aterro manual com importação de solo | F56: m³ | G56: 14 | H56: 230.47439 | I56: =H56*G56 -> 3226.6415 | K56: 12.335 | L56: =G56-K56 -> 1.665 | V56: =$H56*K56 -> 2842.9016 | W56: =$H56*L56 -> 383.73986 | X56: =$H56*M56 -> 0 | Y56: =$H56*N56 -> 0 | Z56: =$H56*O56 -> 0 | AA56: =$H56*P56 -> 0 | AB56: =$H56*Q56 -> 0 | AC56: =$H56*R56 -> 0 | ... AE56: =$H56*T56 -> 0 | AF56: =SUM(X56:AE56) -> 0 | AH56: =L56-SUM(M56:T56) -> 1.665 | AI56: =W56-SUM(X56:AE56) -> 383.73986
B57: SS-60/2025 | C57: IN-5250-25-014 - ETDI - DESARENADOR | D57: 1.1.2.9 | E57: Aterro mecanizado sem fornecimento de solo | F57: m³ | G57: 402 | H57: 67.097751 | I57: =H57*G57 -> 26973.296 | K57: 392.364 | L57: =G57-K57 -> 9.636 | V57: =$H57*K57 -> 26326.742 | W57: =$H57*L57 -> 646.55393 | X57: =$H57*M57 -> 0 | Y57: =$H57*N57 -> 0 | Z57: =$H57*O57 -> 0 | AA57: =$H57*P57 -> 0 | AB57: =$H57*Q57 -> 0 | AC57: =$H57*R57 -> 0 | ... AE57: =$H57*T57 -> 0 | AF57: =SUM(X57:AE57) -> 0 | AH57: =L57-SUM(M57:T57) -> 9.636 | AI57: =W57-SUM(X57:AE57) -> 646.55393
B58: SS-60/2025 | C58: IN-5250-25-014 - ETDI - DESARENADOR | D58: 1.1.2.12 | E58: Transporte de material escavado, incluindo carga e descarga e espalhamento | F58: m³ | G58: 408.289 | H58: 90.646229 | I58: =H58*G58 -> 37009.858 | K58: 408.256 | L58: =G58-K58 -> 0.033 | V58: =$H58*K58 -> 37006.867 | W58: =$H58*L58 -> 2.9913256 | X58: =$H58*M58 -> 0 | Y58: =$H58*N58 -> 0 | Z58: =$H58*O58 -> 0 | AA58: =$H58*P58 -> 0 | AB58: =$H58*Q58 -> 0 | AC58: =$H58*R58 -> 0 | ... AE58: =$H58*T58 -> 0 | AF58: =SUM(X58:AE58) -> 0 | AH58: =L58-SUM(M58:T58) -> 0.033 | AI58: =W58-SUM(X58:AE58) -> 2.9913256
B59: SS-60/2025 | C59: IN-5250-25-014 - ETDI - DESARENADOR | D59: 1.1.3.1 | E59: Forma em chapa compensada plastificada | F59: m³ | G59: 8.1 | H59: 15728.69 | I59: =H59*G59 -> 127402.39 | K59: 5.436 | L59: =G59-K59 -> 2.664 | M59: 0.8 | V59: =$H59*K59 -> 85501.157 | W59: =$H59*L59 -> 41901.229 | X59: =$H59*M59 -> 12582.952 | Y59: =$H59*N59 -> 0 | Z59: =$H59*O59 -> 0 | AA59: =$H59*P59 -> 0 | AB59: =$H59*Q59 -> 0 | AC59: =$H59*R59 -> 0 | ... AE59: =$H59*T59 -> 0 | AF59: =SUM(X59:AE59) -> 12582.952 | AH59: =L59-SUM(M59:T59) -> 1.864 | AI59: =W59-SUM(X59:AE59) -> 29318.278
B60: SS-60/2025 | C60: IN-5250-25-014 - ETDI - DESARENADOR | D60: 1.1.3.5 | E60: Armadura Aço CA-50 ou CA-60 | F60: kg | G60: 8897.98 | H60: 25.691751 | I60: =H60*G60 -> 228604.68 | K60: 4912.548 | L60: =G60-K60 -> 3985.432 | M60: =2414.14-1265 -> 1149.14 | V60: =$H60*K60 -> 126211.96 | W60: =$H60*L60 -> 102392.72 | X60: =$H60*M60 -> 29523.418 | Y60: =$H60*N60 -> 0 | Z60: =$H60*O60 -> 0 | AA60: =$H60*P60 -> 0 | AB60: =$H60*Q60 -> 0 | AC60: =$H60*R60 -> 0 | ... AE60: =$H60*T60 -> 0 | AF60: =SUM(X60:AE60) -> 29523.418 | AH60: =L60-SUM(M60:T60) -> 2836.292 | AI60: =W60-SUM(X60:AE60) -> 72869.306
B61: SS-60/2025 | C61: IN-5250-25-014 - ETDI - DESARENADOR | D61: 1.1.3.7 | E61: Concreto fck 15 MPa | F61: m³ | G61: 25 | H61: 1248.9987 | I61: =H61*G61 -> 31224.967 | K61: 11.482 | L61: =G61-K61 -> 13.518 | M61: =2.7*2.4*0.05 -> 0.324 | V61: =$H61*K61 -> 14341.003 | W61: =$H61*L61 -> 16883.964 | X61: =$H61*M61 -> 404.67558 | Y61: =$H61*N61 -> 0 | Z61: =$H61*O61 -> 0 | AA61: =$H61*P61 -> 0 | AB61: =$H61*Q61 -> 0 | AC61: =$H61*R61 -> 0 | ... AE61: =$H61*T61 -> 0 | AF61: =SUM(X61:AE61) -> 404.67558 | AH61: =L61-SUM(M61:T61) -> 13.194 | AI61: =W61-SUM(X61:AE61) -> 16479.289
B62: SS-60/2025 | C62: IN-5250-25-014 - ETDI - DESARENADOR | D62: 1.1.3.9 | E62: Concreto estrutural fck 30 MPa | F62: m³ | G62: 65 | H62: 1703.4074 | I62: =H62*G62 -> 110721.48 | K62: 50.211 | L62: =G62-K62 -> 14.789 | M62: 5 | V62: =$H62*K62 -> 85529.791 | W62: =$H62*L62 -> 25191.693 | X62: =$H62*M62 -> 8517.0372 | Y62: =$H62*N62 -> 0 | Z62: =$H62*O62 -> 0 | AA62: =$H62*P62 -> 0 | AB62: =$H62*Q62 -> 0 | AC62: =$H62*R62 -> 0 | ... AE62: =$H62*T62 -> 0 | AF62: =SUM(X62:AE62) -> 8517.0372 | AH62: =L62-SUM(M62:T62) -> 9.789 | AI62: =W62-SUM(X62:AE62) -> 16674.655
B63: SS-60/2025 | C63: IN-5250-25-014 - ETDI - DESARENADOR | D63: 1.1.3.10 | E63: Concreto estrutural fck 40 MPa | F63: m³ | G63: 5 | H63: 2157.2457 | I63: =H63*G63 -> 10786.228 | K63: 1.44 | L63: =G63-K63 -> 3.56 | V63: =$H63*K63 -> 3106.4338 | W63: =$H63*L63 -> 7679.7946 | X63: =$H63*M63 -> 0 | Y63: =$H63*N63 -> 0 | Z63: =$H63*O63 -> 0 | AA63: =$H63*P63 -> 0 | AB63: =$H63*Q63 -> 0 | AC63: =$H63*R63 -> 0 | ... AE63: =$H63*T63 -> 0 | AF63: =SUM(X63:AE63) -> 0 | AH63: =L63-SUM(M63:T63) -> 3.56 | AI63: =W63-SUM(X63:AE63) -> 7679.7946
B64: SS-60/2025 | C64: IN-5250-25-014 - ETDI - DESARENADOR | D64: 1.1.3.11 | E64: Graute de base cimentícia auto-adensável | F64: m³ | G64: 2 | H64: 5609.7853 | I64: =H64*G64 -> 11219.571 | K64: 0 | L64: =G64-K64 -> 2 | M64: =L64 -> 2 | V64: =$H64*K64 -> 0 | W64: =$H64*L64 -> 11219.571 | X64: =$H64*M64 -> 11219.571 | Y64: =$H64*N64 -> 0 | Z64: =$H64*O64 -> 0 | AA64: =$H64*P64 -> 0 | AB64: =$H64*Q64 -> 0 | AC64: =$H64*R64 -> 0 | ... AE64: =$H64*T64 -> 0 | AF64: =SUM(X64:AE64) -> 11219.571 | AH64: =L64-SUM(M64:T64) -> 0 | AI64: =W64-SUM(X64:AE64) -> 0
B65: SS-60/2025 | C65: IN-5250-25-014 - ETDI - DESARENADOR | D65: 1.1.3.14 | E65: Chumbadores e inserts metálicos embutidos em concreto | F65: kg | G65: 41.67 | H65: 168.33412 | I65: =H65*G65 -> 7014.483 | K65: 3.2 | L65: =G65-K65 -> 38.47 | V65: =$H65*K65 -> 538.6692 | W65: =$H65*L65 -> 6475.8138 | X65: =$H65*M65 -> 0 | Y65: =$H65*N65 -> 0 | Z65: =$H65*O65 -> 0 | AA65: =$H65*P65 -> 0 | AB65: =$H65*Q65 -> 0 | AC65: =$H65*R65 -> 0 | ... AE65: =$H65*T65 -> 0 | AF65: =SUM(X65:AE65) -> 0 | AH65: =L65-SUM(M65:T65) -> 38.47 | AI65: =W65-SUM(X65:AE65) -> 6475.8138
B66: SS-60/2025 | C66: IN-5250-25-014 - ETDI - DESARENADOR | D66: 1.1.11.5 | E66: Pintura em Envelopes de Concreto | F66: m² | G66: 53.405 | H66: 22.403728 | I66: =H66*G66 -> 1196.4711 | K66: 53.405 | L66: =G66-K66 -> 0 | V66: =$H66*K66 -> 1196.4711 | W66: =$H66*L66 -> 0 | X66: =$H66*M66 -> 0 | Y66: =$H66*N66 -> 0 | Z66: =$H66*O66 -> 0 | AA66: =$H66*P66 -> 0 | AB66: =$H66*Q66 -> 0 | AC66: =$H66*R66 -> 0 | ... AE66: =$H66*T66 -> 0 | AF66: =SUM(X66:AE66) -> 0 | AH66: =L66-SUM(M66:T66) -> 0 | AI66: =W66-SUM(X66:AE66) -> 0
B67: SS-60/2025 | C67: IN-5250-25-014 - ETDI - DESARENADOR | D67: 1.1.12.1 | E67: Tubulação em ferro fundido qualquer diâmetro, inclusive conexões e acessórios | F67: kg | G67: 259 | H67: 68.279073 | I67: =H67*G67 -> 17684.28 | K67: 0 | L67: =G67-K67 -> 259 | M67: =L67 -> 259 | V67: =$H67*K67 -> 0 | W67: =$H67*L67 -> 17684.28 | X67: =$H67*M67 -> 17684.28 | Y67: =$H67*N67 -> 0 | Z67: =$H67*O67 -> 0 | AA67: =$H67*P67 -> 0 | AB67: =$H67*Q67 -> 0 | AC67: =$H67*R67 -> 0 | ... AE67: =$H67*T67 -> 0 | AF67: =SUM(X67:AE67) -> 17684.28 | AH67: =L67-SUM(M67:T67) -> 0 | AI67: =W67-SUM(X67:AE67) -> 0
B68: SS-60/2025 | C68: IN-5250-25-014 - ETDI - DESARENADOR | D68: 1.1.12.3 | E68: Tampão articulado em ferro fundido, diâmetro 600 mm a 800 mm | F68: unid. | G68: 3 | H68: 796.99149 | I68: =H68*G68 -> 2390.9745 | K68: 0 | L68: =G68-K68 -> 3 | M68: 2 | V68: =$H68*K68 -> 0 | W68: =$H68*L68 -> 2390.9745 | X68: =$H68*M68 -> 1593.983 | Y68: =$H68*N68 -> 0 | Z68: =$H68*O68 -> 0 | AA68: =$H68*P68 -> 0 | AB68: =$H68*Q68 -> 0 | AC68: =$H68*R68 -> 0 | ... AE68: =$H68*T68 -> 0 | AF68: =SUM(X68:AE68) -> 1593.983 | AH68: =L68-SUM(M68:T68) -> 1 | AI68: =W68-SUM(X68:AE68) -> 796.99149
B69: SS-60/2025 | C69: IN-5250-25-014 - ETDI - DESARENADOR | D69: 1.1.13.18 | E69: Demolição e remoção de pavimento asfáltico | F69: m³ | G69: 2.208 | H69: 97.381973 | I69: =H69*G69 -> 215.0194 | K69: 2.208 | L69: =G69-K69 -> 0 | V69: =$H69*K69 -> 215.0194 | W69: =$H69*L69 -> 0 | X69: =$H69*M69 -> 0 | Y69: =$H69*N69 -> 0 | Z69: =$H69*O69 -> 0 | AA69: =$H69*P69 -> 0 | AB69: =$H69*Q69 -> 0 | AC69: =$H69*R69 -> 0 | ... AE69: =$H69*T69 -> 0 | AF69: =SUM(X69:AE69) -> 0 | AH69: =L69-SUM(M69:T69) -> 0 | AI69: =W69-SUM(X69:AE69) -> 0
B70: SS-60/2025 | C70: IN-5250-25-014 - ETDI - DESARENADOR | D70: 1.7.2.1 | E70: Serviços Técnicos Especializados de Engenharia - Hora Normal | F70: Hs | G70: 27.624 | H70: 254.25 | I70: =H70*G70 -> 7023.402 | K70: 27.624 | L70: =G70-K70 -> 0 | V70: =$H70*K70 -> 7023.402 | W70: =$H70*L70 -> 0 | X70: =$H70*M70 -> 0 | Y70: =$H70*N70 -> 0 | Z70: =$H70*O70 -> 0 | AA70: =$H70*P70 -> 0 | AB70: =$H70*Q70 -> 0 | AC70: =$H70*R70 -> 0 | ... AE70: =$H70*T70 -> 0 | AF70: =SUM(X70:AE70) -> 0 | AH70: =L70-SUM(M70:T70) -> 0 | AI70: =W70-SUM(X70:AE70) -> 0
B71: SS-61/2025 | C71: IN-5250-20-001 - ETDI - REDE CONTAMINADA | I71: =SUM(I72:I88) -> 3261384.6 | V71: =SUM(V72:V88) -> 2882138.5 | W71: =SUM(W72:W88) -> 379246.14 | X71: =SUM(X72:X88) -> 1040.7412 | Y71: =SUM(Y72:Y88) -> 0 | Z71: =SUM(Z72:Z88) -> 0 | AA71: =SUM(AA72:AA88) -> 0 | AB71: =SUM(AB72:AB88) -> 0 | AC71: =SUM(AC72:AC88) -> 0 | ... AF71: =SUM(AF72:AF88) -> 1040.7412
B72: SS-61/2025 | C72: IN-5250-20-001 - ETDI - REDE CONTAMINADA | D72: 1.1.1.2 | E72: Demolição de concreto simples, armado ou refratários | F72: m³ | G72: 15 | H72: 584.29184 | I72: =H72*G72 -> 8764.3776 | K72: 0.581 | L72: =G72-K72 -> 14.419 | V72: =$H72*K72 -> 339.47356 | W72: =$H72*L72 -> 8424.904 | X72: =$H72*M72 -> 0 | Y72: =$H72*N72 -> 0 | Z72: =$H72*O72 -> 0 | AA72: =$H72*P72 -> 0 | AB72: =$H72*Q72 -> 0 | AC72: =$H72*R72 -> 0 | ... AE72: =$H72*T72 -> 0 | AF72: =SUM(X72:AE72) -> 0 | AH72: =L72-SUM(M72:T72) -> 14.419 | AI72: =W72-SUM(X72:AE72) -> 8424.904
B73: SS-61/2025 | C73: IN-5250-20-001 - ETDI - REDE CONTAMINADA | D73: 1.1.1.16 | E73: Levantamento topográfico | F73: Hs | G73: 117.04 | H73: 231.15275 | I73: =H73*G73 -> 27054.118 | K73: 117.04 | L73: =G73-K73 -> 0 | V73: =$H73*K73 -> 27054.118 | W73: =$H73*L73 -> 0 | X73: =$H73*M73 -> 0 | Y73: =$H73*N73 -> 0 | Z73: =$H73*O73 -> 0 | AA73: =$H73*P73 -> 0 | AB73: =$H73*Q73 -> 0 | AC73: =$H73*R73 -> 0 | ... AE73: =$H73*T73 -> 0 | AF73: =SUM(X73:AE73) -> 0 | AH73: =L73-SUM(M73:T73) -> 0 | AI73: =W73-SUM(X73:AE73) -> 0
B74: SS-61/2025 | C74: IN-5250-20-001 - ETDI - REDE CONTAMINADA | D74: 1.1.2.1 | E74: Escavação manual em solo | F74: m³ | G74: 150 | H74: 199.78886 | I74: =H74*G74 -> 29968.328 | K74: 99.401 | L74: =G74-K74 -> 50.599 | V74: =$H74*K74 -> 19859.212 | W74: =$H74*L74 -> 10109.116 | X74: =$H74*M74 -> 0 | Y74: =$H74*N74 -> 0 | Z74: =$H74*O74 -> 0 | AA74: =$H74*P74 -> 0 | AB74: =$H74*Q74 -> 0 | AC74: =$H74*R74 -> 0 | ... AE74: =$H74*T74 -> 0 | AF74: =SUM(X74:AE74) -> 0 | AH74: =L74-SUM(M74:T74) -> 50.599 | AI74: =W74-SUM(X74:AE74) -> 10109.116
B75: SS-61/2025 | C75: IN-5250-20-001 - ETDI - REDE CONTAMINADA | D75: 1.1.2.3 | E75: Escavação mecanizada em solo acima de 3m | F75: m³ | G75: 1350 | H75: 44.117647 | I75: =H75*G75 -> 59558.824 | K75: 832.675 | L75: =G75-K75 -> 517.325 | V75: =$H75*K75 -> 36735.662 | W75: =$H75*L75 -> 22823.162 | X75: =$H75*M75 -> 0 | Y75: =$H75*N75 -> 0 | Z75: =$H75*O75 -> 0 | AA75: =$H75*P75 -> 0 | AB75: =$H75*Q75 -> 0 | AC75: =$H75*R75 -> 0 | ... AE75: =$H75*T75 -> 0 | AF75: =SUM(X75:AE75) -> 0 | AH75: =L75-SUM(M75:T75) -> 517.325 | AI75: =W75-SUM(X75:AE75) -> 22823.162
B76: SS-61/2025 | C76: IN-5250-20-001 - ETDI - REDE CONTAMINADA | D76: 1.1.2.8 | E76: Aterro manual com importação de areia , inclusive adensamento | F76: m³ | G76: 62 | H76: 281.2814 | I76: =H76*G76 -> 17439.447 | K76: 58.3 | L76: =G76-K76 -> 3.7 | M76: =L76 -> 3.7 | V76: =$H76*K76 -> 16398.706 | W76: =$H76*L76 -> 1040.7412 | X76: =$H76*M76 -> 1040.7412 | Y76: =$H76*N76 -> 0 | Z76: =$H76*O76 -> 0 | AA76: =$H76*P76 -> 0 | AB76: =$H76*Q76 -> 0 | AC76: =$H76*R76 -> 0 | ... AE76: =$H76*T76 -> 0 | AF76: =SUM(X76:AE76) -> 1040.7412 | AH76: =L76-SUM(M76:T76) -> 0 | AI76: =W76-SUM(X76:AE76) -> 0
B77: SS-61/2025 | C77: IN-5250-20-001 - ETDI - REDE CONTAMINADA | D77: 1.1.2.9 | E77: Aterro mecanizado sem fornecimento de solo | F77: m³ | G77: 745 | H77: 67.097751 | I77: =H77*G77 -> 49987.824 | K77: 743.797 | L77: =G77-K77 -> 1.203 | V77: =$H77*K77 -> 49907.106 | W77: =$H77*L77 -> 80.718594 | X77: =$H77*M77 -> 0 | Y77: =$H77*N77 -> 0 | Z77: =$H77*O77 -> 0 | AA77: =$H77*P77 -> 0 | AB77: =$H77*Q77 -> 0 | AC77: =$H77*R77 -> 0 | ... AE77: =$H77*T77 -> 0 | AF77: =SUM(X77:AE77) -> 0 | AH77: =L77-SUM(M77:T77) -> 1.203 | AI77: =W77-SUM(X77:AE77) -> 80.718594
B78: SS-61/2025 | C78: IN-5250-20-001 - ETDI - REDE CONTAMINADA | D78: 1.1.2.12 | E78: Transporte de material escavado, incluindo carga e descarga e espalhamento | F78: m³ | G78: 691.125 | H78: 90.646229 | I78: =H78*G78 -> 62647.875 | K78: 253.3 | L78: =G78-K78 -> 437.825 | V78: =$H78*K78 -> 22960.69 | W78: =$H78*L78 -> 39687.185 | X78: =$H78*M78 -> 0 | Y78: =$H78*N78 -> 0 | Z78: =$H78*O78 -> 0 | AA78: =$H78*P78 -> 0 | AB78: =$H78*Q78 -> 0 | AC78: =$H78*R78 -> 0 | ... AE78: =$H78*T78 -> 0 | AF78: =SUM(X78:AE78) -> 0 | AH78: =L78-SUM(M78:T78) -> 437.825 | AI78: =W78-SUM(X78:AE78) -> 39687.185
B79: SS-61/2025 | C79: IN-5250-20-001 - ETDI - REDE CONTAMINADA | D79: 1.1.3.1 | E79: Forma em chapa compensada plastificada | F79: m³ | G79: 3 | H79: 15728.69 | I79: =H79*G79 -> 47186.069 | K79: 0.73 | L79: =G79-K79 -> 2.27 | V79: =$H79*K79 -> 11481.943 | W79: =$H79*L79 -> 35704.126 | X79: =$H79*M79 -> 0 | Y79: =$H79*N79 -> 0 | Z79: =$H79*O79 -> 0 | AA79: =$H79*P79 -> 0 | AB79: =$H79*Q79 -> 0 | AC79: =$H79*R79 -> 0 | ... AE79: =$H79*T79 -> 0 | AF79: =SUM(X79:AE79) -> 0 | AH79: =L79-SUM(M79:T79) -> 2.27 | AI79: =W79-SUM(X79:AE79) -> 35704.126
B80: SS-61/2025 | C80: IN-5250-20-001 - ETDI - REDE CONTAMINADA | D80: 1.1.3.5 | E80: Armadura Aço CA-50 ou CA-60 | F80: kg | G80: 7051.59 | H80: 25.691751 | I80: =H80*G80 -> 181167.69 | K80: 5121.508 | L80: =G80-K80 -> 1930.082 | V80: =$H80*K80 -> 131580.51 | W80: =$H80*L80 -> 49587.185 | X80: =$H80*M80 -> 0 | Y80: =$H80*N80 -> 0 | Z80: =$H80*O80 -> 0 | AA80: =$H80*P80 -> 0 | AB80: =$H80*Q80 -> 0 | AC80: =$H80*R80 -> 0 | ... AE80: =$H80*T80 -> 0 | AF80: =SUM(X80:AE80) -> 0 | AH80: =L80-SUM(M80:T80) -> 1930.082 | AI80: =W80-SUM(X80:AE80) -> 49587.185
B81: SS-61/2025 | C81: IN-5250-20-001 - ETDI - REDE CONTAMINADA | D81: 1.1.3.7 | E81: Concreto fck 15 MPa | F81: m³ | G81: 8 | H81: 1248.9987 | I81: =H81*G81 -> 9991.9895 | K81: 0 | L81: =G81-K81 -> 8 | V81: =$H81*K81 -> 0 | W81: =$H81*L81 -> 9991.9895 | X81: =$H81*M81 -> 0 | Y81: =$H81*N81 -> 0 | Z81: =$H81*O81 -> 0 | AA81: =$H81*P81 -> 0 | AB81: =$H81*Q81 -> 0 | AC81: =$H81*R81 -> 0 | ... AE81: =$H81*T81 -> 0 | AF81: =SUM(X81:AE81) -> 0 | AH81: =L81-SUM(M81:T81) -> 8 | AI81: =W81-SUM(X81:AE81) -> 9991.9895
B82: SS-61/2025 | C82: IN-5250-20-001 - ETDI - REDE CONTAMINADA | D82: 1.1.3.9 | E82: Concreto estrutural fck 30 MPa | F82: m³ | G82: 21.9 | H82: 1703.4074 | I82: =H82*G82 -> 37304.623 | K82: 9.158 | L82: =G82-K82 -> 12.742 | V82: =$H82*K82 -> 15599.805 | W82: =$H82*L82 -> 21704.818 | X82: =$H82*M82 -> 0 | Y82: =$H82*N82 -> 0 | Z82: =$H82*O82 -> 0 | AA82: =$H82*P82 -> 0 | AB82: =$H82*Q82 -> 0 | AC82: =$H82*R82 -> 0 | ... AE82: =$H82*T82 -> 0 | AF82: =SUM(X82:AE82) -> 0 | AH82: =L82-SUM(M82:T82) -> 12.742 | AI82: =W82-SUM(X82:AE82) -> 21704.818
B83: SS-61/2025 | C83: IN-5250-20-001 - ETDI - REDE CONTAMINADA | D83: 1.1.3.10 | E83: Concreto estrutural fck 40 MPa | F83: m³ | G83: 23.5 | H83: 2157.2457 | I83: =H83*G83 -> 50695.273 | K83: 11.338 | L83: =G83-K83 -> 12.162 | V83: =$H83*K83 -> 24458.851 | W83: =$H83*L83 -> 26236.422 | X83: =$H83*M83 -> 0 | Y83: =$H83*N83 -> 0 | Z83: =$H83*O83 -> 0 | AA83: =$H83*P83 -> 0 | AB83: =$H83*Q83 -> 0 | AC83: =$H83*R83 -> 0 | ... AE83: =$H83*T83 -> 0 | AF83: =SUM(X83:AE83) -> 0 | AH83: =L83-SUM(M83:T83) -> 12.162 | AI83: =W83-SUM(X83:AE83) -> 26236.422
B84: SS-61/2025 | C84: IN-5250-20-001 - ETDI - REDE CONTAMINADA | D84: 1.1.12.1 | E84: Tubulação em ferro fundido qualquer diâmetro, inclusive conexões e acessórios | F84: kg | G84: 36059 | H84: 68.279073 | I84: =H84*G84 -> 2462075.1 | K84: 34058.64 | L84: =G84-K84 -> 2000.36 | V84: =$H84*K84 -> 2325492.4 | W84: =$H84*L84 -> 136582.73 | X84: =$H84*M84 -> 0 | Y84: =$H84*N84 -> 0 | Z84: =$H84*O84 -> 0 | AA84: =$H84*P84 -> 0 | AB84: =$H84*Q84 -> 0 | AC84: =$H84*R84 -> 0 | ... AE84: =$H84*T84 -> 0 | AF84: =SUM(X84:AE84) -> 0 | AH84: =L84-SUM(M84:T84) -> 2000.36 | AI84: =W84-SUM(X84:AE84) -> 136582.73
B85: SS-61/2025 | C85: IN-5250-20-001 - ETDI - REDE CONTAMINADA | D85: 1.1.12.3 | E85: Tampão articulado em ferro fundido, diâmetro 600 mm a 800 mm | F85: unid. | G85: 2 | H85: 796.99149 | I85: =H85*G85 -> 1593.983 | K85: 1.8 | L85: =G85-K85 -> 0.2 | V85: =$H85*K85 -> 1434.5847 | W85: =$H85*L85 -> 159.3983 | X85: =$H85*M85 -> 0 | Y85: =$H85*N85 -> 0 | Z85: =$H85*O85 -> 0 | AA85: =$H85*P85 -> 0 | AB85: =$H85*Q85 -> 0 | AC85: =$H85*R85 -> 0 | ... AE85: =$H85*T85 -> 0 | AF85: =SUM(X85:AE85) -> 0 | AH85: =L85-SUM(M85:T85) -> 0.2 | AI85: =W85-SUM(X85:AE85) -> 159.3983
B86: SS-61/2025 | C86: IN-5250-20-001 - ETDI - REDE CONTAMINADA | D86: 1.2.14.7 | E86: Pintura de identificação de equipamentos e ou tubulação conforme Norma | F86: un | G86: 45 | H86: 238.84378 | I86: =H86*G86 -> 10747.97 | K86: 22 | L86: =G86-K86 -> 23 | V86: =$H86*K86 -> 5254.5632 | W86: =$H86*L86 -> 5493.407 | X86: =$H86*M86 -> 0 | Y86: =$H86*N86 -> 0 | Z86: =$H86*O86 -> 0 | AA86: =$H86*P86 -> 0 | AB86: =$H86*Q86 -> 0 | AC86: =$H86*R86 -> 0 | ... AE86: =$H86*T86 -> 0 | AF86: =SUM(X86:AE86) -> 0 | AH86: =L86-SUM(M86:T86) -> 23 | AI86: =W86-SUM(X86:AE86) -> 5493.407
B87: SS-61/2025 | C87: IN-5250-20-001 - ETDI - REDE CONTAMINADA | D87: 1.2.23.1 | E87: Serviço de montagem de estrutura | F87: kg | G87: 7752.2 | H87: 24.436627 | I87: =H87*G87 -> 189437.62 | K87: 7752.2 | L87: =G87-K87 -> 0 | V87: =$H87*K87 -> 189437.62 | W87: =$H87*L87 -> 0 | X87: =$H87*M87 -> 0 | Y87: =$H87*N87 -> 0 | Z87: =$H87*O87 -> 0 | AA87: =$H87*P87 -> 0 | AB87: =$H87*Q87 -> 0 | AC87: =$H87*R87 -> 0 | ... AE87: =$H87*T87 -> 0 | AF87: =SUM(X87:AE87) -> 0 | AH87: =L87-SUM(M87:T87) -> 0 | AI87: =W87-SUM(X87:AE87) -> 0
B88: SS-61/2025 | C88: IN-5250-20-001 - ETDI - REDE CONTAMINADA | D88: 1.7.2.1 | E88: Serviços Técnicos Especializados de Engenharia - Hora Normal | F88: Hs | G88: 62 | H88: 254.25 | I88: =H88*G88 -> 15763.5 | K88: 16.296 | L88: =G88-K88 -> 45.704 | V88: =$H88*K88 -> 4143.258 | W88: =$H88*L88 -> 11620.242 | X88: =$H88*M88 -> 0 | Y88: =$H88*N88 -> 0 | Z88: =$H88*O88 -> 0 | AA88: =$H88*P88 -> 0 | AB88: =$H88*Q88 -> 0 | AC88: =$H88*R88 -> 0 | ... AE88: =$H88*T88 -> 0 | AF88: =SUM(X88:AE88) -> 0 | AH88: =L88-SUM(M88:T88) -> 45.704 | AI88: =W88-SUM(X88:AE88) -> 11620.242
B89: SS-62/2025 | C89: IN - 5250-25-005 - ETDI - FRENTE 01 - BOMBAS DO PPI - ELÉTRICA | I89: =SUM(I90:I120) -> 1007169.5 | V89: =SUM(V90:V120) -> 818006.17 | W89: =SUM(W90:W120) -> 190185.34 | X89: =SUM(X90:X120) -> 0 | Y89: =SUM(Y90:Y120) -> 73329.335 | Z89: =SUM(Z90:Z120) -> 0 | AA89: =SUM(AA90:AA120) -> 0 | AB89: =SUM(AB90:AB120) -> 0 | AC89: =SUM(AC90:AC120) -> 0 | ... AF89: =SUM(AF90:AF120) -> 73329.335
B90: SS-62/2025 | C90: IN - 5250-25-005 - ETDI - FRENTE 01 - BOMBAS DO PPI - ELÉTRICA | D90: 1.3.1.5 | E90: Instalação de motor elétrico acima de 100 cv | F90: un | G90: 2 | H90: 5871.6704 | I90: =H90*G90 -> 11743.341 | K90: 0 | L90: =G90-K90 -> 2 | N90: =G90 -> 2 | V90: =$H90*K90 -> 0 | W90: =$H90*L90 -> 11743.341 | X90: =$H90*M90 -> 0 | Y90: =$H90*N90 -> 11743.341 | Z90: =$H90*O90 -> 0 | AA90: =$H90*P90 -> 0 | AB90: =$H90*Q90 -> 0 | AC90: =$H90*R90 -> 0 | ... AE90: =$H90*T90 -> 0 | AF90: =SUM(X90:AE90) -> 11743.341 | AH90: =L90-SUM(M90:T90) -> 0 | AI90: =W90-SUM(X90:AE90) -> 0
B91: SS-62/2025 | C91: IN - 5250-25-005 - ETDI - FRENTE 01 - BOMBAS DO PPI - ELÉTRICA | D91: 1.3.2.3 | E91: Instalação de motor elétrico acima de 300 cv | F91: un | G91: 2 | H91: 12404.017 | I91: =H91*G91 -> 24808.034 | K91: 0 | L91: =G91-K91 -> 2 | N91: =G91 -> 2 | V91: =$H91*K91 -> 0 | W91: =$H91*L91 -> 24808.034 | X91: =$H91*M91 -> 0 | Y91: =$H91*N91 -> 24808.034 | Z91: =$H91*O91 -> 0 | AA91: =$H91*P91 -> 0 | AB91: =$H91*Q91 -> 0 | AC91: =$H91*R91 -> 0 | ... AE91: =$H91*T91 -> 0 | AF91: =SUM(X91:AE91) -> 24808.034 | AH91: =L91-SUM(M91:T91) -> 0 | AI91: =W91-SUM(X91:AE91) -> 0
B92: SS-62/2025 | C92: IN - 5250-25-005 - ETDI - FRENTE 01 - BOMBAS DO PPI - ELÉTRICA | D92: 1.3.2.4 | E92: Remoção de motor elétrico acima de 300 cv | F92: un | G92: 2 | H92: 3096.8726 | I92: =H92*G92 -> 6193.7452 | K92: 0 | L92: =G92-K92 -> 2 | N92: =G92 -> 2 | V92: =$H92*K92 -> 0 | W92: =$H92*L92 -> 6193.7452 | X92: =$H92*M92 -> 0 | Y92: =$H92*N92 -> 6193.7452 | Z92: =$H92*O92 -> 0 | AA92: =$H92*P92 -> 0 | AB92: =$H92*Q92 -> 0 | AC92: =$H92*R92 -> 0 | ... AE92: =$H92*T92 -> 0 | AF92: =SUM(X92:AE92) -> 6193.7452 | AH92: =L92-SUM(M92:T92) -> 0 | AI92: =W92-SUM(X92:AE92) -> 0
B93: SS-62/2025 | C93: IN - 5250-25-005 - ETDI - FRENTE 01 - BOMBAS DO PPI - ELÉTRICA | D93: 1.3.6.1 | E93: Instalação e ligação de coluna de painel elétrico de tensão até 1 kV | F93: un | G93: 2 | H93: 6308.4785 | I93: =H93*G93 -> 12616.957 | K93: 0 | L93: =G93-K93 -> 2 | N93: =G93 -> 2 | V93: =$H93*K93 -> 0 | W93: =$H93*L93 -> 12616.957 | X93: =$H93*M93 -> 0 | Y93: =$H93*N93 -> 12616.957 | Z93: =$H93*O93 -> 0 | AA93: =$H93*P93 -> 0 | AB93: =$H93*Q93 -> 0 | AC93: =$H93*R93 -> 0 | ... AE93: =$H93*T93 -> 0 | AF93: =SUM(X93:AE93) -> 12616.957 | AH93: =L93-SUM(M93:T93) -> 0 | AI93: =W93-SUM(X93:AE93) -> 0
B94: SS-62/2025 | C94: IN - 5250-25-005 - ETDI - FRENTE 01 - BOMBAS DO PPI - ELÉTRICA | D94: 1.3.7.1 | E94: Instalação de painel elétrico tipo sobrepor de até 32 circuitos monofásicos ou equivalente | F94: un | G94: 1 | H94: 2609.178 | I94: =H94*G94 -> 2609.178 | K94: 1 | L94: =G94-K94 -> 0 | V94: =$H94*K94 -> 2609.178 | W94: =$H94*L94 -> 0 | X94: =$H94*M94 -> 0 | Y94: =$H94*N94 -> 0 | Z94: =$H94*O94 -> 0 | AA94: =$H94*P94 -> 0 | AB94: =$H94*Q94 -> 0 | AC94: =$H94*R94 -> 0 | ... AE94: =$H94*T94 -> 0 | AF94: =SUM(X94:AE94) -> 0 | AH94: =L94-SUM(M94:T94) -> 0 | AI94: =W94-SUM(X94:AE94) -> 0
B95: SS-62/2025 | C95: IN - 5250-25-005 - ETDI - FRENTE 01 - BOMBAS DO PPI - ELÉTRICA | D95: 1.3.12.1 | E95: Instalação de caixa de terminação | F95: un | G95: 4 | H95: 990.99922 | I95: =H95*G95 -> 3963.9969 | K95: 0 | L95: =G95-K95 -> 4 | V95: =$H95*K95 -> 0 | W95: =$H95*L95 -> 3963.9969 | X95: =$H95*M95 -> 0 | Y95: =$H95*N95 -> 0 | Z95: =$H95*O95 -> 0 | AA95: =$H95*P95 -> 0 | AB95: =$H95*Q95 -> 0 | AC95: =$H95*R95 -> 0 | ... AE95: =$H95*T95 -> 0 | AF95: =SUM(X95:AE95) -> 0 | AH95: =L95-SUM(M95:T95) -> 4 | AI95: =W95-SUM(X95:AE95) -> 3963.9969
B96: SS-62/2025 | C96: IN - 5250-25-005 - ETDI - FRENTE 01 - BOMBAS DO PPI - ELÉTRICA | D96: 1.3.17.3 | E96: Instalação de luminária/projetor em ambiente industrial | F96: un | G96: 2 | H96: 461.94016 | I96: =H96*G96 -> 923.88033 | K96: 2 | L96: =G96-K96 -> 0 | V96: =$H96*K96 -> 923.88033 | W96: =$H96*L96 -> 0 | X96: =$H96*M96 -> 0 | Y96: =$H96*N96 -> 0 | Z96: =$H96*O96 -> 0 | AA96: =$H96*P96 -> 0 | AB96: =$H96*Q96 -> 0 | AC96: =$H96*R96 -> 0 | ... AE96: =$H96*T96 -> 0 | AF96: =SUM(X96:AE96) -> 0 | AH96: =L96-SUM(M96:T96) -> 0 | AI96: =W96-SUM(X96:AE96) -> 0
B97: SS-62/2025 | C97: IN - 5250-25-005 - ETDI - FRENTE 01 - BOMBAS DO PPI - ELÉTRICA | D97: 1.3.19.1 | E97: Instalação de botoeira ou chave para comando local de cargas elétricas | F97: un | G97: 2 | H97: 270.4702 | I97: =H97*G97 -> 540.9404 | K97: 0 | L97: =G97-K97 -> 2 | V97: =$H97*K97 -> 0 | W97: =$H97*L97 -> 540.9404 | X97: =$H97*M97 -> 0 | Y97: =$H97*N97 -> 0 | Z97: =$H97*O97 -> 0 | AA97: =$H97*P97 -> 0 | AB97: =$H97*Q97 -> 0 | AC97: =$H97*R97 -> 0 | ... AE97: =$H97*T97 -> 0 | AF97: =SUM(X97:AE97) -> 0 | AH97: =L97-SUM(M97:T97) -> 2 | AI97: =W97-SUM(X97:AE97) -> 540.9404
B98: SS-62/2025 | C98: IN - 5250-25-005 - ETDI - FRENTE 01 - BOMBAS DO PPI - ELÉTRICA | D98: 1.3.20.1 | E98: Instalação de eletrodutos aparentes em ambiente industrial até 1 1/2" de diâmetro | F98: m | G98: 160 | H98: 214.31315 | I98: =H98*G98 -> 34290.105 | K98: 120 | L98: =G98-K98 -> 40 | V98: =$H98*K98 -> 25717.579 | W98: =$H98*L98 -> 8572.5262 | X98: =$H98*M98 -> 0 | Y98: =$H98*N98 -> 0 | Z98: =$H98*O98 -> 0 | AA98: =$H98*P98 -> 0 | AB98: =$H98*Q98 -> 0 | AC98: =$H98*R98 -> 0 | ... AE98: =$H98*T98 -> 0 | AF98: =SUM(X98:AE98) -> 0 | AH98: =L98-SUM(M98:T98) -> 40 | AI98: =W98-SUM(X98:AE98) -> 8572.5262
B99: SS-62/2025 | C99: IN - 5250-25-005 - ETDI - FRENTE 01 - BOMBAS DO PPI - ELÉTRICA | D99: 1.3.20.2 | E99: Instalação de eletrodutos aparentes em ambiente industrial acima de 1 1/2" até 2" de diâmetro | F99: m | G99: 105 | H99: 300.03842 | I99: =H99*G99 -> 31504.034 | K99: 71.3 | L99: =G99-K99 -> 33.7 | V99: =$H99*K99 -> 21392.739 | W99: =$H99*L99 -> 10111.295 | X99: =$H99*M99 -> 0 | Y99: =$H99*N99 -> 0 | Z99: =$H99*O99 -> 0 | AA99: =$H99*P99 -> 0 | AB99: =$H99*Q99 -> 0 | AC99: =$H99*R99 -> 0 | ... AE99: =$H99*T99 -> 0 | AF99: =SUM(X99:AE99) -> 0 | AH99: =L99-SUM(M99:T99) -> 33.7 | AI99: =W99-SUM(X99:AE99) -> 10111.295
B100: SS-62/2025 | C100: IN - 5250-25-005 - ETDI - FRENTE 01 - BOMBAS DO PPI - ELÉTRICA | D100: 1.3.20.3 | E100: Instalação de eletrodutos aparentes em ambiente industrual acima de 2" até 4" de diâmetro | F100: m | G100: 103 | H100: 175.49711 | I100: =H100*G100 -> 18076.202 | K100: 41 | L100: =G100-K100 -> 62 | V100: =$H100*K100 -> 7195.3813 | W100: =$H100*L100 -> 10880.821 | X100: =$H100*M100 -> 0 | Y100: =$H100*N100 -> 0 | Z100: =$H100*O100 -> 0 | AA100: =$H100*P100 -> 0 | AB100: =$H100*Q100 -> 0 | AC100: =$H100*R100 -> 0 | ... AE100: =$H100*T100 -> 0 | AF100: =SUM(X100:AE100) -> 0 | AH100: =L100-SUM(M100:T100) -> 62 | AI100: =W100-SUM(X100:AE100) -> 10880.821
B101: SS-62/2025 | C101: IN - 5250-25-005 - ETDI - FRENTE 01 - BOMBAS DO PPI - ELÉTRICA | D101: 1.3.23.1 | E101: Instalação de eletrodutos rígidos subterrâneos até 2" de diâmetro | F101: m | G101: 600 | H101: 141.94999 | I101: =H101*G101 -> 85169.993 | K101: 509.001 | L101: =G101-K101 -> 90.999 | V101: =$H101*K101 -> 72252.686 | W101: =$H101*L101 -> 12917.307 | X101: =$H101*M101 -> 0 | Y101: =$H101*N101 -> 0 | Z101: =$H101*O101 -> 0 | AA101: =$H101*P101 -> 0 | AB101: =$H101*Q101 -> 0 | AC101: =$H101*R101 -> 0 | ... AE101: =$H101*T101 -> 0 | AF101: =SUM(X101:AE101) -> 0 | AH101: =L101-SUM(M101:T101) -> 90.999 | AI101: =W101-SUM(X101:AE101) -> 12917.307
B102: SS-62/2025 | C102: IN - 5250-25-005 - ETDI - FRENTE 01 - BOMBAS DO PPI - ELÉTRICA | D102: 1.3.23.2 | E102: Instalação de eletrodutos rígidos subterrâneos acima de 2" até 4" de diâmetro | F102: m | G102: 450 | H102: 182.20933 | I102: =H102*G102 -> 81994.199 | K102: 386.001 | L102: =G102-K102 -> 63.999 | V102: =$H102*K102 -> 70332.984 | W102: =$H102*L102 -> 11661.215 | X102: =$H102*M102 -> 0 | Y102: =$H102*N102 -> 0 | Z102: =$H102*O102 -> 0 | AA102: =$H102*P102 -> 0 | AB102: =$H102*Q102 -> 0 | AC102: =$H102*R102 -> 0 | ... AE102: =$H102*T102 -> 0 | AF102: =SUM(X102:AE102) -> 0 | AH102: =L102-SUM(M102:T102) -> 63.999 | AI102: =W102-SUM(X102:AE102) -> 11661.215
...

Sheet Planilha3
A1: Verificar executados
A3: SS-1/2026 | B3: Adequação Escadas de Marinheiro - Execução - UN 01,102,108,109,209 - UDAV 01/02
A4: SS-2/2026 | B4: IN-5250-24-092 - PT-200 - Escavação Manual para Pré Furos e Fundação
A5: SS-36/2026 | B5: Manutenção Civil - Linha do Flare na Av. 8
A6: SS-44/2026 | B6: IN - 5250-24-085 - Phase-Out do Diesel S500 - Mudança 2.1 - Fabricação (Tubovias)
A7: SS-60/2025 | B7: IN-5250-25-014 - ETDI - DESARENADOR
A8: SS-61/2025 | B8: IN-5250-20-001 - ETDI - REDE CONTAMINADA
A9: SS-62/2025 | B9: IN - 5250-25-005 - ETDI - FRENTE 01 - BOMBAS DO PPI - ELÉTRICA
A10: SS-66/2026 | B10: CALDEIRAS 0121-F-001 ABC - FUNDAÇÃO PARA GRUA
A11: SS-73/2025 | B11: IN - 5250-20-001 - ETDI - BOMBAS DO PPI - CIVIL
A12: SS-74/2025 | B12: IN-5250-25-015 - ETDI - CONTAMINADA FASE 2 - CIVIL
A13: SS-79/2026 | B13: UNIDADE 47 - TANQUE DE ÁGUA ÁCIDA
A14: SS-94/2025 | B14: IN - 5250-20-001 - ETDI - BOMBAS DO PPI - MECANICA
... A16: SS-97/2025 | B16: IN - 5250-25-011 - Melhoria acesso bloco P 27-TQ-01 K e M - Montagem

Sheet CRONO BENS
K2: FISICO_QUANTIDADES | W2: FINANCEIRO_VALOR (R$)
K3: Medido | L3: Saldo | M3: 46113 | N3: 46143 | O3: 46174 | P3: 46204 | Q3: 46235 | R3: 46266 | S3: 46296 | T3: 46327 | U3: 46357 | W3: Acum | X3: Saldo | Y3: 46143 | Z3: 46174 | AA3: 46204 | AB3: 46235 | AC3: 46266 | AD3: 46296 | AE3: 46327 | AF3: 46357 | AG3: TOTAL MAIO A DEZ/2026 | AI3: CONF.FIS | AJ3: CONF.R$
B4: SS | C4: DESCRIÇÃO-SS | D4: ITEM | E4: DESCRIÇÃO-ITEM | F4: UN | G4: Qtd | H4: PREÇO UNITÁRIO (R$) | I4: PREÇO TOTAL (R$)
C6: FORNECIMENTO DE BENS - TOTAL GERAL | W6: =SUM(W7,W10,W14,W16,W19,W23,W27,W30,W37,W39,W41,W61) -> 928949.64 | X6: =SUM(X7,X10,X14,X16,X19,X23,X27,X30,X37,X39,X41,X61) -> 3971639.9 | Y6: =SUM(Y7,Y10,Y14,Y16,Y19,Y23,Y27,Y30,Y37,Y39,Y41,Y61) -> 566418.96 | Z6: =SUM(Z7,Z10,Z14,Z16,Z19,Z23,Z27,Z30,Z37,Z39,Z41,Z61) -> 1413110.6 | AA6: =SUM(AA7,AA10,AA14,AA16,AA19,AA23,AA27,AA30,AA37,AA39,AA41,AA61) -> 1039652.3 | AB6: =SUM(AB7,AB10,AB14,AB16,AB19,AB23,AB27,AB30,AB37,AB39,AB41,AB61) -> 970841.89 | AC6: =SUM(AC7,AC10,AC14,AC16,AC19,AC23,AC27,AC30,AC37,AC39,AC41,AC61) -> 0 | AD6: =SUM(AD7,AD10,AD14,AD16,AD19,AD23,AD27,AD30,AD37,AD39,AD41,AD61) -> 0 | ... AG6: =SUM(AG7,AG10,AG14,AG16,AG19,AG23,AG27,AG30,AG37,AG39,AG41,AG61) -> 3990023.8
B7: SS-184/2026 | C7: Rede Envelopada - Armazéns S5 x S6 - Bens | I7: =SUM(I8:I9) -> 31206.549 | W7: =SUM(W8:W9) -> 0 | X7: =SUM(X8:X9) -> 31206.549 | Y7: =SUM(Y8:Y9) -> 0 | Z7: =SUM(Z8:Z9) -> 31206.549 | AA7: =SUM(AA8:AA9) -> 0 | AB7: =SUM(AB8:AB9) -> 0 | AC7: =SUM(AC8:AC9) -> 0 | AD7: =SUM(AD8:AD9) -> 0 | ... AG7: =SUM(AG8:AG9) -> 31206.549
B8: SS-184/2026 | C8: Rede Envelopada - Armazéns S5 x S6 - Bens | D8: 2.2.1.155 | E8: CABO EL. NU DE COBRE CL.2A 70MM² | F8: M | G8: 200 | H8: 42.655855 | I8: =H8*G8 -> 8531.1711 | L8: =G8-K8 -> 200 | O8: =G8 -> 200 | W8: =$H8*K8 -> 0 | X8: =$H8*L8 -> 8531.1711 | Y8: =$H8*N8 -> 0 | Z8: =$H8*O8 -> 8531.1711 | AA8: =$H8*P8 -> 0 | AB8: =$H8*Q8 -> 0 | AC8: =$H8*R8 -> 0 | AD8: =$H8*S8 -> 0 | AE8: =$H8*T8 -> 0 | AF8: =$H8*U8 -> 0 | AG8: =SUM(Y8:AF8) -> 8531.1711 | AI8: =L8-SUM(M8:U8) -> 0 | AJ8: =X8-SUM(Y8:AF8) -> 0
B9: SS-184/2026 | C9: Rede Envelopada - Armazéns S5 x S6 - Bens | D9: 2.2.3.6 | E9: Aço carbono com revestimento protetor de zinco (galvanizado a fogo)/ DN 4" | F9: M | G9: 187 | H9: 121.25871 | I9: =H9*G9 -> 22675.378 | L9: =G9-K9 -> 187 | O9: =G9 -> 187 | W9: =$H9*K9 -> 0 | X9: =$H9*L9 -> 22675.378 | Y9: =$H9*N9 -> 0 | Z9: =$H9*O9 -> 22675.378 | AA9: =$H9*P9 -> 0 | AB9: =$H9*Q9 -> 0 | AC9: =$H9*R9 -> 0 | AD9: =$H9*S9 -> 0 | AE9: =$H9*T9 -> 0 | AF9: =$H9*U9 -> 0 | AG9: =SUM(Y9:AF9) -> 22675.378 | AI9: =L9-SUM(M9:U9) -> 0 | AJ9: =X9-SUM(Y9:AF9) -> 0
B10: SS-152/2026 | C10: U-623 - RELOCAÇÃO TUBULAÇÃO RACE - BENS | I10: =SUM(I11:I13) -> 192523.85 | W10: =SUM(W11:W13) -> 0 | X10: =SUM(X11:X13) -> 192523.85 | Y10: =SUM(Y11:Y13) -> 0 | Z10: =SUM(Z11:Z13) -> 192523.85 | AA10: =SUM(AA11:AA13) -> 0 | AB10: =SUM(AB11:AB13) -> 0 | AC10: =SUM(AC11:AC13) -> 0 | AD10: =SUM(AD11:AD13) -> 0 | ... AG10: =SUM(AG11:AG13) -> 192523.85
B11: SS-152/2026 | C11: U-623 - RELOCAÇÃO TUBULAÇÃO RACE - BENS | D11: 2.1.2.1 | E11: Tubos de condução em aço carbono | F11: KG | G11: 3209.502 | H11: 36.384822 | I11: =H11*G11 -> 116777.16 | L11: =G11-K11 -> 3209.502 | O11: =L11 -> 3209.502 | W11: =$H11*K11 -> 0 | X11: =$H11*L11 -> 116777.16 | Y11: =$H11*N11 -> 0 | Z11: =$H11*O11 -> 116777.16 | AA11: =$H11*P11 -> 0 | AB11: =$H11*Q11 -> 0 | AC11: =$H11*R11 -> 0 | AD11: =$H11*S11 -> 0 | AE11: =$H11*T11 -> 0 | AF11: =$H11*U11 -> 0 | AG11: =SUM(Y11:AF11) -> 116777.16 | AI11: =L11-SUM(M11:U11) -> 0 | AJ11: =X11-SUM(Y11:AF11) -> 0
B12: SS-152/2026 | C12: U-623 - RELOCAÇÃO TUBULAÇÃO RACE - BENS | D12: 2.1.3.1 | E12: Acessórios em aço carbono | F12: KG | G12: 549.134 | H12: 132.51219 | I12: =H12*G12 -> 72766.951 | L12: =G12-K12 -> 549.134 | O12: =L12 -> 549.134 | W12: =$H12*K12 -> 0 | X12: =$H12*L12 -> 72766.951 | Y12: =$H12*N12 -> 0 | Z12: =$H12*O12 -> 72766.951 | AA12: =$H12*P12 -> 0 | AB12: =$H12*Q12 -> 0 | AC12: =$H12*R12 -> 0 | AD12: =$H12*S12 -> 0 | AE12: =$H12*T12 -> 0 | AF12: =$H12*U12 -> 0 | AG12: =SUM(Y12:AF12) -> 72766.951 | AI12: =L12-SUM(M12:U12) -> 0 | AJ12: =X12-SUM(Y12:AF12) -> 0
B13: SS-152/2026 | C13: U-623 - RELOCAÇÃO TUBULAÇÃO RACE - BENS | D13: 2.1.4.1 | E13: Material de referência ASTM A193 Gr B7 | F13: KG | G13: 54.88 | H13: 54.295645 | I13: =H13*G13 -> 2979.745 | L13: =G13-K13 -> 54.88 | O13: =L13 -> 54.88 | W13: =$H13*K13 -> 0 | X13: =$H13*L13 -> 2979.745 | Y13: =$H13*N13 -> 0 | Z13: =$H13*O13 -> 2979.745 | AA13: =$H13*P13 -> 0 | AB13: =$H13*Q13 -> 0 | AC13: =$H13*R13 -> 0 | AD13: =$H13*S13 -> 0 | AE13: =$H13*T13 -> 0 | AF13: =$H13*U13 -> 0 | AG13: =SUM(Y13:AF13) -> 2979.745 | AI13: =L13-SUM(M13:U13) -> 0 | AJ13: =X13-SUM(Y13:AF13) -> 0
B14: SS-139/2026 | C14: UN-623 - CASA DE QUÍMICOS - FORNECIMENTO DE BENS | I14: =SUM(I15:I15) -> 3597.6295 | W14: =SUM(W15:W15) -> 0 | X14: =SUM(X15:X15) -> 3597.6295 | Y14: =SUM(Y15:Y15) -> 0 | Z14: =SUM(Z15:Z15) -> 3597.6295 | AA14: =SUM(AA15:AA15) -> 0 | AB14: =SUM(AB15:AB15) -> 0 | AC14: =SUM(AC15:AC15) -> 0 | AD14: =SUM(AD15:AD15) -> 0 | ... AG14: =SUM(AG15:AG15) -> 3597.6295
B15: SS-139/2026 | C15: UN-623 - CASA DE QUÍMICOS - FORNECIMENTO DE BENS | D15: 2.1.4.1 | E15: Material de referência ASTM A193 Gr B7 | F15: KG | G15: 66.26 | H15: 54.295645 | I15: =H15*G15 -> 3597.6295 | L15: =G15-K15 -> 66.26 | O15: =L15 -> 66.26 | W15: =$H15*K15 -> 0 | X15: =$H15*L15 -> 3597.6295 | Y15: =$H15*N15 -> 0 | Z15: =$H15*O15 -> 3597.6295 | AA15: =$H15*P15 -> 0 | AB15: =$H15*Q15 -> 0 | AC15: =$H15*R15 -> 0 | AD15: =$H15*S15 -> 0 | AE15: =$H15*T15 -> 0 | AF15: =$H15*U15 -> 0 | AG15: =SUM(Y15:AF15) -> 3597.6295 | AI15: =L15-SUM(M15:U15) -> 0 | AJ15: =X15-SUM(Y15:AF15) -> 0
B16: SS-128/2026 | C16: FORNECIMENTO DE BENS - ALIMENTAÇÕES PROVISÓRIAS TAF - SDCD UDAV II | I16: =SUM(I17:I18) -> 777.83798 | W16: =SUM(W17:W18) -> 0 | X16: =SUM(X17:X18) -> 777.83798 | Y16: =SUM(Y17:Y18) -> 0 | Z16: =SUM(Z17:Z18) -> 777.83798 | AA16: =SUM(AA17:AA18) -> 0 | AB16: =SUM(AB17:AB18) -> 0 | AC16: =SUM(AC17:AC18) -> 0 | AD16: =SUM(AD17:AD18) -> 0 | ... AG16: =SUM(AG17:AG18) -> 777.83798
B17: SS-128/2026 | C17: FORNECIMENTO DE BENS - ALIMENTAÇÕES PROVISÓRIAS TAF - SDCD UDAV II | D17: 2.2.1.35 | E17: Cabo potência até 1kV (de 3x até 4x) de 2,5mm² a 4,0 mm², EPR/HEPR, ST1/ST2 | F17: M | G17: 40 | H17: 9.1244181 | I17: =H17*G17 -> 364.97672 | L17: =G17-K17 -> 40 | O17: =G17 -> 40 | W17: =$H17*K17 -> 0 | X17: =$H17*L17 -> 364.97672 | Y17: =$H17*N17 -> 0 | Z17: =$H17*O17 -> 364.97672 | AA17: =$H17*P17 -> 0 | AB17: =$H17*Q17 -> 0 | AC17: =$H17*R17 -> 0 | AD17: =$H17*S17 -> 0 | AE17: =$H17*T17 -> 0 | AF17: =$H17*U17 -> 0 | AG17: =SUM(Y17:AF17) -> 364.97672 | AI17: =L17-SUM(M17:U17) -> 0 | AJ17: =X17-SUM(Y17:AF17) -> 0
B18: SS-128/2026 | C18: FORNECIMENTO DE BENS - ALIMENTAÇÕES PROVISÓRIAS TAF - SDCD UDAV II | D18: 2.2.1.158 | E18: CABO EL. NU DE COBRE CL.2C 16MM² | F18: M | G18: 20 | H18: 20.643063 | I18: =H18*G18 -> 412.86126 | L18: =G18-K18 -> 20 | O18: =G18 -> 20 | W18: =$H18*K18 -> 0 | X18: =$H18*L18 -> 412.86126 | Y18: =$H18*N18 -> 0 | Z18: =$H18*O18 -> 412.86126 | AA18: =$H18*P18 -> 0 | AB18: =$H18*Q18 -> 0 | AC18: =$H18*R18 -> 0 | AD18: =$H18*S18 -> 0 | AE18: =$H18*T18 -> 0 | AF18: =$H18*U18 -> 0 | AG18: =SUM(Y18:AF18) -> 412.86126 | AI18: =L18-SUM(M18:U18) -> 0 | AJ18: =X18-SUM(Y18:AF18) -> 0
B19: SS-108/2026 | C19: IN - 5250-24-085 - Phase-Out do Diesel S500 - Mudança 4.1 - Aquisição de Bens (Tubovias) | I19: =SUM(I20:I22) -> 162194.8 | W19: =SUM(W20:W22) -> 0 | X19: =SUM(X20:X22) -> 162194.8 | Y19: =SUM(Y20:Y22) -> 0 | Z19: =SUM(Z20:Z22) -> 162194.8 | AA19: =SUM(AA20:AA22) -> 0 | AB19: =SUM(AB20:AB22) -> 0 | AC19: =SUM(AC20:AC22) -> 0 | AD19: =SUM(AD20:AD22) -> 0 | ... AG19: =SUM(AG20:AG22) -> 162194.8
B20: SS-108/2026 | C20: IN - 5250-24-085 - Phase-Out do Diesel S500 - Mudança 4.1 - Aquisição de Bens (Tubovias) | D20: 2.1.1.1 | E20: Chapas e perfis estruturais em aço carbono | F20: KG | G20: 193.1593 | H20: 26.960219 | I20: =H20*G20 -> 5207.6171 | L20: =G20-K20 -> 193.1593 | O20: =G20 -> 193.1593 | W20: =$H20*K20 -> 0 | X20: =$H20*L20 -> 5207.6171 | Y20: =$H20*N20 -> 0 | Z20: =$H20*O20 -> 5207.6171 | AA20: =$H20*P20 -> 0 | AB20: =$H20*Q20 -> 0 | AC20: =$H20*R20 -> 0 | AD20: =$H20*S20 -> 0 | AE20: =$H20*T20 -> 0 | AF20: =$H20*U20 -> 0 | AG20: =SUM(Y20:AF20) -> 5207.6171 | AI20: =L20-SUM(M20:U20) -> 0 | AJ20: =X20-SUM(Y20:AF20) -> 0
B21: SS-108/2026 | C21: IN - 5250-24-085 - Phase-Out do Diesel S500 - Mudança 4.1 - Aquisição de Bens (Tubovias) | D21: 2.1.2.1 | E21: Tubos de condução em aço carbono | F21: KG | G21: 2417.8148 | H21: 36.384822 | I21: =H21*G21 -> 87971.761 | L21: =G21-K21 -> 2417.8148 | O21: =G21 -> 2417.8148 | W21: =$H21*K21 -> 0 | X21: =$H21*L21 -> 87971.761 | Y21: =$H21*N21 -> 0 | Z21: =$H21*O21 -> 87971.761 | AA21: =$H21*P21 -> 0 | AB21: =$H21*Q21 -> 0 | AC21: =$H21*R21 -> 0 | AD21: =$H21*S21 -> 0 | AE21: =$H21*T21 -> 0 | AF21: =$H21*U21 -> 0 | AG21: =SUM(Y21:AF21) -> 87971.761 | AI21: =L21-SUM(M21:U21) -> 0 | AJ21: =X21-SUM(Y21:AF21) -> 0
B22: SS-108/2026 | C22: IN - 5250-24-085 - Phase-Out do Diesel S500 - Mudança 4.1 - Aquisição de Bens (Tubovias) | D22: 2.1.3.1 | E22: Acessórios em aço carbono | F22: KG | G22: 520.82316 | H22: 132.51219 | I22: =H22*G22 -> 69015.419 | L22: =G22-K22 -> 520.82316 | O22: =G22 -> 520.82316 | W22: =$H22*K22 -> 0 | X22: =$H22*L22 -> 69015.419 | Y22: =$H22*N22 -> 0 | Z22: =$H22*O22 -> 69015.419 | AA22: =$H22*P22 -> 0 | AB22: =$H22*Q22 -> 0 | AC22: =$H22*R22 -> 0 | AD22: =$H22*S22 -> 0 | AE22: =$H22*T22 -> 0 | AF22: =$H22*U22 -> 0 | AG22: =SUM(Y22:AF22) -> 69015.419 | AI22: =L22-SUM(M22:U22) -> 0 | AJ22: =X22-SUM(Y22:AF22) -> 0
B23: SS-43/2026 | C23: IN - 5250-24-085 - Phase-Out do Diesel S500 - Mudança 2.1 - Aquisição de Bens (Tubovias) | I23: =SUM(I24:I26) -> 606944.81 | W23: =SUM(W24:W26) -> 559174.06 | X23: =SUM(X24:X26) -> 47770.757 | Y23: =SUM(Y24:Y26) -> 47770.757 | Z23: =SUM(Z24:Z26) -> 0 | AA23: =SUM(AA24:AA26) -> 0 | AB23: =SUM(AB24:AB26) -> 0 | AC23: =SUM(AC24:AC26) -> 0 | AD23: =SUM(AD24:AD26) -> 0 | ... AG23: =SUM(AG24:AG26) -> 47770.757
B24: SS-43/2026 | C24: IN - 5250-24-085 - Phase-Out do Diesel S500 - Mudança 2.1 - Aquisição de Bens (Tubovias) | D24: 2.1.1.1 | E24: Chapas e perfis estruturais em aço carbono | F24: KG | G24: 1771.8979 | H24: 26.960219 | I24: =H24*G24 -> 47770.757 | L24: =G24-K24 -> 1771.8979 | N24: =G24 -> 1771.8979 | W24: =$H24*K24 -> 0 | X24: =$H24*L24 -> 47770.757 | Y24: =$H24*N24 -> 47770.757 | Z24: =$H24*O24 -> 0 | AA24: =$H24*P24 -> 0 | AB24: =$H24*Q24 -> 0 | AC24: =$H24*R24 -> 0 | AD24: =$H24*S24 -> 0 | AE24: =$H24*T24 -> 0 | AF24: =$H24*U24 -> 0 | AG24: =SUM(Y24:AF24) -> 47770.757 | AI24: =L24-SUM(M24:U24) -> 0 | AJ24: =X24-SUM(Y24:AF24) -> 0
B25: SS-43/2026 | C25: IN - 5250-24-085 - Phase-Out do Diesel S500 - Mudança 2.1 - Aquisição de Bens (Tubovias) | D25: 2.1.2.1 | E25: Tubos de condução em aço carbono | F25: KG | G25: 14736.06 | H25: 36.384822 | I25: =H25*G25 -> 536168.92 | K25: 14736.06 | L25: =G25-K25 -> 0 | W25: =$H25*K25 -> 536168.92 | X25: =$H25*L25 -> 0 | Y25: =$H25*N25 -> 0 | Z25: =$H25*O25 -> 0 | AA25: =$H25*P25 -> 0 | AB25: =$H25*Q25 -> 0 | AC25: =$H25*R25 -> 0 | AD25: =$H25*S25 -> 0 | AE25: =$H25*T25 -> 0 | AF25: =$H25*U25 -> 0 | AG25: =SUM(Y25:AF25) -> 0 | AI25: =L25-SUM(M25:U25) -> 0 | AJ25: =X25-SUM(Y25:AF25) -> 0
B26: SS-43/2026 | C26: IN - 5250-24-085 - Phase-Out do Diesel S500 - Mudança 2.1 - Aquisição de Bens (Tubovias) | D26: 2.1.3.1 | E26: Acessórios em aço carbono | F26: KG | G26: 173.60772 | H26: 132.51219 | I26: =H26*G26 -> 23005.14 | K26: 173.60772 | L26: =G26-K26 -> 0 | W26: =$H26*K26 -> 23005.14 | X26: =$H26*L26 -> 0 | Y26: =$H26*N26 -> 0 | Z26: =$H26*O26 -> 0 | AA26: =$H26*P26 -> 0 | AB26: =$H26*Q26 -> 0 | AC26: =$H26*R26 -> 0 | AD26: =$H26*S26 -> 0 | AE26: =$H26*T26 -> 0 | AF26: =$H26*U26 -> 0 | AG26: =SUM(Y26:AF26) -> 0 | AI26: =L26-SUM(M26:U26) -> 0 | AJ26: =X26-SUM(Y26:AF26) -> 0
B27: SS-38/2026 | C27: IN-5250-24-092 - PT-200 - Estrutura Metálica - Fornecimento de Bens | I27: =SUM(I28:I29) -> 3219797 | W27: =SUM(W28:W29) -> 0 | X27: =SUM(X28:X29) -> 3219797 | Y27: =SUM(Y28:Y29) -> 404403.29 | Z27: =SUM(Z28:Z29) -> 804899.54 | AA27: =SUM(AA28:AA29) -> 1039652.3 | AB27: =SUM(AB28:AB29) -> 970841.89 | AC27: =SUM(AC28:AC29) -> 0 | AD27: =SUM(AD28:AD29) -> 0 | ... AG27: =SUM(AG28:AG29) -> 3219797
B28: SS-38/2026 | C28: IN-5250-24-092 - PT-200 - Estrutura Metálica - Fornecimento de Bens | D28: 2.1.1.1 | E28: Chapas e perfis estruturais em aço carbono | F28: KG | G28: 119420.33 | H28: 26.960219 | I28: =H28*G28 -> 3219598.2 | L28: =G28-K28 -> 119420.33 | N28: 15000 | O28: 29855.081 | P28: 38555.081 | Q28: =G28-O28-P28-N28 -> 36010.163 | W28: =$H28*K28 -> 0 | X28: =$H28*L28 -> 3219598.2 | Y28: =$H28*N28 -> 404403.29 | Z28: =$H28*O28 -> 804899.54 | AA28: =$H28*P28 -> 1039453.5 | AB28: =$H28*Q28 -> 970841.89 | AC28: =$H28*R28 -> 0 | AD28: =$H28*S28 -> 0 | AE28: =$H28*T28 -> 0 | AF28: =$H28*U28 -> 0 | AG28: =SUM(Y28:AF28) -> 3219598.2 | AI28: =L28-SUM(M28:U28) -> 0 | AJ28: =X28-SUM(Y28:AF28) -> 0
B29: SS-38/2026 | C29: IN-5250-24-092 - PT-200 - Estrutura Metálica - Fornecimento de Bens | D29: 2.1.4.1 | E29: Material de referência ASTM A193 Gr B7 | F29: KG | G29: 3.6618 | H29: 54.295645 | I29: =H29*G29 -> 198.81979 | L29: =G29-K29 -> 3.6618 | P29: =L29 -> 3.6618 | W29: =$H29*K29 -> 0 | X29: =$H29*L29 -> 198.81979 | Y29: =$H29*N29 -> 0 | Z29: =$H29*O29 -> 0 | AA29: =$H29*P29 -> 198.81979 | AB29: =$H29*Q29 -> 0 | AC29: =$H29*R29 -> 0 | AD29: =$H29*S29 -> 0 | AE29: =$H29*T29 -> 0 | AF29: =$H29*U29 -> 0 | AG29: =SUM(Y29:AF29) -> 198.81979 | AI29: =L29-SUM(M29:U29) -> 0 | AJ29: =X29-SUM(Y29:AF29) -> 0
B30: SS-16/2026 | C30: PMBC - 5250-26-100 - HAZOP DA U-001 E U-101 - BENS | I30: =SUM(I31:I36) -> 16989.47 | W30: =SUM(W31:W36) -> 0 | X30: =SUM(X31:X36) -> 16989.47 | Y30: =SUM(Y31:Y36) -> 16989.47 | Z30: =SUM(Z31:Z36) -> 0 | AA30: =SUM(AA31:AA36) -> 0 | AB30: =SUM(AB31:AB36) -> 0 | AC30: =SUM(AC31:AC36) -> 0 | AD30: =SUM(AD31:AD36) -> 0 | ... AG30: =SUM(AG31:AG36) -> 16989.47
B31: SS-16/2026 | C31: PMBC - 5250-26-100 - HAZOP DA U-001 E U-101 - BENS | D31: 2.1.1.1 | E31: Chapas e perfis estruturais em aço carbono | F31: KG | G31: 0 | H31: 26.960219 | I31: =H31*G31 -> 0 | L31: =G31-K31 -> 0 | N31: =G31 -> 0 | W31: =$H31*K31 -> 0 | X31: =$H31*L31 -> 0 | Y31: =$H31*N31 -> 0 | Z31: =$H31*O31 -> 0 | AA31: =$H31*P31 -> 0 | AB31: =$H31*Q31 -> 0 | AC31: =$H31*R31 -> 0 | AD31: =$H31*S31 -> 0 | AE31: =$H31*T31 -> 0 | AF31: =$H31*U31 -> 0 | AG31: =SUM(Y31:AF31) -> 0 | AI31: =L31-SUM(M31:U31) -> 0 | AJ31: =X31-SUM(Y31:AF31) -> 0
B32: SS-16/2026 | C32: PMBC - 5250-26-100 - HAZOP DA U-001 E U-101 - BENS | D32: 2.1.2.1 | E32: Tubos de condução em aço carbono | F32: KG | G32: 44.5 | H32: 36.384822 | I32: =H32*G32 -> 1619.1246 | L32: =G32-K32 -> 44.5 | N32: =G32 -> 44.5 | W32: =$H32*K32 -> 0 | X32: =$H32*L32 -> 1619.1246 | Y32: =$H32*N32 -> 1619.1246 | Z32: =$H32*O32 -> 0 | AA32: =$H32*P32 -> 0 | AB32: =$H32*Q32 -> 0 | AC32: =$H32*R32 -> 0 | AD32: =$H32*S32 -> 0 | AE32: =$H32*T32 -> 0 | AF32: =$H32*U32 -> 0 | AG32: =SUM(Y32:AF32) -> 1619.1246 | AI32: =L32-SUM(M32:U32) -> 0 | AJ32: =X32-SUM(Y32:AF32) -> 0
B33: SS-16/2026 | C33: PMBC - 5250-26-100 - HAZOP DA U-001 E U-101 - BENS | D33: 2.1.3.1 | E33: Acessórios em aço carbono | F33: KG | G33: 37.92865 | H33: 132.51219 | I33: =H33*G33 -> 5026.0086 | L33: =G33-K33 -> 37.92865 | N33: =G33 -> 37.92865 | W33: =$H33*K33 -> 0 | X33: =$H33*L33 -> 5026.0086 | Y33: =$H33*N33 -> 5026.0086 | Z33: =$H33*O33 -> 0 | AA33: =$H33*P33 -> 0 | AB33: =$H33*Q33 -> 0 | AC33: =$H33*R33 -> 0 | AD33: =$H33*S33 -> 0 | AE33: =$H33*T33 -> 0 | AF33: =$H33*U33 -> 0 | AG33: =SUM(Y33:AF33) -> 5026.0086 | AI33: =L33-SUM(M33:U33) -> 0 | AJ33: =X33-SUM(Y33:AF33) -> 0
B34: SS-16/2026 | C34: PMBC - 5250-26-100 - HAZOP DA U-001 E U-101 - BENS | D34: 2.1.4.1 | E34: Material de referência ASTM A193 Gr B7 | F34: KG | G34: 8.8 | H34: 54.295645 | I34: =H34*G34 -> 477.80168 | L34: =G34-K34 -> 8.8 | N34: =G34 -> 8.8 | W34: =$H34*K34 -> 0 | X34: =$H34*L34 -> 477.80168 | Y34: =$H34*N34 -> 477.80168 | Z34: =$H34*O34 -> 0 | AA34: =$H34*P34 -> 0 | AB34: =$H34*Q34 -> 0 | AC34: =$H34*R34 -> 0 | AD34: =$H34*S34 -> 0 | AE34: =$H34*T34 -> 0 | AF34: =$H34*U34 -> 0 | AG34: =SUM(Y34:AF34) -> 477.80168 | AI34: =L34-SUM(M34:U34) -> 0 | AJ34: =X34-SUM(Y34:AF34) -> 0
B35: SS-16/2026 | C35: PMBC - 5250-26-100 - HAZOP DA U-001 E U-101 - BENS | D35: 2.1.6.5 | E35: Válvulas Tipo esfera ou gaveta - Classe 800# - Extremid. ES ou RO - Corpo em Aço Carbono - DN 1/2" a 3/4" | F35: UN | G35: 9 | H35: 511.52225 | I35: =H35*G35 -> 4603.7003 | L35: =G35-K35 -> 9 | N35: =G35 -> 9 | W35: =$H35*K35 -> 0 | X35: =$H35*L35 -> 4603.7003 | Y35: =$H35*N35 -> 4603.7003 | Z35: =$H35*O35 -> 0 | AA35: =$H35*P35 -> 0 | AB35: =$H35*Q35 -> 0 | AC35: =$H35*R35 -> 0 | AD35: =$H35*S35 -> 0 | AE35: =$H35*T35 -> 0 | AF35: =$H35*U35 -> 0 | AG35: =SUM(Y35:AF35) -> 4603.7003 | AI35: =L35-SUM(M35:U35) -> 0 | AJ35: =X35-SUM(Y35:AF35) -> 0
B36: SS-16/2026 | C36: PMBC - 5250-26-100 - HAZOP DA U-001 E U-101 - BENS | D36: 2.1.6.7 | E36: Válvulas Tipo globo ou retenção - Classe 800# - Extremid. ES ou RO - Corpo em Aço Carbono - DN 1/2" a 3/4" | F36: UN | G36: 10 | H36: 526.28346 | I36: =H36*G36 -> 5262.8346 | L36: =G36-K36 -> 10 | N36: =G36 -> 10 | W36: =$H36*K36 -> 0 | X36: =$H36*L36 -> 5262.8346 | Y36: =$H36*N36 -> 5262.8346 | Z36: =$H36*O36 -> 0 | AA36: =$H36*P36 -> 0 | AB36: =$H36*Q36 -> 0 | AC36: =$H36*R36 -> 0 | AD36: =$H36*S36 -> 0 | AE36: =$H36*T36 -> 0 | AF36: =$H36*U36 -> 0 | AG36: =SUM(Y36:AF36) -> 5262.8346 | AI36: =L36-SUM(M36:U36) -> 0 | AJ36: =X36-SUM(Y36:AF36) -> 0
B37: SS-9/2026 | C37: Adequação Escadas de Marinheiro - Fornecimento de Bens | I37: =SUM(I38:I38) -> 18400.35 | W37: =SUM(W38:W38) -> 0 | X37: =SUM(X38:X38) -> 18400.35 | Y37: =SUM(Y38:Y38) -> 18400.35 | Z37: =SUM(Z38:Z38) -> 0 | AA37: =SUM(AA38:AA38) -> 0 | AB37: =SUM(AB38:AB38) -> 0 | AC37: =SUM(AC38:AC38) -> 0 | AD37: =SUM(AD38:AD38) -> 0 | ... AG37: =SUM(AG38:AG38) -> 18400.35
B38: SS-9/2026 | C38: Adequação Escadas de Marinheiro - Fornecimento de Bens | D38: 2.1.1.1 | E38: Chapas e perfis estruturais em aço carbono | F38: KG | G38: 682.5 | H38: 26.960219 | I38: =H38*G38 -> 18400.35 | L38: =G38-K38 -> 682.5 | N38: =G38 -> 682.5 | W38: =$H38*K38 -> 0 | X38: =$H38*L38 -> 18400.35 | Y38: =$H38*N38 -> 18400.35 | Z38: =$H38*O38 -> 0 | AA38: =$H38*P38 -> 0 | AB38: =$H38*Q38 -> 0 | AC38: =$H38*R38 -> 0 | AD38: =$H38*S38 -> 0 | AE38: =$H38*T38 -> 0 | AF38: =$H38*U38 -> 0 | AG38: =SUM(Y38:AF38) -> 18400.35 | AI38: =L38-SUM(M38:U38) -> 0 | AJ38: =X38-SUM(Y38:AF38) -> 0
B39: SS-233/2025 | C39: IN - 5250-25-005 - ETDI - FRENTE 01 - BOMBAS DO PPI - ELÉTRICA - Bens | I39: =SUM(I40:I40) -> 2453.8429 | W39: =SUM(W40:W40) -> 0 | X39: =SUM(X40:X40) -> 2453.8429 | Y39: =SUM(Y40:Y40) -> 2453.8429 | Z39: =SUM(Z40:Z40) -> 0 | AA39: =SUM(AA40:AA40) -> 0 | AB39: =SUM(AB40:AB40) -> 0 | AC39: =SUM(AC40:AC40) -> 0 | AD39: =SUM(AD40:AD40) -> 0 | ... AG39: =SUM(AG40:AG40) -> 2453.8429
B40: SS-233/2025 | C40: IN - 5250-25-005 - ETDI - FRENTE 01 - BOMBAS DO PPI - ELÉTRICA - Bens | D40: 2.2.2.1 | E40: Terminação polimérica 6kV 25-35mm² | F40: UN | G40: 13 | H40: 188.75715 | I40: =H40*G40 -> 2453.8429 | L40: =G40-K40 -> 13 | N40: =G40 -> 13 | W40: =$H40*K40 -> 0 | X40: =$H40*L40 -> 2453.8429 | Y40: =$H40*N40 -> 2453.8429 | Z40: =$H40*O40 -> 0 | AA40: =$H40*P40 -> 0 | AB40: =$H40*Q40 -> 0 | AC40: =$H40*R40 -> 0 | AD40: =$H40*S40 -> 0 | AE40: =$H40*T40 -> 0 | AF40: =$H40*U40 -> 0 | AG40: =SUM(Y40:AF40) -> 2453.8429 | AI40: =L40-SUM(M40:U40) -> 0 | AJ40: =X40-SUM(Y40:AF40) -> 0
B41: SS-198/2025 | C41: IN - 5250-24-074 - Adequações para Recebimento de C5+ - Bens | I41: =SUM(I42:I60) -> 343364.38 | W41: =SUM(W42:W60) -> 285346.96 | X41: =SUM(X42:X60) -> 58017.412 | Y41: =SUM(Y42:Y60) -> 26297.299 | Z41: =SUM(Z42:Z60) -> 0 | AA41: =SUM(AA42:AA60) -> 0 | AB41: =SUM(AB42:AB60) -> 0 | AC41: =SUM(AC42:AC60) -> 0 | AD41: =SUM(AD42:AD60) -> 0 | ... AG41: =SUM(AG42:AG60) -> 26297.299
B42: SS-198/2025 | C42: IN - 5250-24-074 - Adequações para Recebimento de C5+ - Bens | D42: 2.1.1.1 | E42: Chapas e perfis estruturais em aço carbono | F42: KG | G42: 1123.2 | H42: 26.960219 | I42: =H42*G42 -> 30281.718 | K42: 1026.2 | L42: =G42-K42 -> 97 | W42: =$H42*K42 -> 27666.577 | X42: =$H42*L42 -> 2615.1413 | Y42: =$H42*N42 -> 0 | Z42: =$H42*O42 -> 0 | AA42: =$H42*P42 -> 0 | AB42: =$H42*Q42 -> 0 | AC42: =$H42*R42 -> 0 | AD42: =$H42*S42 -> 0 | AE42: =$H42*T42 -> 0 | AF42: =$H42*U42 -> 0 | AG42: =SUM(Y42:AF42) -> 0 | AI42: =L42-SUM(M42:U42) -> 97 | AJ42: =X42-SUM(Y42:AF42) -> 2615.1413
B43: SS-198/2025 | C43: IN - 5250-24-074 - Adequações para Recebimento de C5+ - Bens | D43: 2.1.2.1 | E43: Tubos de condução em aço carbono | F43: KG | G43: 1572.575 | H43: 36.384822 | I43: =H43*G43 -> 57217.861 | K43: 1565.98 | L43: =G43-K43 -> 6.595 | W43: =$H43*K43 -> 56977.903 | X43: =$H43*L43 -> 239.9579 | Y43: =$H43*N43 -> 0 | Z43: =$H43*O43 -> 0 | AA43: =$H43*P43 -> 0 | AB43: =$H43*Q43 -> 0 | AC43: =$H43*R43 -> 0 | AD43: =$H43*S43 -> 0 | AE43: =$H43*T43 -> 0 | AF43: =$H43*U43 -> 0 | AG43: =SUM(Y43:AF43) -> 0 | AI43: =L43-SUM(M43:U43) -> 6.595 | AJ43: =X43-SUM(Y43:AF43) -> 239.9579
B44: SS-198/2025 | C44: IN - 5250-24-074 - Adequações para Recebimento de C5+ - Bens | D44: 2.1.3.1 | E44: Acessórios em aço carbono | F44: KG | G44: 1246.74 | H44: 132.51219 | I44: =H44*G44 -> 165208.25 | K44: 1070.77 | L44: =G44-K44 -> 175.97 | W44: =$H44*K44 -> 141890.08 | X44: =$H44*L44 -> 23318.171 | Y44: =$H44*N44 -> 0 | Z44: =$H44*O44 -> 0 | AA44: =$H44*P44 -> 0 | AB44: =$H44*Q44 -> 0 | AC44: =$H44*R44 -> 0 | AD44: =$H44*S44 -> 0 | AE44: =$H44*T44 -> 0 | AF44: =$H44*U44 -> 0 | AG44: =SUM(Y44:AF44) -> 0 | AI44: =L44-SUM(M44:U44) -> 175.97 | AJ44: =X44-SUM(Y44:AF44) -> 23318.171
B45: SS-198/2025 | C45: IN - 5250-24-074 - Adequações para Recebimento de C5+ - Bens | D45: 2.1.4.1 | E45: Material de referência ASTM A193 Gr B7 | F45: KG | G45: 102.16 | H45: 54.295645 | I45: =H45*G45 -> 5546.8431 | L45: =G45-K45 -> 102.16 | W45: =$H45*K45 -> 0 | X45: =$H45*L45 -> 5546.8431 | Y45: =$H45*N45 -> 0 | Z45: =$H45*O45 -> 0 | AA45: =$H45*P45 -> 0 | AB45: =$H45*Q45 -> 0 | AC45: =$H45*R45 -> 0 | AD45: =$H45*S45 -> 0 | AE45: =$H45*T45 -> 0 | AF45: =$H45*U45 -> 0 | AG45: =SUM(Y45:AF45) -> 0 | AI45: =L45-SUM(M45:U45) -> 102.16 | AJ45: =X45-SUM(Y45:AF45) -> 5546.8431
B46: SS-198/2025 | C46: IN - 5250-24-074 - Adequações para Recebimento de C5+ - Bens | D46: 2.1.6.5 | E46: Válvulas Tipo esfera ou gaveta - Classe 800# - Extremid. ES ou RO - Corpo em Aço Carbono - DN 1/2" a 3/4" | F46: UN | G46: 11 | H46: 511.52225 | I46: =H46*G46 -> 5626.7448 | K46: 11 | L46: =G46-K46 -> 0 | W46: =$H46*K46 -> 5626.7448 | X46: =$H46*L46 -> 0 | Y46: =$H46*N46 -> 0 | Z46: =$H46*O46 -> 0 | AA46: =$H46*P46 -> 0 | AB46: =$H46*Q46 -> 0 | AC46: =$H46*R46 -> 0 | AD46: =$H46*S46 -> 0 | AE46: =$H46*T46 -> 0 | AF46: =$H46*U46 -> 0 | AG46: =SUM(Y46:AF46) -> 0 | AI46: =L46-SUM(M46:U46) -> 0 | AJ46: =X46-SUM(Y46:AF46) -> 0
B47: SS-198/2025 | C47: IN - 5250-24-074 - Adequações para Recebimento de C5+ - Bens | D47: 2.1.6.6 | E47: Válvulas Tipo esfera ou gaveta - Classe 800# - Extremid. ES ou RO - Corpo em Aço Carbono - DN 1" a 1 1/2" | F47: UN | G47: 2 | H47: 1039.3312 | I47: =H47*G47 -> 2078.6623 | K47: 2 | L47: =G47-K47 -> 0 | W47: =$H47*K47 -> 2078.6623 | X47: =$H47*L47 -> 0 | Y47: =$H47*N47 -> 0 | Z47: =$H47*O47 -> 0 | AA47: =$H47*P47 -> 0 | AB47: =$H47*Q47 -> 0 | AC47: =$H47*R47 -> 0 | AD47: =$H47*S47 -> 0 | AE47: =$H47*T47 -> 0 | AF47: =$H47*U47 -> 0 | AG47: =SUM(Y47:AF47) -> 0 | AI47: =L47-SUM(M47:U47) -> 0 | AJ47: =X47-SUM(Y47:AF47) -> 0
B48: SS-198/2025 | C48: IN - 5250-24-074 - Adequações para Recebimento de C5+ - Bens | D48: 2.1.6.9 | E48: Válvulas Tipo gaveta - Classe até 300# - Corpo em Aço Carbono - DN 2" a 3" | F48: UN | G48: 2 | H48: 3010.9347 | I48: =H48*G48 -> 6021.8693 | K48: 2 | L48: =G48-K48 -> 0 | W48: =$H48*K48 -> 6021.8693 | X48: =$H48*L48 -> 0 | Y48: =$H48*N48 -> 0 | Z48: =$H48*O48 -> 0 | AA48: =$H48*P48 -> 0 | AB48: =$H48*Q48 -> 0 | AC48: =$H48*R48 -> 0 | AD48: =$H48*S48 -> 0 | AE48: =$H48*T48 -> 0 | AF48: =$H48*U48 -> 0 | AG48: =SUM(Y48:AF48) -> 0 | AI48: =L48-SUM(M48:U48) -> 0 | AJ48: =X48-SUM(Y48:AF48) -> 0
B49: SS-198/2025 | C49: IN - 5250-24-074 - Adequações para Recebimento de C5+ - Bens | D49: 2.1.6.10 | E49: Válvulas Tipo esfera - Classe até 300# - Corpo em Aço Carbono - DN 2" a 3" | F49: UN | G49: 1 | H49: 2814.6459 | I49: =H49*G49 -> 2814.6459 | K49: 1 | L49: =G49-K49 -> 0 | W49: =$H49*K49 -> 2814.6459 | X49: =$H49*L49 -> 0 | Y49: =$H49*N49 -> 0 | Z49: =$H49*O49 -> 0 | AA49: =$H49*P49 -> 0 | AB49: =$H49*Q49 -> 0 | AC49: =$H49*R49 -> 0 | AD49: =$H49*S49 -> 0 | AE49: =$H49*T49 -> 0 | AF49: =$H49*U49 -> 0 | AG49: =SUM(Y49:AF49) -> 0 | AI49: =L49-SUM(M49:U49) -> 0 | AJ49: =X49-SUM(Y49:AF49) -> 0
B50: SS-198/2025 | C50: IN - 5250-24-074 - Adequações para Recebimento de C5+ - Bens | D50: 2.1.6.13 | E50: Válvulas Tipo gaveta - Classe até 300# - Corpo em Aço Carbono - DN 4" a 6" | F50: UN | G50: 3 | H50: 5325.2969 | I50: =H50*G50 -> 15975.891 | K50: 3 | L50: =G50-K50 -> 0 | W50: =$H50*K50 -> 15975.891 | X50: =$H50*L50 -> 0 | Y50: =$H50*N50 -> 0 | Z50: =$H50*O50 -> 0 | AA50: =$H50*P50 -> 0 | AB50: =$H50*Q50 -> 0 | AC50: =$H50*R50 -> 0 | AD50: =$H50*S50 -> 0 | AE50: =$H50*T50 -> 0 | AF50: =$H50*U50 -> 0 | AG50: =SUM(Y50:AF50) -> 0 | AI50: =L50-SUM(M50:U50) -> 0 | AJ50: =X50-SUM(Y50:AF50) -> 0
B51: SS-198/2025 | C51: IN - 5250-24-074 - Adequações para Recebimento de C5+ - Bens | D51: 2.1.6.16 | E51: Válvulas Tipo retenção - Classe até 300# - Corpo em Aço Carbono - DN 4" a 6" | F51: UN | G51: 2 | H51: 4248.6718 | I51: =H51*G51 -> 8497.3437 | K51: 2 | L51: =G51-K51 -> 0 | W51: =$H51*K51 -> 8497.3437 | X51: =$H51*L51 -> 0 | Y51: =$H51*N51 -> 0 | Z51: =$H51*O51 -> 0 | AA51: =$H51*P51 -> 0 | AB51: =$H51*Q51 -> 0 | AC51: =$H51*R51 -> 0 | AD51: =$H51*S51 -> 0 | AE51: =$H51*T51 -> 0 | AF51: =$H51*U51 -> 0 | AG51: =SUM(Y51:AF51) -> 0 | AI51: =L51-SUM(M51:U51) -> 0 | AJ51: =X51-SUM(Y51:AF51) -> 0
B52: SS-198/2025 | C52: IN - 5250-24-074 - Adequações para Recebimento de C5+ - Bens | D52: 2.1.6.17 | E52: Válvulas Tipo gaveta - Classe até 300# - Corpo em Aço Carbono - DN 8" a 10" | F52: UN | G52: 1 | H52: 17797.246 | I52: =H52*G52 -> 17797.246 | K52: 1 | L52: =G52-K52 -> 0 | W52: =$H52*K52 -> 17797.246 | X52: =$H52*L52 -> 0 | Y52: =$H52*N52 -> 0 | Z52: =$H52*O52 -> 0 | AA52: =$H52*P52 -> 0 | AB52: =$H52*Q52 -> 0 | AC52: =$H52*R52 -> 0 | AD52: =$H52*S52 -> 0 | AE52: =$H52*T52 -> 0 | AF52: =$H52*U52 -> 0 | AG52: =SUM(Y52:AF52) -> 0 | AI52: =L52-SUM(M52:U52) -> 0 | AJ52: =X52-SUM(Y52:AF52) -> 0
B53: SS-198/2025 | C53: IN - 5250-24-074 - Adequações para Recebimento de C5+ - Bens | D53: 2.2.1.9 | E53: Cabo instr. 250V 01P de 1,5mm² ou mais PVC/E / PVC/A; ST1/ST2 | F53: M | G53: 150 | H53: 5.7254389 | I53: =H53*G53 -> 858.81584 | L53: =G53-K53 -> 150 | N53: =G53 -> 150 | W53: =$H53*K53 -> 0 | X53: =$H53*L53 -> 858.81584 | Y53: =$H53*N53 -> 858.81584 | Z53: =$H53*O53 -> 0 | AA53: =$H53*P53 -> 0 | AB53: =$H53*Q53 -> 0 | AC53: =$H53*R53 -> 0 | AD53: =$H53*S53 -> 0 | AE53: =$H53*T53 -> 0 | AF53: =$H53*U53 -> 0 | AG53: =SUM(Y53:AF53) -> 858.81584 | AI53: =L53-SUM(M53:U53) -> 0 | AJ53: =X53-SUM(Y53:AF53) -> 0
B54: SS-198/2025 | C54: IN - 5250-24-074 - Adequações para Recebimento de C5+ - Bens | D54: 2.2.1.17 | E54: Cabo el. controle 1kV (de 5x até 7x) até 1,0mm² PVC/A | F54: M | G54: 1200 | H54: 6.2843762 | I54: =H54*G54 -> 7541.2515 | L54: =G54-K54 -> 1200 | N54: =G54 -> 1200 | W54: =$H54*K54 -> 0 | X54: =$H54*L54 -> 7541.2515 | Y54: =$H54*N54 -> 7541.2515 | Z54: =$H54*O54 -> 0 | AA54: =$H54*P54 -> 0 | AB54: =$H54*Q54 -> 0 | AC54: =$H54*R54 -> 0 | AD54: =$H54*S54 -> 0 | AE54: =$H54*T54 -> 0 | AF54: =$H54*U54 -> 0 | AG54: =SUM(Y54:AF54) -> 7541.2515 | AI54: =L54-SUM(M54:U54) -> 0 | AJ54: =X54-SUM(Y54:AF54) -> 0
B55: SS-198/2025 | C55: IN - 5250-24-074 - Adequações para Recebimento de C5+ - Bens | D55: 2.2.1.34 | E55: Cabo potência até 1kV (de 1x até 2x) de 2,5mm² a 4,0 mm², EPR/HEPR, ST1/ST2 | F55: M | G55: 250 | H55: 5.0657861 | I55: =H55*G55 -> 1266.4465 | L55: =G55-K55 -> 250 | N55: =G55 -> 250 | W55: =$H55*K55 -> 0 | X55: =$H55*L55 -> 1266.4465 | Y55: =$H55*N55 -> 1266.4465 | Z55: =$H55*O55 -> 0 | AA55: =$H55*P55 -> 0 | AB55: =$H55*Q55 -> 0 | AC55: =$H55*R55 -> 0 | AD55: =$H55*S55 -> 0 | AE55: =$H55*T55 -> 0 | AF55: =$H55*U55 -> 0 | AG55: =SUM(Y55:AF55) -> 1266.4465 | AI55: =L55-SUM(M55:U55) -> 0 | AJ55: =X55-SUM(Y55:AF55) -> 0
B56: SS-198/2025 | C56: IN - 5250-24-074 - Adequações para Recebimento de C5+ - Bens | D56: 2.2.1.37 | E56: Cabo potência até 1kV (de 3x até 4x) de 6,0mm² a 10,0 mm², EPR/HEPR, ST1/ST2 | F56: M | G56: 250 | H56: 22.025332 | I56: =H56*G56 -> 5506.333 | L56: =G56-K56 -> 250 | N56: =G56 -> 250 | W56: =$H56*K56 -> 0 | X56: =$H56*L56 -> 5506.333 | Y56: =$H56*N56 -> 5506.333 | Z56: =$H56*O56 -> 0 | AA56: =$H56*P56 -> 0 | AB56: =$H56*Q56 -> 0 | AC56: =$H56*R56 -> 0 | AD56: =$H56*S56 -> 0 | AE56: =$H56*T56 -> 0 | AF56: =$H56*U56 -> 0 | AG56: =SUM(Y56:AF56) -> 5506.333 | AI56: =L56-SUM(M56:U56) -> 0 | AJ56: =X56-SUM(Y56:AF56) -> 0
B57: SS-198/2025 | C57: IN - 5250-24-074 - Adequações para Recebimento de C5+ - Bens | D57: 2.2.1.153 | E57: CABO EL. NU DE COBRE CL.2A 35MM² | F57: M | G57: 40 | H57: 24.684219 | I57: =H57*G57 -> 987.36876 | L57: =G57-K57 -> 40 | N57: =G57 -> 40 | W57: =$H57*K57 -> 0 | X57: =$H57*L57 -> 987.36876 | Y57: =$H57*N57 -> 987.36876 | Z57: =$H57*O57 -> 0 | AA57: =$H57*P57 -> 0 | AB57: =$H57*Q57 -> 0 | AC57: =$H57*R57 -> 0 | AD57: =$H57*S57 -> 0 | AE57: =$H57*T57 -> 0 | AF57: =$H57*U57 -> 0 | AG57: =SUM(Y57:AF57) -> 987.36876 | AI57: =L57-SUM(M57:U57) -> 0 | AJ57: =X57-SUM(Y57:AF57) -> 0
B58: SS-198/2025 | C58: IN - 5250-24-074 - Adequações para Recebimento de C5+ - Bens | D58: 2.2.1.155 | E58: CABO EL. NU DE COBRE CL.2A 70MM² | F58: M | G58: 10 | H58: 42.655855 | I58: =H58*G58 -> 426.55855 | L58: =G58-K58 -> 10 | N58: =G58 -> 10 | W58: =$H58*K58 -> 0 | X58: =$H58*L58 -> 426.55855 | Y58: =$H58*N58 -> 426.55855 | Z58: =$H58*O58 -> 0 | AA58: =$H58*P58 -> 0 | AB58: =$H58*Q58 -> 0 | AC58: =$H58*R58 -> 0 | AD58: =$H58*S58 -> 0 | AE58: =$H58*T58 -> 0 | AF58: =$H58*U58 -> 0 | AG58: =SUM(Y58:AF58) -> 426.55855 | AI58: =L58-SUM(M58:U58) -> 0 | AJ58: =X58-SUM(Y58:AF58) -> 0
B59: SS-198/2025 | C59: IN - 5250-24-074 - Adequações para Recebimento de C5+ - Bens | D59: 2.2.3.1 | E59: Aço carbono com revestimento protetor de zinco (galvanizado a fogo)/ DN 3/4" | F59: M | G59: 6 | H59: 28.411088 | I59: =H59*G59 -> 170.46653 | L59: =G59-K59 -> 6 | N59: =G59 -> 6 | W59: =$H59*K59 -> 0 | X59: =$H59*L59 -> 170.46653 | Y59: =$H59*N59 -> 170.46653 | Z59: =$H59*O59 -> 0 | AA59: =$H59*P59 -> 0 | AB59: =$H59*Q59 -> 0 | AC59: =$H59*R59 -> 0 | AD59: =$H59*S59 -> 0 | AE59: =$H59*T59 -> 0 | AF59: =$H59*U59 -> 0 | AG59: =SUM(Y59:AF59) -> 170.46653 | AI59: =L59-SUM(M59:U59) -> 0 | AJ59: =X59-SUM(Y59:AF59) -> 0
B60: SS-198/2025 | C60: IN - 5250-24-074 - Adequações para Recebimento de C5+ - Bens | D60: 2.2.3.3 | E60: Aço carbono com revestimento protetor de zinco (galvanizado a fogo)/ DN 1 1/2" | F60: M | G60: 180 | H60: 53.000326 | I60: =H60*G60 -> 9540.0586 | L60: =G60-K60 -> 180 | N60: =G60 -> 180 | W60: =$H60*K60 -> 0 | X60: =$H60*L60 -> 9540.0586 | Y60: =$H60*N60 -> 9540.0586 | Z60: =$H60*O60 -> 0 | AA60: =$H60*P60 -> 0 | AB60: =$H60*Q60 -> 0 | AC60: =$H60*R60 -> 0 | AD60: =$H60*S60 -> 0 | AE60: =$H60*T60 -> 0 | AF60: =$H60*U60 -> 0 | AG60: =SUM(Y60:AF60) -> 9540.0586 | AI60: =L60-SUM(M60:U60) -> 0 | AJ60: =X60-SUM(Y60:AF60) -> 0
B61: SS-196/2025 | C61: Fornecimento de Bens - SS-132/2025 - Envelope Elétrico GPI | I61: =SUM(I62:I69) -> 302339.06 | W61: =SUM(W62:W69) -> 84428.623 | X61: =SUM(X62:X69) -> 217910.43 | Y61: =SUM(Y62:Y69) -> 50103.95 | Z61: =SUM(Z62:Z69) -> 217910.43 | AA61: =SUM(AA62:AA69) -> 0 | AB61: =SUM(AB62:AB69) -> 0 | AC61: =SUM(AC62:AC69) -> 0 | AD61: =SUM(AD62:AD69) -> 0 | ... AG61: =SUM(AG62:AG69) -> 268014.38
B62: SS-196/2025 | C62: Fornecimento de Bens - SS-132/2025 - Envelope Elétrico GPI | D62: 2.1.1.1 | E62: Chapas e perfis estruturais em aço carbono | F62: KG | G62: 4990.04 | H62: 26.960219 | I62: =H62*G62 -> 134532.57 | K62: 3131.6 | L62: =G62-K62 -> 1858.44 | N62: 1858.44 | O62: =L62 -> 1858.44 | W62: =$H62*K62 -> 84428.623 | X62: =$H62*L62 -> 50103.95 | Y62: =$H62*N62 -> 50103.95 | Z62: =$H62*O62 -> 50103.95 | AA62: =$H62*P62 -> 0 | AB62: =$H62*Q62 -> 0 | AC62: =$H62*R62 -> 0 | AD62: =$H62*S62 -> 0 | AE62: =$H62*T62 -> 0 | AF62: =$H62*U62 -> 0 | AG62: =SUM(Y62:AF62) -> 100207.9 | AI62: =L62-SUM(M62:U62) -> -1858.44 | AJ62: =X62-SUM(Y62:AF62) -> -50103.95
B63: SS-196/2025 | C63: Fornecimento de Bens - SS-132/2025 - Envelope Elétrico GPI | D63: 2.2.1.42 | E63: Cabo potência até 1kV 1x de 50,0mm² , EPR/HEPR, ST1/ST2 | F63: M | G63: 10 | H63: 25.618404 | I63: =H63*G63 -> 256.18404 | L63: =G63-K63 -> 10 | O63: =L63 -> 10 | W63: =$H63*K63 -> 0 | X63: =$H63*L63 -> 256.18404 | Y63: =$H63*N63 -> 0 | Z63: =$H63*O63 -> 256.18404 | AA63: =$H63*P63 -> 0 | AB63: =$H63*Q63 -> 0 | AC63: =$H63*R63 -> 0 | AD63: =$H63*S63 -> 0 | AE63: =$H63*T63 -> 0 | AF63: =$H63*U63 -> 0 | AG63: =SUM(Y63:AF63) -> 256.18404 | AI63: =L63-SUM(M63:U63) -> 0 | AJ63: =X63-SUM(Y63:AF63) -> 0
B64: SS-196/2025 | C64: Fornecimento de Bens - SS-132/2025 - Envelope Elétrico GPI | D64: 2.2.1.46 | E64: Cabo potência até 1kV 1x de 70,0mm² , EPR/HEPR, ST1/ST2 | F64: M | G64: 145 | H64: 37.570192 | I64: =H64*G64 -> 5447.6778 | L64: =G64-K64 -> 145 | O64: =L64 -> 145 | W64: =$H64*K64 -> 0 | X64: =$H64*L64 -> 5447.6778 | Y64: =$H64*N64 -> 0 | Z64: =$H64*O64 -> 5447.6778 | AA64: =$H64*P64 -> 0 | AB64: =$H64*Q64 -> 0 | AC64: =$H64*R64 -> 0 | AD64: =$H64*S64 -> 0 | AE64: =$H64*T64 -> 0 | AF64: =$H64*U64 -> 0 | AG64: =SUM(Y64:AF64) -> 5447.6778 | AI64: =L64-SUM(M64:U64) -> 0 | AJ64: =X64-SUM(Y64:AF64) -> 0
B65: SS-196/2025 | C65: Fornecimento de Bens - SS-132/2025 - Envelope Elétrico GPI | D65: 2.2.1.54 | E65: Cabo potência até 1kV 1x de 120,0mm² , EPR/HEPR, ST1/ST2 | F65: M | G65: 715 | H65: 64.51524 | I65: =H65*G65 -> 46128.396 | L65: =G65-K65 -> 715 | O65: =L65 -> 715 | W65: =$H65*K65 -> 0 | X65: =$H65*L65 -> 46128.396 | Y65: =$H65*N65 -> 0 | Z65: =$H65*O65 -> 46128.396 | AA65: =$H65*P65 -> 0 | AB65: =$H65*Q65 -> 0 | AC65: =$H65*R65 -> 0 | AD65: =$H65*S65 -> 0 | AE65: =$H65*T65 -> 0 | AF65: =$H65*U65 -> 0 | AG65: =SUM(Y65:AF65) -> 46128.396 | AI65: =L65-SUM(M65:U65) -> 0 | AJ65: =X65-SUM(Y65:AF65) -> 0
B66: SS-196/2025 | C66: Fornecimento de Bens - SS-132/2025 - Envelope Elétrico GPI | D66: 2.2.1.152 | E66: CABO EL. NU DE COBRE CL.2A 25MM² | F66: M | G66: 10 | H66: 20.630656 | I66: =H66*G66 -> 206.30656 | L66: =G66-K66 -> 10 | O66: =L66 -> 10 | W66: =$H66*K66 -> 0 | X66: =$H66*L66 -> 206.30656 | Y66: =$H66*N66 -> 0 | Z66: =$H66*O66 -> 206.30656 | AA66: =$H66*P66 -> 0 | AB66: =$H66*Q66 -> 0 | AC66: =$H66*R66 -> 0 | AD66: =$H66*S66 -> 0 | AE66: =$H66*T66 -> 0 | AF66: =$H66*U66 -> 0 | AG66: =SUM(Y66:AF66) -> 206.30656 | AI66: =L66-SUM(M66:U66) -> 0 | AJ66: =X66-SUM(Y66:AF66) -> 0
B67: SS-196/2025 | C67: Fornecimento de Bens - SS-132/2025 - Envelope Elétrico GPI | D67: 2.2.1.155 | E67: CABO EL. NU DE COBRE CL.2A 70MM² | F67: M | G67: 200 | H67: 42.655855 | I67: =H67*G67 -> 8531.1711 | L67: =G67-K67 -> 200 | O67: =L67 -> 200 | W67: =$H67*K67 -> 0 | X67: =$H67*L67 -> 8531.1711 | Y67: =$H67*N67 -> 0 | Z67: =$H67*O67 -> 8531.1711 | AA67: =$H67*P67 -> 0 | AB67: =$H67*Q67 -> 0 | AC67: =$H67*R67 -> 0 | AD67: =$H67*S67 -> 0 | AE67: =$H67*T67 -> 0 | AF67: =$H67*U67 -> 0 | AG67: =SUM(Y67:AF67) -> 8531.1711 | AI67: =L67-SUM(M67:U67) -> 0 | AJ67: =X67-SUM(Y67:AF67) -> 0
B68: SS-196/2025 | C68: Fornecimento de Bens - SS-132/2025 - Envelope Elétrico GPI | D68: 2.2.1.163 | E68: CABO EL. NU DE COBRE CL.2C 6MM² | F68: M | G68: 30 | H68: 9.5523589 | I68: =H68*G68 -> 286.57077 | L68: =G68-K68 -> 30 | O68: =L68 -> 30 | W68: =$H68*K68 -> 0 | X68: =$H68*L68 -> 286.57077 | Y68: =$H68*N68 -> 0 | Z68: =$H68*O68 -> 286.57077 | AA68: =$H68*P68 -> 0 | AB68: =$H68*Q68 -> 0 | AC68: =$H68*R68 -> 0 | AD68: =$H68*S68 -> 0 | AE68: =$H68*T68 -> 0 | AF68: =$H68*U68 -> 0 | AG68: =SUM(Y68:AF68) -> 286.57077 | AI68: =L68-SUM(M68:U68) -> 0 | AJ68: =X68-SUM(Y68:AF68) -> 0
B69: SS-196/2025 | C69: Fornecimento de Bens - SS-132/2025 - Envelope Elétrico GPI | D69: 2.2.3.6 | E69: Aço carbono com revestimento protetor de zinco (galvanizado a fogo)/ DN 4" | F69: M | G69: 882 | H69: 121.25871 | I69: =H69*G69 -> 106950.18 | L69: =G69-K69 -> 882 | O69: =L69 -> 882 | W69: =$H69*K69 -> 0 | X69: =$H69*L69 -> 106950.18 | Y69: =$H69*N69 -> 0 | Z69: =$H69*O69 -> 106950.18 | AA69: =$H69*P69 -> 0 | AB69: =$H69*Q69 -> 0 | AC69: =$H69*R69 -> 0 | AD69: =$H69*S69 -> 0 | AE69: =$H69*T69 -> 0 | AF69: =$H69*U69 -> 0 | AG69: =SUM(Y69:AF69) -> 106950.18 | AI69: =L69-SUM(M69:U69) -> 0 | AJ69: =X69-SUM(Y69:AF69) -> 0

Sheet CRONO PROJETOS_TOPO
K2: FISICO_QUANTIDADES | X2: FINANCEIRO_VALOR (R$)
K3: Medido | L3: Saldo | M3: Saldo | N3: 46113 | O3: 46143 | P3: 46174 | Q3: 46204 | R3: 46235 | S3: 46266 | T3: 46296 | U3: 46327 | V3: 46357 | X3: Acum | Y3: Saldo | Z3: 46143 | AA3: 46174 | AB3: 46204 | AC3: 46235 | AD3: 46266 | AE3: 46296 | AF3: 46327 | AG3: 46357 | AH3: TOTAL MAIO A DEZ/2026 | AK3: CONF.FIS | AL3: CONF.R$
B4: SS | C4: DESCRIÇÃO-SS | D4: ITEM | E4: DESCRIÇÃO-ITEM | F4: UN | G4: Qtd | H4: PREÇO UNITÁRIO (R$) | I4: PREÇO TOTAL (R$)
B6: - | C6: PROJETOS E TOPOGRAFIA - TOTAL GERAL | I6: =SUM(I7:I33) -> 1863634.8 | X6: =SUM(X7:X33) -> 375845.09 | Y6: =SUM(Y7:Y33) -> 1487789.7 | Z6: =SUM(Z7:Z33) -> 145635.84 | AA6: =SUM(AA7:AA33) -> 245318.74 | AB6: =SUM(AB7:AB33) -> 583663.08 | AC6: =SUM(AC7:AC33) -> 245368.2 | AD6: =SUM(AD7:AD33) -> 27128.475 | AE6: =SUM(AE7:AE33) -> 27128.475 | ... AH6: =SUM(AH7:AH33) -> 1286175.6
B7: SS-111/2026 | C7: IN - 5250-24-051 - Melhoria do Acesso aos TQ´s de Escuros 27-TQ-116-A/B/C/D/E/F - Detalhamento - Projeto Mecânica | D7: 1.7.3.1 | E7: Serviços Técnicos Especializados de Projeto - Hora Normal | F7: Hs | G7: 1114 | H7: 186.45 | I7: =H7*G7 -> 207705.3 | K7: 0 | L7: =G7-K7 -> 1114 | Q7: =G7 -> 1114 | X7: =$H7*K7 -> 0 | Y7: =$H7*L7 -> 207705.3 | Z7: =$H7*O7 -> 0 | AA7: =$H7*P7 -> 0 | AB7: =$H7*Q7 -> 207705.3 | AC7: =$H7*R7 -> 0 | AD7: =$H7*S7 -> 0 | AE7: =$H7*T7 -> 0 | AF7: =$H7*U7 -> 0 | AG7: =$H7*V7 -> 0 | AH7: =SUM(Z7:AG7) -> 207705.3 | AK7: =L7-SUM(N7:V7) -> 0 | AL7: =Y7-SUM(Z7:AG7) -> 0
B8: SS-112/2026 | C8: IN - 5250-24-051 - Melhoria do Acesso aos TQ´s de Escuros 27-TQ-116-A/B/C/D/E/F - Detalhamento - Projeto Civil | D8: 1.7.3.1 | E8: Serviços Técnicos Especializados de Projeto - Hora Normal | F8: Hs | G8: 528 | H8: 186.45 | I8: =H8*G8 -> 98445.6 | K8: 0 | L8: =G8-K8 -> 528 | O8: 120 | P8: 200 | Q8: =G8-O8-P8 -> 208 | X8: =$H8*K8 -> 0 | Y8: =$H8*L8 -> 98445.6 | Z8: =$H8*O8 -> 22374 | AA8: =$H8*P8 -> 37290 | AB8: =$H8*Q8 -> 38781.6 | AC8: =$H8*R8 -> 0 | AD8: =$H8*S8 -> 0 | AE8: =$H8*T8 -> 0 | AF8: =$H8*U8 -> 0 | AG8: =$H8*V8 -> 0 | AH8: =SUM(Z8:AG8) -> 98445.6 | AK8: =L8-SUM(N8:V8) -> 0 | AL8: =Y8-SUM(Z8:AG8) -> 0
B9: SS-113/2026 | C9: IN - 5250-24-051 - Melhoria do Acesso aos TQ´s de Escuros 27-TQ-116-A/B/C/D/E/F - Detalhamento - Projeto Elétrica | D9: 1.7.3.1 | E9: Serviços Técnicos Especializados de Projeto - Hora Normal | F9: Hs | G9: 304.4 | H9: 186.45 | I9: =H9*G9 -> 56755.38 | K9: 0 | L9: =G9-K9 -> 304.4 | Q9: =G9 -> 304.4 | X9: =$H9*K9 -> 0 | Y9: =$H9*L9 -> 56755.38 | Z9: =$H9*O9 -> 0 | AA9: =$H9*P9 -> 0 | AB9: =$H9*Q9 -> 56755.38 | AC9: =$H9*R9 -> 0 | AD9: =$H9*S9 -> 0 | AE9: =$H9*T9 -> 0 | AF9: =$H9*U9 -> 0 | AG9: =$H9*V9 -> 0 | AH9: =SUM(Z9:AG9) -> 56755.38 | AK9: =L9-SUM(N9:V9) -> 0 | AL9: =Y9-SUM(Z9:AG9) -> 0
B10: SS-114/2026 | C10: IN - 5250-25-010 - Melhoria acesso bloco K 27-TQ-01C, D e E - Detalhamento - Projeto Mecânica | D10: 1.7.3.1 | E10: Serviços Técnicos Especializados de Projeto - Hora Normal | F10: Hs | G10: 1120 | H10: 186.45 | I10: =H10*G10 -> 208824 | K10: 0 | L10: =G10-K10 -> 1120 | R10: =G10 -> 1120 | X10: =$H10*K10 -> 0 | Y10: =$H10*L10 -> 208824 | Z10: =$H10*O10 -> 0 | AA10: =$H10*P10 -> 0 | AB10: =$H10*Q10 -> 0 | AC10: =$H10*R10 -> 208824 | AD10: =$H10*S10 -> 0 | AE10: =$H10*T10 -> 0 | AF10: =$H10*U10 -> 0 | AG10: =$H10*V10 -> 0 | AH10: =SUM(Z10:AG10) -> 208824 | AK10: =L10-SUM(N10:V10) -> 0 | AL10: =Y10-SUM(Z10:AG10) -> 0
B11: SS-115/2026 | C11: IN - 5250-25-010 - Melhoria acesso bloco K 27-TQ-01C, D e E - Detalhamento - Projeto Civil | D11: 1.7.3.1 | E11: Serviços Técnicos Especializados de Projeto - Hora Normal | F11: Hs | G11: 264 | H11: 186.45 | I11: =H11*G11 -> 49222.8 | K11: 0 | L11: =G11-K11 -> 264 | O11: 80 | P11: 184 | X11: =$H11*K11 -> 0 | Y11: =$H11*L11 -> 49222.8 | Z11: =$H11*O11 -> 14916 | AA11: =$H11*P11 -> 34306.8 | AB11: =$H11*Q11 -> 0 | AC11: =$H11*R11 -> 0 | AD11: =$H11*S11 -> 0 | AE11: =$H11*T11 -> 0 | AF11: =$H11*U11 -> 0 | AG11: =$H11*V11 -> 0 | AH11: =SUM(Z11:AG11) -> 49222.8 | AK11: =L11-SUM(N11:V11) -> 0 | AL11: =Y11-SUM(Z11:AG11) -> 0
B12: SS-116/2026 | C12: IN - 5250-25-010 - Melhoria acesso bloco K 27-TQ-01C, D e E - Detalhamento - Projeto Elétrica | D12: 1.7.3.1 | E12: Serviços Técnicos Especializados de Projeto - Hora Normal | F12: Hs | G12: 152 | H12: 186.45 | I12: =H12*G12 -> 28340.4 | K12: 0 | L12: =G12-K12 -> 152 | R12: =G12 -> 152 | X12: =$H12*K12 -> 0 | Y12: =$H12*L12 -> 28340.4 | Z12: =$H12*O12 -> 0 | AA12: =$H12*P12 -> 0 | AB12: =$H12*Q12 -> 0 | AC12: =$H12*R12 -> 28340.4 | AD12: =$H12*S12 -> 0 | AE12: =$H12*T12 -> 0 | AF12: =$H12*U12 -> 0 | AG12: =$H12*V12 -> 0 | AH12: =SUM(Z12:AG12) -> 28340.4 | AK12: =L12-SUM(N12:V12) -> 0 | AL12: =Y12-SUM(Z12:AG12) -> 0
B13: SS-117/2026 | C13: IN - 5250-25-011 - Melhoria acesso bloco P 27-TQ-01 K e M - Detalhamento - Projeto Mecânica | D13: 1.7.3.1 | E13: Serviços Técnicos Especializados de Projeto - Hora Normal | F13: Hs | G13: 632 | H13: 186.45 | I13: =H13*G13 -> 117836.4 | K13: 0 | L13: =G13-K13 -> 632 | Q13: =G13 -> 632 | X13: =$H13*K13 -> 0 | Y13: =$H13*L13 -> 117836.4 | Z13: =$H13*O13 -> 0 | AA13: =$H13*P13 -> 0 | AB13: =$H13*Q13 -> 117836.4 | AC13: =$H13*R13 -> 0 | AD13: =$H13*S13 -> 0 | AE13: =$H13*T13 -> 0 | AF13: =$H13*U13 -> 0 | AG13: =$H13*V13 -> 0 | AH13: =SUM(Z13:AG13) -> 117836.4 | AK13: =L13-SUM(N13:V13) -> 0 | AL13: =Y13-SUM(Z13:AG13) -> 0
B14: SS-118/2026 | C14: IN - 5250-25-011 - Melhoria acesso bloco P 27-TQ-01 K e M - Detalhamento - Projeto Civil | D14: 1.7.3.1 | E14: Serviços Técnicos Especializados de Projeto - Hora Normal | F14: Hs | G14: 176 | H14: 186.45 | I14: =H14*G14 -> 32815.2 | K14: 0 | L14: =G14-K14 -> 176 | O14: =G14 -> 176 | X14: =$H14*K14 -> 0 | Y14: =$H14*L14 -> 32815.2 | Z14: =$H14*O14 -> 32815.2 | AA14: =$H14*P14 -> 0 | AB14: =$H14*Q14 -> 0 | AC14: =$H14*R14 -> 0 | AD14: =$H14*S14 -> 0 | AE14: =$H14*T14 -> 0 | AF14: =$H14*U14 -> 0 | AG14: =$H14*V14 -> 0 | AH14: =SUM(Z14:AG14) -> 32815.2 | AK14: =L14-SUM(N14:V14) -> 0 | AL14: =Y14-SUM(Z14:AG14) -> 0
B15: SS-119/2026 | C15: IN - 5250-25-011 - Melhoria acesso bloco P 27-TQ-01 K e M - Detalhamento - Projeto Elétrica | D15: 1.7.3.1 | E15: Serviços Técnicos Especializados de Projeto - Hora Normal | F15: Hs | G15: 101.5 | H15: 186.45 | I15: =H15*G15 -> 18924.675 | K15: 0 | L15: =G15-K15 -> 101.5 | S15: 101.5 | X15: =$H15*K15 -> 0 | Y15: =$H15*L15 -> 18924.675 | Z15: =$H15*O15 -> 0 | AA15: =$H15*P15 -> 0 | AB15: =$H15*Q15 -> 0 | AC15: =$H15*R15 -> 0 | AD15: =$H15*S15 -> 18924.675 | AE15: =$H15*T15 -> 0 | AF15: =$H15*U15 -> 0 | AG15: =$H15*V15 -> 0 | AH15: =SUM(Z15:AG15) -> 18924.675 | AK15: =L15-SUM(N15:V15) -> 0 | AL15: =Y15-SUM(Z15:AG15) -> 0
B16: SS-120/2026 | C16: IN - 5250-25-012 - Melhoria acesso bloco P 27-TQ-01 L e N - Detalhamento - Projeto Mecânica | D16: 1.7.3.1 | E16: Serviços Técnicos Especializados de Projeto - Hora Normal | F16: Hs | G16: 828 | H16: 186.45 | I16: =H16*G16 -> 154380.6 | K16: 0 | L16: =G16-K16 -> 828 | Q16: =G16 -> 828 | X16: =$H16*K16 -> 0 | Y16: =$H16*L16 -> 154380.6 | Z16: =$H16*O16 -> 0 | AA16: =$H16*P16 -> 0 | AB16: =$H16*Q16 -> 154380.6 | AC16: =$H16*R16 -> 0 | AD16: =$H16*S16 -> 0 | AE16: =$H16*T16 -> 0 | AF16: =$H16*U16 -> 0 | AG16: =$H16*V16 -> 0 | AH16: =SUM(Z16:AG16) -> 154380.6 | AK16: =L16-SUM(N16:V16) -> 0 | AL16: =Y16-SUM(Z16:AG16) -> 0
B17: SS-121/2026 | C17: IN - 5250-25-012 - Melhoria acesso bloco P 27-TQ-01 L e N - Detalhamento - Projeto Civil | D17: 1.7.3.1 | E17: Serviços Técnicos Especializados de Projeto - Hora Normal | F17: Hs | G17: 176 | H17: 186.45 | I17: =H17*G17 -> 32815.2 | K17: 0 | L17: =G17-K17 -> 176 | O17: =G17 -> 176 | X17: =$H17*K17 -> 0 | Y17: =$H17*L17 -> 32815.2 | Z17: =$H17*O17 -> 32815.2 | AA17: =$H17*P17 -> 0 | AB17: =$H17*Q17 -> 0 | AC17: =$H17*R17 -> 0 | AD17: =$H17*S17 -> 0 | AE17: =$H17*T17 -> 0 | AF17: =$H17*U17 -> 0 | AG17: =$H17*V17 -> 0 | AH17: =SUM(Z17:AG17) -> 32815.2 | AK17: =L17-SUM(N17:V17) -> 0 | AL17: =Y17-SUM(Z17:AG17) -> 0
B18: SS-122/2026 | C18: IN - 5250-25-012 - Melhoria acesso bloco P 27-TQ-01 L e N - Detalhamento - Projeto Elétrica | D18: 1.7.3.1 | E18: Serviços Técnicos Especializados de Projeto - Hora Normal | F18: Hs | G18: 101.5 | H18: 186.45 | I18: =H18*G18 -> 18924.675 | K18: 0 | L18: =G18-K18 -> 101.5 | T18: =G18 -> 101.5 | X18: =$H18*K18 -> 0 | Y18: =$H18*L18 -> 18924.675 | Z18: =$H18*O18 -> 0 | AA18: =$H18*P18 -> 0 | AB18: =$H18*Q18 -> 0 | AC18: =$H18*R18 -> 0 | AD18: =$H18*S18 -> 0 | AE18: =$H18*T18 -> 18924.675 | AF18: =$H18*U18 -> 0 | AG18: =$H18*V18 -> 0 | AH18: =SUM(Z18:AG18) -> 18924.675 | AK18: =L18-SUM(N18:V18) -> 0 | AL18: =Y18-SUM(Z18:AG18) -> 0
B19: SS-117/2025 | C19: Adequação Escadas de Marinheiro - Projeto | D19: 1.7.3.2 | E19: Serviços Técnicos Especializados de Projeto - Em hora extra (HSE) | F19: Hs | G19: 176 | H19: 245.775 | I19: =H19*G19 -> 43256.4 | K19: 0 | L19: =G19-K19 -> 176 | X19: =$H19*K19 -> 0 | Y19: =$H19*L19 -> 43256.4 | Z19: =$H19*O19 -> 0 | AA19: =$H19*P19 -> 0 | AB19: =$H19*Q19 -> 0 | AC19: =$H19*R19 -> 0 | AD19: =$H19*S19 -> 0 | AE19: =$H19*T19 -> 0 | AF19: =$H19*U19 -> 0 | AG19: =$H19*V19 -> 0 | AH19: =SUM(Z19:AG19) -> 0 | AK19: =L19-SUM(N19:V19) -> 176 | AL19: =Y19-SUM(Z19:AG19) -> 43256.4
B20: SS-117/2025 | C20: Adequação Escadas de Marinheiro - Projeto | D20: 1.7.3.1 | E20: Serviços Técnicos Especializados de Projeto - Hora Normal | F20: Hs | G20: 827.2 | H20: 186.45 | I20: =H20*G20 -> 154231.44 | K20: =G20-284.5 -> 542.7 | L20: =G20-K20 -> 284.5 | P20: 44.5 | Q20: 44 | R20: 44 | S20: 44 | T20: 44 | U20: 64 | X20: =$H20*K20 -> 101186.42 | Y20: =$H20*L20 -> 53045.025 | Z20: =$H20*O20 -> 0 | AA20: =$H20*P20 -> 8297.025 | AB20: =$H20*Q20 -> 8203.8 | AC20: =$H20*R20 -> 8203.8 | AD20: =$H20*S20 -> 8203.8 | AE20: =$H20*T20 -> 8203.8 | AF20: =$H20*U20 -> 11932.8 | AG20: =$H20*V20 -> 0 | AH20: =SUM(Z20:AG20) -> 53045.025 | AK20: =L20-SUM(N20:V20) -> 0 | AL20: =Y20-SUM(Z20:AG20) -> 0
B21: SS-133/2025 | C21: IN - 5250-24-085 - Phase-Out do Diesel S500 - Projeto | D21: 1.7.2.1 | E21: Serviços Técnicos Especializados de Engenharia - Hora Normal | F21: Hs | G21: 820.4 | H21: 254.25 | I21: =H21*G21 -> 208586.7 | K21: =G21-121.92 -> 698.48 | L21: =G21-K21 -> 121.92 | P21: =L21 -> 121.92 | X21: =$H21*K21 -> 177588.54 | Y21: =$H21*L21 -> 30998.16 | Z21: =$H21*O21 -> 0 | AA21: =$H21*P21 -> 30998.16 | AB21: =$H21*Q21 -> 0 | AC21: =$H21*R21 -> 0 | AD21: =$H21*S21 -> 0 | AE21: =$H21*T21 -> 0 | AF21: =$H21*U21 -> 0 | AG21: =$H21*V21 -> 0 | AH21: =SUM(Z21:AG21) -> 30998.16 | AK21: =L21-SUM(N21:V21) -> 0 | AL21: =Y21-SUM(Z21:AG21) -> 0
B22: SS-133/2025 | C22: IN - 5250-24-085 - Phase-Out do Diesel S500 - Projeto | D22: 1.7.3.1 | E22: Serviços Técnicos Especializados de Projeto - Hora Normal | F22: Hs | G22: 628.8 | H22: 186.45 | I22: =H22*G22 -> 117239.76 | K22: =G22-277.28 -> 351.52 | L22: =G22-K22 -> 277.28 | O22: 120 | P22: =L22-O22 -> 157.28 | X22: =$H22*K22 -> 65540.904 | Y22: =$H22*L22 -> 51698.856 | Z22: =$H22*O22 -> 22374 | AA22: =$H22*P22 -> 29324.856 | AB22: =$H22*Q22 -> 0 | AC22: =$H22*R22 -> 0 | AD22: =$H22*S22 -> 0 | AE22: =$H22*T22 -> 0 | AF22: =$H22*U22 -> 0 | AG22: =$H22*V22 -> 0 | AH22: =SUM(Z22:AG22) -> 51698.856 | AK22: =L22-SUM(N22:V22) -> 0 | AL22: =Y22-SUM(Z22:AG22) -> 0
B23: SS-133/2025 | C23: IN - 5250-24-085 - Phase-Out do Diesel S500 - Projeto | D23: 1.1.1.16 | E23: Levantamento topográfico | F23: Hs | G23: 17.6 | H23: 231.15275 | I23: =H23*G23 -> 4068.2884 | K23: 8.8 | L23: =G23-K23 -> 8.8 | X23: =$H23*K23 -> 2034.1442 | Y23: =$H23*L23 -> 2034.1442 | Z23: =$H23*O23 -> 0 | AA23: =$H23*P23 -> 0 | AB23: =$H23*Q23 -> 0 | AC23: =$H23*R23 -> 0 | AD23: =$H23*S23 -> 0 | AE23: =$H23*T23 -> 0 | AF23: =$H23*U23 -> 0 | AG23: =$H23*V23 -> 0 | AH23: =SUM(Z23:AG23) -> 0 | AK23: =L23-SUM(N23:V23) -> 8.8 | AL23: =Y23-SUM(Z23:AG23) -> 2034.1442
B24: SS-133/2025 | C24: IN - 5250-24-085 - Phase-Out do Diesel S500 - Projeto | D24: 1.1.1.17 | E24: Serviços de Escaneamento a Laser | F24: Hs | G24: 35.2 | H24: 4441.0109 | I24: =H24*G24 -> 156323.58 | K24: 0 | L24: =G24-K24 -> 35.2 | X24: =$H24*K24 -> 0 | Y24: =$H24*L24 -> 156323.58 | Z24: =$H24*O24 -> 0 | AA24: =$H24*P24 -> 0 | AB24: =$H24*Q24 -> 0 | AC24: =$H24*R24 -> 0 | AD24: =$H24*S24 -> 0 | AE24: =$H24*T24 -> 0 | AF24: =$H24*U24 -> 0 | AG24: =$H24*V24 -> 0 | AH24: =SUM(Z24:AG24) -> 0 | AK24: =L24-SUM(N24:V24) -> 35.2 | AL24: =Y24-SUM(Z24:AG24) -> 156323.58
B25: SS-191/2026 | C25: PMBC - REATIVAÇÃO DE BANHEIRO SANITÁRIO - 6° ANDAR REATORES 52-R-01 ABCD - ELABORAÇÃO DE PROJETOS | D25: 1.7.3.1 | E25: Serviços Técnicos Especializados de Projeto - Hora Normal | F25: Hs | G25: 88.4 | H25: 186.45 | I25: =H25*G25 -> 16482.18 | K25: 0 | L25: =G25-K25 -> 88.4 | P25: =G25 -> 88.4 | X25: =$H25*K25 -> 0 | Y25: =$H25*L25 -> 16482.18 | Z25: =$H25*O25 -> 0 | AA25: =$H25*P25 -> 16482.18 | AB25: =$H25*Q25 -> 0 | AC25: =$H25*R25 -> 0 | AD25: =$H25*S25 -> 0 | AE25: =$H25*T25 -> 0 | AF25: =$H25*U25 -> 0 | AG25: =$H25*V25 -> 0 | AH25: =SUM(Z25:AG25) -> 16482.18 | AK25: =L25-SUM(N25:V25) -> 0 | AL25: =Y25-SUM(Z25:AG25) -> 0
B26: SS-195/2026 | C26: PMBC - 27-TQ-01 E - ELABORAÇÃO PROJETOS LGE | D26: 1.1.1.16 | E26: Levantamento topográfico | F26: Hs | G26: 26.4 | H26: 231.15275 | I26: =H26*G26 -> 6102.4326 | K26: 0 | L26: =G26-K26 -> 26.4 | P26: =G26 -> 26.4 | X26: =$H26*K26 -> 0 | Y26: =$H26*L26 -> 6102.4326 | Z26: =$H26*O26 -> 0 | AA26: =$H26*P26 -> 6102.4326 | AB26: =$H26*Q26 -> 0 | AC26: =$H26*R26 -> 0 | AD26: =$H26*S26 -> 0 | AE26: =$H26*T26 -> 0 | AF26: =$H26*U26 -> 0 | AG26: =$H26*V26 -> 0 | AH26: =SUM(Z26:AG26) -> 6102.4326 | AK26: =L26-SUM(N26:V26) -> 0 | AL26: =Y26-SUM(Z26:AG26) -> 0
B27: SS-195/2026 | C27: PMBC - 27-TQ-01 E - ELABORAÇÃO PROJETOS LGE | D27: 1.7.3.1 | E27: Serviços Técnicos Especializados de Projeto - Hora Normal | F27: Hs | G27: 88 | H27: 186.45 | I27: =H27*G27 -> 16407.6 | K27: 0 | L27: =G27-K27 -> 88 | P27: =G27 -> 88 | X27: =$H27*K27 -> 0 | Y27: =$H27*L27 -> 16407.6 | Z27: =$H27*O27 -> 0 | AA27: =$H27*P27 -> 16407.6 | AB27: =$H27*Q27 -> 0 | AC27: =$H27*R27 -> 0 | AD27: =$H27*S27 -> 0 | AE27: =$H27*T27 -> 0 | AF27: =$H27*U27 -> 0 | AG27: =$H27*V27 -> 0 | AH27: =SUM(Z27:AG27) -> 16407.6 | AK27: =L27-SUM(N27:V27) -> 0 | AL27: =Y27-SUM(Z27:AG27) -> 0
B28: SS-75/2026 | C28: TOPOGRAFIA - 0027-TQ-0037B | D28: 1.1.1.16 | E28: Levantamento topográfico | F28: Hs | G28: 35.2 | H28: 231.15275 | I28: =H28*G28 -> 8136.5768 | K28: =G28-26.4 -> 8.8 | L28: =G28-K28 -> 26.4 | O28: =L28 -> 26.4 | X28: =$H28*K28 -> 2034.1442 | Y28: =$H28*L28 -> 6102.4326 | Z28: =$H28*O28 -> 6102.4326 | AA28: =$H28*P28 -> 0 | AB28: =$H28*Q28 -> 0 | AC28: =$H28*R28 -> 0 | AD28: =$H28*S28 -> 0 | AE28: =$H28*T28 -> 0 | AF28: =$H28*U28 -> 0 | AG28: =$H28*V28 -> 0 | AH28: =SUM(Z28:AG28) -> 6102.4326 | AK28: =L28-SUM(N28:V28) -> 0 | AL28: =Y28-SUM(Z28:AG28) -> 0
B29: SS-76/2026 | C29: TOPOGRAFIA - 0027-TQ-0001N | D29: 1.1.1.16 | E29: Levantamento topográfico | F29: Hs | G29: 35.2 | H29: 231.15275 | I29: =H29*G29 -> 8136.5768 | K29: 0 | L29: =G29-K29 -> 35.2 | O29: =L29 -> 35.2 | X29: =$H29*K29 -> 0 | Y29: =$H29*L29 -> 8136.5768 | Z29: =$H29*O29 -> 8136.5768 | AA29: =$H29*P29 -> 0 | AB29: =$H29*Q29 -> 0 | AC29: =$H29*R29 -> 0 | AD29: =$H29*S29 -> 0 | AE29: =$H29*T29 -> 0 | AF29: =$H29*U29 -> 0 | AG29: =$H29*V29 -> 0 | AH29: =SUM(Z29:AG29) -> 8136.5768 | AK29: =L29-SUM(N29:V29) -> 0 | AL29: =Y29-SUM(Z29:AG29) -> 0
B30: SS-77/2026 | C30: TOPOGRAFIA - 0027-TQ-0001E | D30: 1.1.1.16 | E30: Levantamento topográfico | F30: Hs | G30: 35.2 | H30: 231.15275 | I30: =H30*G30 -> 8136.5768 | K30: 8.8 | L30: =G30-K30 -> 26.4 | O30: =L30 -> 26.4 | X30: =$H30*K30 -> 2034.1442 | Y30: =$H30*L30 -> 6102.4326 | Z30: =$H30*O30 -> 6102.4326 | AA30: =$H30*P30 -> 0 | AB30: =$H30*Q30 -> 0 | AC30: =$H30*R30 -> 0 | AD30: =$H30*S30 -> 0 | AE30: =$H30*T30 -> 0 | AF30: =$H30*U30 -> 0 | AG30: =$H30*V30 -> 0 | AH30: =SUM(Z30:AG30) -> 6102.4326 | AK30: =L30-SUM(N30:V30) -> 0 | AL30: =Y30-SUM(Z30:AG30) -> 0
B31: SS-81/2026 | C31: TOPOGRAFIA U-623 / DRENAGEM PLUVIAL - BLOCO L | D31: 1.1.1.16 | E31: Levantamento topográfico | F31: Hs | G31: 132 | H31: 231.15275 | I31: =H31*G31 -> 30512.163 | K31: =G31-92.4 -> 39.6 | L31: =G31-K31 -> 92.4 | P31: =L31 -> 92.4 | X31: =$H31*K31 -> 9153.6489 | Y31: =$H31*L31 -> 21358.514 | Z31: =$H31*O31 -> 0 | AA31: =$H31*P31 -> 21358.514 | AB31: =$H31*Q31 -> 0 | AC31: =$H31*R31 -> 0 | AD31: =$H31*S31 -> 0 | AE31: =$H31*T31 -> 0 | AF31: =$H31*U31 -> 0 | AG31: =$H31*V31 -> 0 | AH31: =SUM(Z31:AG31) -> 21358.514 | AK31: =L31-SUM(N31:V31) -> 0 | AL31: =Y31-SUM(Z31:AG31) -> 0
B32: SS-82/2026 | C32: TOPOGRAFIA - DRENAGEM CONTAMINADA BLOCO G | D32: 1.1.1.16 | E32: Levantamento topográfico | F32: Hs | G32: 132 | H32: 231.15275 | I32: =H32*G32 -> 30512.163 | K32: =G32-61.6 -> 70.4 | L32: =G32-K32 -> 61.6 | P32: =L32 -> 61.6 | X32: =$H32*K32 -> 16273.154 | Y32: =$H32*L32 -> 14239.009 | Z32: =$H32*O32 -> 0 | AA32: =$H32*P32 -> 14239.009 | AB32: =$H32*Q32 -> 0 | AC32: =$H32*R32 -> 0 | AD32: =$H32*S32 -> 0 | AE32: =$H32*T32 -> 0 | AF32: =$H32*U32 -> 0 | AG32: =$H32*V32 -> 0 | AH32: =SUM(Z32:AG32) -> 14239.009 | AK32: =L32-SUM(N32:V32) -> 0 | AL32: =Y32-SUM(Z32:AG32) -> 0
B33: SS-83/2026 | C33: TOPOGRAFIA - ESTRUTURA PLATAFORMA PERMUTADORES | D33: 1.1.1.16 | E33: Levantamento topográfico | F33: Hs | G33: 132 | H33: 231.15275 | I33: =H33*G33 -> 30512.163 | K33: 0 | L33: =G33-K33 -> 132 | P33: =G33 -> 132 | X33: =$H33*K33 -> 0 | Y33: =$H33*L33 -> 30512.163 | Z33: =$H33*O33 -> 0 | AA33: =$H33*P33 -> 30512.163 | AB33: =$H33*Q33 -> 0 | AC33: =$H33*R33 -> 0 | AD33: =$H33*S33 -> 0 | AE33: =$H33*T33 -> 0 | AF33: =$H33*U33 -> 0 | AG33: =$H33*V33 -> 0 | AH33: =SUM(Z33:AG33) -> 30512.163 | AK33: =L33-SUM(N33:V33) -> 0 | AL33: =Y33-SUM(Z33:AG33) -> 0

Sheet PREV. MENSAL MAIO26
A1: EQUIPAMENTOS 14 MEDIÇÃO 26/04/2026 Á 25/05/2026 | AL1: APLICAÇÕES PREPONDERANTES - ÁREAS
A2: EQUIPAMENTO | C2: 46138 | D2: 46139 | E2: 46140 | F2: 46141 | G2: 46142 | H2: 46143 | I2: 46144 | J2: 46145 | K2: 46146 | L2: 46147 | M2: 46148 | N2: 46149 | O2: 46150 | P2: 46151 | Q2: 46152 | R2: 46153 | S2: 46154 | T2: 46155 | U2: 46156 | V2: 46157 | W2: 46158 | X2: 46159 | Y2: 46160 | Z2: 46161 | AA2: 46162 | AB2: 46163 | AC2: 46164 | AD2: 46165 | AE2: 46166 | AF2: 46167 | AG2: 46168 | AH2: SOMA HH | AI2: Item | AJ2: Valor do Item | AK2: Valor Previsto | AL2: APLICAÇÃO 1 | AM2: APLICAÇÃO 2 | AN2: APLICAÇÃO 3 | AO2: APLICAÇÃO 4
B3: TAG | C3: Domingo | D3: Segunda-feira | E3: Terça-feira | F3: Quarta-feira | G3: Quinta-feira | H3: Sexta-feira | I3: Sábado | J3: Domingo | K3: Segunda-feira | L3: Terça-feira | M3: Quarta-feira | N3: Quinta-feira | O3: Sexta-feira | P3: Sábado | Q3: Domingo | R3: Segunda-feira | S3: Terça-feira | T3: Quarta-feira | U3: Quinta-feira | V3: Sexta-feira | W3: Sábado | X3: Domingo | Y3: Segunda-feira | Z3: Terça-feira | AA3: Quarta-feira | AB3: Quinta-feira | AC3: Sexta-feira | AD3: Sábado | AE3: Domingo | AF3: Segunda-feira | AG3: Terça-feira | AK3: =SUM(AK4:AK51) -> 2120004.8
A4: GUINDASTE 120TON | B4: GD01 | D4: 8.8 | E4: 8.8 | F4: 8.8 | G4: 8.8 | K4: 8.8 | L4: 8.8 | M4: 8.8 | N4: 8.8 | O4: 8.8 | R4: 8.8 | S4: 8.8 | T4: 8.8 | U4: 8.8 | V4: 8.8 | Y4: 8.8 | Z4: 8.8 | AA4: 8.8 | AB4: 8.8 | AC4: 8.8 | AF4: 8.8 | AH4: =SUM(C4:AG4) -> 176 | AI4: 1.5.1.3 | AJ4: 1175.3156 | AK4: 206855.55 | AL4: TQ'S 116 | AM4: ETDI
A5: GUINDASTE 70TON | B5: GD02 | D5: 8.8 | E5: 8.8 | F5: 8.8 | G5: 8.8 | K5: 8.8 | L5: 8.8 | M5: 8.8 | N5: 8.8 | O5: 8.8 | R5: 8.8 | S5: 8.8 | T5: 8.8 | U5: 8.8 | V5: 8.8 | Y5: 8.8 | Z5: 8.8 | AA5: 8.8 | AB5: 8.8 | AC5: 8.8 | AF5: 8.8 | AH5: =SUM(C5:AG5) -> 176 | AI5: 1.5.1.2 | AJ5: 740.58398 | AK5: 130342.78 | AL5: PHASEOUT | AM5: ENVELOPE GPI
A6: CAMINHÃO MUNCK | B6: MK01 | D6: 8.8 | E6: 8.8 | F6: 8.8 | G6: 8.8 | K6: 8.8 | L6: 8.8 | M6: 8.8 | N6: 8.8 | O6: 8.8 | R6: 8.8 | S6: 8.8 | T6: 8.8 | U6: 8.8 | V6: 8.8 | Y6: 8.8 | Z6: 8.8 | AA6: 8.8 | AB6: 8.8 | AC6: 8.8 | AF6: 8.8 | AH6: =SUM(C6:AG6) -> 176 | AI6: 1.5.2.1 | AJ6: 429.45411 | AK6: 75583.923 | AL6: DEMANDAS SPOT
A7: CAMINHÃO MUNCK | B7: MK02 | D7: 8.8 | E7: 8.8 | F7: 8.8 | G7: 8.8 | K7: 8.8 | L7: 8.8 | M7: 8.8 | N7: 8.8 | O7: 8.8 | R7: 8.8 | S7: 8.8 | T7: 8.8 | U7: 8.8 | V7: 8.8 | Y7: 8.8 | Z7: 8.8 | AA7: 8.8 | AB7: 8.8 | AC7: 8.8 | AF7: 8.8 | AH7: =SUM(C7:AG7) -> 176 | AI7: 1.5.2.1 | AJ7: 429.45411 | AK7: 75583.923 | AL7: DEMANDAS PROJ. CIVIL | AM7: LOGISTICA DE AREA
A8: CAMINHÃO MUNCK | B8: MK03 | D8: 8.8 | E8: 8.8 | F8: 8.8 | G8: 8.8 | K8: 8.8 | L8: 8.8 | M8: 8.8 | N8: 8.8 | O8: 8.8 | R8: 8.8 | S8: 8.8 | T8: 8.8 | U8: 8.8 | V8: 8.8 | Y8: 8.8 | Z8: 8.8 | AA8: 8.8 | AB8: 8.8 | AC8: 8.8 | AF8: 8.8 | AH8: =SUM(C8:AG8) -> 176 | AI8: 1.5.2.1 | AJ8: 429.45411 | AK8: 75583.923 | AL8: UNIDADE 513 | AM8: DEMANDAS CALDEIRARIA | AN8: LOGISTICA DE AREA
A9: CAMINHÃO MUNCK | B9: MK04 | D9: 8.8 | E9: 8.8 | F9: 8.8 | G9: 8.8 | K9: 8.8 | L9: 8.8 | M9: 8.8 | N9: 8.8 | O9: 8.8 | R9: 8.8 | S9: 8.8 | T9: 8.8 | U9: 8.8 | V9: 8.8 | Y9: 8.8 | Z9: 8.8 | AA9: 8.8 | AB9: 8.8 | AC9: 8.8 | AF9: 8.8 | AH9: =SUM(C9:AG9) -> 176 | AI9: 1.5.2.1 | AJ9: 429.45411 | AK9: 75583.923 | AL9: UNIDADE 121 CIVIL
A10: ESCAVADEIRA HIDRÁULICA | B10: ES03 | D10: 8.8 | E10: 8.8 | F10: 8.8 | G10: 8.8 | K10: 8.8 | L10: 8.8 | M10: 8.8 | N10: 8.8 | O10: 8.8 | R10: 8.8 | S10: 8.8 | T10: 8.8 | U10: 8.8 | V10: 8.8 | Y10: 8.8 | Z10: 8.8 | AA10: 8.8 | AB10: 8.8 | AC10: 8.8 | AF10: 8.8 | AH10: =SUM(C10:AG10) -> 176 | AI10: 1.5.2.4 | AJ10: 338.54497 | AK10: 59583.915 | AL10: ETDI
A11: ESCAVADEIRA HIDRÁULICA | B11: ES02 | D11: 8.8 | E11: 8.8 | F11: 8.8 | G11: 8.8 | K11: 8.8 | L11: 8.8 | M11: 8.8 | N11: 8.8 | O11: 8.8 | AH11: =SUM(C11:AG11) -> 79.2 | AI11: 1.5.2.4 | AJ11: 338.54497 | AK11: 26812.762 | AL11: PORTARIA 03 | AM11: CORREGO PALMEIRAS
A12: RETROESCAVADEIRA | B12: RT06 | D12: 8.8 | E12: 8.8 | F12: 8.8 | G12: 8.8 | K12: 8.8 | L12: 8.8 | M12: 8.8 | N12: 8.8 | O12: 8.8 | R12: 8.8 | S12: 8.8 | T12: 8.8 | U12: 8.8 | V12: 8.8 | Y12: 8.8 | Z12: 8.8 | AA12: 8.8 | AB12: 8.8 | AC12: 8.8 | AF12: 8.8 | AH12: =SUM(C12:AG12) -> 176 | AI12: 1.5.2.6 | AJ12: 280.78208 | AK12: 49417.647 | AL12: LIMPEZA DA ÁREA DO PM
A13: RETROESCAVADEIRA | B13: RT03 | D13: 8.8 | E13: 8.8 | F13: 8.8 | G13: 8.8 | K13: 8.8 | L13: 8.8 | M13: 8.8 | N13: 8.8 | O13: 8.8 | R13: 8.8 | S13: 8.8 | T13: 8.8 | U13: 8.8 | V13: 8.8 | Y13: 8.8 | Z13: 8.8 | AA13: 8.8 | AB13: 8.8 | AC13: 8.8 | AF13: 8.8 | AH13: =SUM(C13:AG13) -> 176 | AI13: 1.5.2.6 | AJ13: 280.78208 | AK13: 49417.647 | AL13: DEMANDAS MANUT CIVIL
A14: RETROESCAVADEIRA | B14: RT02 | D14: 8.8 | E14: 8.8 | F14: 8.8 | G14: 8.8 | K14: 8.8 | L14: 8.8 | M14: 8.8 | N14: 8.8 | O14: 8.8 | R14: 8.8 | S14: 8.8 | T14: 8.8 | U14: 8.8 | V14: 8.8 | Y14: 8.8 | Z14: 8.8 | AA14: 8.8 | AB14: 8.8 | AC14: 8.8 | AF14: 8.8 | AH14: =SUM(C14:AG14) -> 176 | AI14: 1.5.2.6 | AJ14: 280.78208 | AK14: 49417.647 | AL14: UNIDADE 111
A15: RETROESCAVADEIRA | B15: RT05 | D15: 8.8 | E15: 8.8 | F15: 8.8 | G15: 8.8 | K15: 8.8 | L15: 8.8 | M15: 8.8 | AH15: =SUM(C15:AG15) -> 61.6 | AI15: 1.5.2.6 | AJ15: 280.78208 | AK15: 17296.176 | AL15: ETDI
A16: EMPILHADEIRA ATÉ 4 TON | B16: EP05 | D16: 8.8 | E16: 8.8 | F16: 8.8 | G16: 8.8 | K16: 8.8 | L16: 8.8 | M16: 8.8 | N16: 8.8 | O16: 8.8 | R16: 8.8 | S16: 8.8 | T16: 8.8 | U16: 8.8 | V16: 8.8 | Y16: 8.8 | Z16: 8.8 | AA16: 8.8 | AB16: 8.8 | AC16: 8.8 | AF16: 8.8 | AH16: =SUM(C16:AG16) -> 176 | AI16: 1.5.2.18 | AJ16: 237.74569 | AK16: 41843.242 | AL16: PIPE SHOP | AM16: CONTAINERS SMS | AN16: APOIO ARMAZEM S2 | AO16: LOGISTICA DE ÁREAS
A17: EMPILHADEIRA ATÉ 4 TON | B17: EP04 | D17: 8.8 | E17: 8.8 | F17: 8.8 | G17: 8.8 | K17: 8.8 | L17: 8.8 | M17: 8.8 | N17: 8.8 | O17: 8.8 | R17: 8.8 | S17: 8.8 | T17: 8.8 | U17: 8.8 | V17: 8.8 | Y17: 8.8 | Z17: 8.8 | AA17: 8.8 | AB17: 8.8 | AC17: 8.8 | AF17: 8.8 | AH17: =SUM(C17:AG17) -> 176 | AI17: 1.5.2.18 | AJ17: 237.74569 | AK17: 41843.242
A18: EMPILHADEIRA ATÉ 7 TON | B18: EP06 | D18: 8.8 | E18: 8.8 | F18: 8.8 | G18: 8.8 | K18: 8.8 | L18: 8.8 | M18: 8.8 | N18: 8.8 | O18: 8.8 | R18: 8.8 | S18: 8.8 | T18: 8.8 | U18: 8.8 | V18: 8.8 | Y18: 8.8 | Z18: 8.8 | AA18: 8.8 | AB18: 8.8 | AC18: 8.8 | AF18: 8.8 | AH18: =SUM(C18:AG18) -> 176 | AI18: 1.5.2.19 | AJ18: 240.12394 | AK18: 42261.813
A19: PLATAFORMA ELEVATÓRIA | B19: PTA01 | D19: 8.8 | E19: 8.8 | F19: 8.8 | G19: 8.8 | K19: 8.8 | L19: 8.8 | M19: 8.8 | AH19: =SUM(C19:AG19) -> 61.6 | AI19: 1.5.2.3 | AJ19: 788.0167 | AK19: 48541.829 | AL19: PIPE SHOP | AM19: GALPÃO S2 | AN19: LIMPEZA DE TENDAS | AO19: DEMANDA COMPLEMENTAR
A20: PLATAFORMA ELEVATÓRIA | B20: PTA02 | D20: 8.8 | E20: 8.8 | F20: 8.8 | G20: 8.8 | K20: 8.8 | L20: 8.8 | M20: 8.8 | AH20: =SUM(C20:AG20) -> 61.6 | AI20: 1.5.2.3 | AJ20: 788.0167 | AK20: 48541.829 | AL20: LABORATÓRIO | AM20: COQUE | AN20: UNIDADE 43 | AO20: UNIDADE 39
A21: CAMINHÃO BÁSCULA | B21: CB01 | D21: 8.8 | E21: 8.8 | F21: 8.8 | G21: 8.8 | K21: 8.8 | L21: 8.8 | M21: 8.8 | N21: 8.8 | O21: 8.8 | R21: 8.8 | S21: 8.8 | T21: 8.8 | U21: 8.8 | V21: 8.8 | Y21: 8.8 | Z21: 8.8 | AA21: 8.8 | AB21: 8.8 | AC21: 8.8 | AF21: 8.8 | AH21: =SUM(C21:AG21) -> 176 | AI21: 1.5.2.7 | AJ21: 419.49354 | AK21: 73830.863 | AL21: ETDI | AM21: GPI
A22: MINI ESCAVADEIRA (BOB CAT) | B22: ME01 | D22: 8.8 | E22: 8.8 | F22: 8.8 | G22: 8.8 | K22: 8.8 | L22: 8.8 | M22: 8.8 | N22: 8.8 | O22: 8.8 | R22: 8.8 | S22: 8.8 | T22: 8.8 | U22: 8.8 | V22: 8.8 | Y22: 8.8 | Z22: 8.8 | AA22: 8.8 | AB22: 8.8 | AC22: 8.8 | AF22: 8.8 | AH22: =SUM(C22:AG22) -> 176 | AI22: 1.5.2.27 | AJ22: 271.08606 | AK22: 47711.146 | AL22: ETDI | AM22: GPI
A23: ROLO COMPACTADOR | B23: RC01 | D23: 8.8 | E23: 8.8 | F23: 8.8 | G23: 8.8 | K23: 8.8 | L23: 8.8 | M23: 8.8 | N23: 8.8 | O23: 8.8 | R23: 8.8 | S23: 8.8 | T23: 8.8 | U23: 8.8 | V23: 8.8 | Y23: 8.8 | Z23: 8.8 | AA23: 8.8 | AB23: 8.8 | AC23: 8.8 | AF23: 8.8 | AH23: =SUM(C23:AG23) -> 176 | AI23: 1.5.2.23 | AJ23: 254.67169 | AK23: 44822.218 | AL23: ASFALTO | AM23: DEMANDAS PROJ. CIVIL
A24: CAMINHÃO VÁCUO | B24: VC02 | D24: 8.8 | E24: 8.8 | F24: 8.8 | G24: 8.8 | K24: 8.8 | L24: 8.8 | M24: 8.8 | N24: 8.8 | O24: 8.8 | R24: 8.8 | S24: 8.8 | T24: 8.8 | U24: 8.8 | V24: 8.8 | Y24: 8.8 | Z24: 8.8 | AA24: 8.8 | AB24: 8.8 | AC24: 8.8 | AF24: 8.8 | AH24: =SUM(C24:AG24) -> 176 | AI24: 1.5.2.2 | AJ24: 351.34763 | AK24: 61837.183 | AL24: ETDI | AM24: PT 200 | AN24: UNIDADE 47
A25: GERADOR | B25: GR01 | D25: 1 | E25: 1 | F25: 1 | G25: 1 | K25: 1 | L25: 1 | M25: 1 | N25: 1 | O25: 1 | R25: 1 | S25: 1 | T25: 1 | U25: 1 | V25: 1 | Y25: 1 | Z25: 1 | AA25: 1 | AB25: 1 | AC25: 1 | AF25: 1 | AH25: =SUM(C25:AG25) -> 20 | AI25: 1.5.2.11 | AJ25: 3804.6217 | AK25: 76092.435 | AL25: ETDI
A26: GERADOR | B26: GR02 | D26: 1 | E26: 1 | F26: 1 | G26: 1 | K26: 1 | L26: 1 | M26: 1 | N26: 1 | O26: 1 | R26: 1 | S26: 1 | T26: 1 | U26: 1 | V26: 1 | Y26: 1 | Z26: 1 | AA26: 1 | AB26: 1 | AC26: 1 | AF26: 1 | AH26: =SUM(C26:AG26) -> 20 | AI26: 1.5.2.11 | AJ26: 3804.6217 | AK26: 76092.435 | AL26: FERRMENTARIA C3
A27: GERADOR | B27: GR04 | D27: 1 | E27: 1 | F27: 1 | G27: 1 | K27: 1 | L27: 1 | M27: 1 | N27: 1 | O27: 1 | R27: 1 | S27: 1 | T27: 1 | U27: 1 | V27: 1 | Y27: 1 | Z27: 1 | AA27: 1 | AB27: 1 | AC27: 1 | AF27: 1 | AH27: =SUM(C27:AG27) -> 20 | AI27: 1.5.2.11 | AJ27: 3804.6217 | AK27: 76092.435 | AL27: TANQUE 116
A28: GERADOR | B28: GR05 | D28: 1 | E28: 1 | F28: 1 | G28: 1 | K28: 1 | L28: 1 | M28: 1 | N28: 1 | O28: 1 | R28: 1 | S28: 1 | T28: 1 | U28: 1 | V28: 1 | Y28: 1 | Z28: 1 | AA28: 1 | AB28: 1 | AC28: 1 | AF28: 1 | AH28: =SUM(C28:AG28) -> 20 | AI28: 1.5.2.11 | AJ28: 3804.6217 | AK28: 76092.435 | AL28: AV B
A29: GERADOR | B29: GR07 | D29: 1 | E29: 1 | F29: 1 | G29: 1 | K29: 1 | L29: 1 | M29: 1 | N29: 1 | O29: 1 | R29: 1 | S29: 1 | T29: 1 | U29: 1 | V29: 1 | Y29: 1 | Z29: 1 | AA29: 1 | AB29: 1 | AC29: 1 | AF29: 1 | AH29: =SUM(C29:AG29) -> 20 | AI29: 1.5.2.11 | AJ29: 3804.6217 | AK29: 76092.435 | AL29: TANQUE 128
A30: GERADOR | B30: GR08 | D30: 1 | E30: 1 | F30: 1 | G30: 1 | K30: 1 | L30: 1 | M30: 1 | N30: 1 | O30: 1 | R30: 1 | S30: 1 | T30: 1 | U30: 1 | V30: 1 | Y30: 1 | Z30: 1 | AA30: 1 | AB30: 1 | AC30: 1 | AF30: 1 | AH30: =SUM(C30:AG30) -> 20 | AI30: 1.5.2.11 | AJ30: 3804.6217 | AK30: 76092.435 | AL30: UFV
A31: GERADOR | B31: GR10 | D31: 1 | E31: 1 | F31: 1 | G31: 1 | K31: 1 | L31: 1 | M31: 1 | N31: 1 | O31: 1 | R31: 1 | S31: 1 | T31: 1 | U31: 1 | V31: 1 | Y31: 1 | Z31: 1 | AA31: 1 | AB31: 1 | AC31: 1 | AF31: 1 | AH31: =SUM(C31:AG31) -> 20 | AI31: 1.5.2.11 | AJ31: 3804.6217 | AK31: 76092.435 | AL31: ÁREA DO FLAIRE
A32: GERADOR | D32: 1 | E32: 1 | F32: 1 | G32: 1 | K32: 1 | L32: 1 | M32: 1 | N32: 1 | O32: 1 | R32: 1 | S32: 1 | T32: 1 | U32: 1 | V32: 1 | Y32: 1 | Z32: 1 | AA32: 1 | AB32: 1 | AC32: 1 | AF32: 1 | AH32: =SUM(C32:AG32) -> 20 | AI32: 1.5.2.11 | AJ32: 3804.6217 | AK32: 76092.435 | AL32: TUBO EXPANSOR
A33: COMPRESSOR 750 PCM | B33: CP01 | D33: 1 | E33: 1 | F33: 1 | G33: 1 | K33: 1 | L33: 1 | M33: 1 | N33: 1 | O33: 1 | R33: 1 | S33: 1 | T33: 1 | U33: 1 | V33: 1 | Y33: 1 | Z33: 1 | AA33: 1 | AB33: 1 | AC33: 1 | AF33: 1 | AH33: =SUM(C33:AG33) -> 20 | AI33: 1.5.2.9 | AJ33: 1965.6284 | AK33: 39312.569 | AL33: ETDI
A34: COMPRESSOR 750 PCM | B34: CP03 | D34: 1 | E34: 1 | F34: 1 | G34: 1 | K34: 1 | L34: 1 | M34: 1 | N34: 1 | O34: 1 | R34: 1 | S34: 1 | T34: 1 | U34: 1 | V34: 1 | Y34: 1 | Z34: 1 | AA34: 1 | AB34: 1 | AC34: 1 | AF34: 1 | AH34: =SUM(C34:AG34) -> 20 | AI34: 1.5.2.9 | AJ34: 1965.6284 | AK34: 39312.569 | AL34: AREA DE JATO
A35: COMPRESSOR DE AR 900 PCM | B35: CP06 | D35: 1 | E35: 1 | F35: 1 | G35: 1 | K35: 1 | L35: 1 | M35: 1 | N35: 1 | O35: 1 | R35: 1 | S35: 1 | T35: 1 | U35: 1 | V35: 1 | Y35: 1 | Z35: 1 | AA35: 1 | AB35: 1 | AC35: 1 | AF35: 1 | AH35: =SUM(C35:AG35) -> 20 | AI35: 1.5.2.10 | AJ35: 2149.0404 | AK35: 42980.809 | AL35: C5+
A36: COMPRESSOR DE AR 900 PCM | AH36: =SUM(C36:AG36) -> 0 | AL36: TUBO EXPANSOR
A37: COMPRESSOR DE AR 900 PCM | AH37: =SUM(C37:AG37) -> 0 | AL37: TUBO EXPANSOR
A38: COMPRESSOR DE AR 900 PCM | AH38: =SUM(C38:AG38) -> 0 | AL38: TUBO EXPANSOR
A39: SISTEMA DE FORNECIMENTO DE AR RESPITAVEL | AH39: =SUM(C39:AG39) -> 0 | AL39: TUBO EXPANSOR
A40: TORRE DE ILUMINÇÃO | B40: TR03 | C40: 1 | D40: 1 | E40: 1 | F40: 1 | G40: 1 | H40: 1 | I40: 1 | J40: 1 | K40: 1 | L40: 1 | M40: 1 | N40: 1 | O40: 1 | P40: 1 | Q40: 1 | R40: 1 | S40: 1 | T40: 1 | U40: 1 | V40: 1 | W40: 1 | X40: 1 | Y40: 1 | Z40: 1 | AA40: 1 | AB40: 1 | AC40: 1 | AD40: 1 | AE40: 1 | AF40: 1 | AH40: =SUM(C40:AG40) -> 30 | AI40: 1.5.2.16 | AJ40: 223.55316 | AK40: 6706.5949 | AL40: UNIDADE 54
A41: TORRE DE ILUMINÇÃO | B41: TR04 | C41: 1 | D41: 1 | E41: 1 | F41: 1 | G41: 1 | H41: 1 | I41: 1 | J41: 1 | K41: 1 | L41: 1 | M41: 1 | N41: 1 | O41: 1 | P41: 1 | Q41: 1 | R41: 1 | S41: 1 | T41: 1 | U41: 1 | V41: 1 | W41: 1 | X41: 1 | Y41: 1 | Z41: 1 | AA41: 1 | AB41: 1 | AC41: 1 | AD41: 1 | AE41: 1 | AF41: 1 | AH41: =SUM(C41:AG41) -> 30 | AI41: 1.5.2.16 | AJ41: 223.55316 | AK41: 6706.5949 | AL41: UNIDADE 54
A42: TORRE DE ILUMINÇÃO | B42: TR05 | C42: 1 | D42: 1 | E42: 1 | F42: 1 | G42: 1 | H42: 1 | I42: 1 | J42: 1 | K42: 1 | L42: 1 | M42: 1 | N42: 1 | O42: 1 | P42: 1 | Q42: 1 | R42: 1 | S42: 1 | T42: 1 | U42: 1 | V42: 1 | W42: 1 | X42: 1 | Y42: 1 | Z42: 1 | AA42: 1 | AB42: 1 | AC42: 1 | AD42: 1 | AE42: 1 | AF42: 1 | AH42: =SUM(C42:AG42) -> 30 | AI42: 1.5.2.16 | AJ42: 223.55316 | AK42: 6706.5949 | AL42: UFV
A43: TORRE DE ILUMINÇÃO | B43: TR06 | C43: 1 | D43: 1 | E43: 1 | F43: 1 | G43: 1 | H43: 1 | I43: 1 | J43: 1 | K43: 1 | L43: 1 | M43: 1 | N43: 1 | O43: 1 | P43: 1 | Q43: 1 | R43: 1 | S43: 1 | T43: 1 | U43: 1 | V43: 1 | W43: 1 | X43: 1 | Y43: 1 | Z43: 1 | AA43: 1 | AB43: 1 | AC43: 1 | AD43: 1 | AE43: 1 | AF43: 1 | AH43: =SUM(C43:AG43) -> 30 | AI43: 1.5.2.16 | AJ43: 223.55316 | AK43: 6706.5949 | AL43: UFV
A44: TORRE DE ILUMINÇÃO | B44: TR09 | C44: 1 | D44: 1 | E44: 1 | F44: 1 | G44: 1 | H44: 1 | I44: 1 | J44: 1 | K44: 1 | L44: 1 | M44: 1 | N44: 1 | O44: 1 | P44: 1 | Q44: 1 | R44: 1 | S44: 1 | T44: 1 | U44: 1 | V44: 1 | W44: 1 | X44: 1 | Y44: 1 | Z44: 1 | AA44: 1 | AB44: 1 | AC44: 1 | AD44: 1 | AE44: 1 | AF44: 1 | AH44: =SUM(C44:AG44) -> 30 | AI44: 1.5.2.16 | AJ44: 223.55316 | AK44: 6706.5949 | AL44: UFV
A45: TORRE DE ILUMINÇÃO | B45: TR10 | C45: 1 | D45: 1 | E45: 1 | F45: 1 | G45: 1 | H45: 1 | I45: 1 | J45: 1 | K45: 1 | L45: 1 | M45: 1 | N45: 1 | O45: 1 | P45: 1 | Q45: 1 | R45: 1 | S45: 1 | T45: 1 | U45: 1 | V45: 1 | W45: 1 | X45: 1 | Y45: 1 | Z45: 1 | AA45: 1 | AB45: 1 | AC45: 1 | AD45: 1 | AE45: 1 | AF45: 1 | AH45: =SUM(C45:AG45) -> 30 | AI45: 1.5.2.16 | AJ45: 223.55316 | AK45: 6706.5949 | AL45: UFV
A46: TORRE DE ILUMINÇÃO | B46: TR11 | C46: 1 | D46: 1 | E46: 1 | F46: 1 | G46: 1 | H46: 1 | I46: 1 | J46: 1 | K46: 1 | L46: 1 | M46: 1 | N46: 1 | O46: 1 | P46: 1 | Q46: 1 | R46: 1 | S46: 1 | T46: 1 | U46: 1 | V46: 1 | W46: 1 | X46: 1 | Y46: 1 | Z46: 1 | AA46: 1 | AB46: 1 | AC46: 1 | AD46: 1 | AE46: 1 | AF46: 1 | AH46: =SUM(C46:AG46) -> 30 | AI46: 1.5.2.16 | AJ46: 223.55316 | AK46: 6706.5949 | AL46: UFV
A47: CONTEINER FERRAMENTARIA | C47: 5 | D47: 5 | E47: 5 | F47: 5 | G47: 5 | H47: 5 | I47: 5 | J47: 5 | K47: 5 | L47: 5 | M47: 5 | N47: 5 | O47: 5 | P47: 5 | Q47: 5 | R47: 5 | S47: 5 | T47: 5 | U47: 5 | V47: 5 | W47: 5 | X47: 5 | Y47: 5 | Z47: 5 | AA47: 5 | AB47: 5 | AC47: 5 | AD47: 5 | AE47: 5 | AF47: 5 | AH47: =SUM(C47:AG47) -> 150 | AI47: 0 | AL47: FERRAMENTARIA
A48: CONTEINER UFV | C48: 4 | D48: 4 | E48: 4 | F48: 4 | G48: 4 | H48: 4 | I48: 4 | J48: 4 | K48: 4 | L48: 4 | M48: 4 | N48: 4 | O48: 4 | P48: 4 | Q48: 4 | R48: 4 | S48: 4 | T48: 4 | U48: 4 | V48: 4 | W48: 4 | X48: 4 | Y48: 4 | Z48: 4 | AA48: 4 | AB48: 4 | AC48: 4 | AD48: 4 | AE48: 4 | AF48: 4 | AH48: =SUM(C48:AG48) -> 120 | AI48: 0 | AL48: UFV
A49: AR CONCIONADO FERRAMENTARIA | C49: 2 | D49: 2 | E49: 2 | F49: 2 | G49: 2 | H49: 2 | I49: 2 | J49: 2 | K49: 2 | L49: 2 | M49: 2 | N49: 2 | O49: 2 | P49: 2 | Q49: 2 | R49: 2 | S49: 2 | T49: 2 | U49: 2 | V49: 2 | W49: 2 | X49: 2 | Y49: 2 | Z49: 2 | AA49: 2 | AB49: 2 | AC49: 2 | AD49: 2 | AE49: 2 | AF49: 2 | AH49: =SUM(C49:AG49) -> 60 | AI49: 0 | AL49: FERRAMENTARIA
A50: AR CONCIONADO UFV | C50: 2 | D50: 2 | E50: 2 | F50: 2 | G50: 2 | H50: 2 | I50: 2 | J50: 2 | K50: 2 | L50: 2 | M50: 2 | N50: 2 | O50: 2 | P50: 2 | Q50: 2 | R50: 2 | S50: 2 | T50: 2 | U50: 2 | V50: 2 | W50: 2 | X50: 2 | Y50: 2 | Z50: 2 | AA50: 2 | AB50: 2 | AC50: 2 | AD50: 2 | AE50: 2 | AF50: 2 | AH50: =SUM(C50:AG50) -> 60 | AI50: 0 | AL50: UFV
A54: SOMATÓRIA
A55: GUINDASTE 120TON | B55: =SUMIF($A$4:$A$50,A55,$AH$4:$AH$50) -> 176
A56: GUINDASTE 70TON | B56: =SUMIF($A$4:$A$50,A56,$AH$4:$AH$50) -> 176
A57: CAMINHÃO MUNCK | B57: =SUMIF($A$4:$A$50,A57,$AH$4:$AH$50) -> 704
A58: ESCAVADEIRA HIDRÁULICA | B58: =SUMIF($A$4:$A$50,A58,$AH$4:$AH$50) -> 255.2
A59: RETROESCAVADEIRA | B59: =SUMIF($A$4:$A$50,A59,$AH$4:$AH$50) -> 589.6
A60: EMPILHADEIRA ATÉ 4 TON | B60: =SUMIF($A$4:$A$50,A60,$AH$4:$AH$50) -> 352
A61: EMPILHADEIRA ATÉ 7 TON | B61: =SUMIF($A$4:$A$50,A61,$AH$4:$AH$50) -> 176
A62: PLATAFORMA ELEVATÓRIA | B62: =SUMIF($A$4:$A$50,A62,$AH$4:$AH$50) -> 123.2
A63: CAMINHÃO BÁSCULA | B63: =SUMIF($A$4:$A$50,A63,$AH$4:$AH$50) -> 176
A64: MINI ESCAVADEIRA (BOB CAT) | B64: =SUMIF($A$4:$A$50,A64,$AH$4:$AH$50) -> 176
A65: ROLO COMPACTADOR | B65: =SUMIF($A$4:$A$50,A65,$AH$4:$AH$50) -> 176
A66: CAMINHÃO VÁCUO | B66: =SUMIF($A$4:$A$50,A66,$AH$4:$AH$50) -> 176
... A75: AR CONCIONADO UFV | B75: =SUMIF($A$4:$A$50,A75,$AH$4:$AH$50) -> 60

Sheet MC_SS 228
L1: 46143 | M1: 46174 | N1: 46204 | O1: 46235 | P1: 46266
A2: Item | B2: Nome da Atividade | F2: ID da Atividade | G2: Prev | H2: Real | I2: Duração Original | J2: Data de Início do Projeto de BL | K2: Data de Término do Projeto de BL
F3: Atividades de Apoio a Everllence | G3: 0 | H3: 0 | I3: 88.6h | J3: 46156.66 | K3: 46176.561
A4: 1.4.11.3 | B4: Instalação de transmissor de pressão, pressão diferencial, pesagem, temperatura ou pressostato | C4: un | D4: 6 | F4: Instalar 6 novos sensores, conforme Everllence | G4: 0 | H4: 0 | I4: 38.0h | J4: 46156.66 | K4: 46164.618 | M4: =D4 -> 6
F5: Instalar sistema de purga | G5: 0 | H5: 0 | I5: 50.6h | J5: 46164.618 | K5: 46176.561
A7: 1.4.4.1 | B7: Instalação de painel de interligação, armário de SDCD ou PLC | C7: un | D7: 2.8 | F7: Desligamento, Remoção e Subistituição de Painéis | G7: 0 | H7: 0 | I7: 92.4h | J7: 46156.354 | K7: 46176.414
A8: 1.4.4.1 | B8: Instalação de painel de interligação, armário de SDCD ou PLC | F8: 4020-PN-115 | G8: 0 | H8: 0 | I8: 88.6h | J8: 46156.354 | K8: 46175.567 | N8: =1 -> 1
A9: 1.4.4.1 | B9: Instalação de painel de interligação, armário de SDCD ou PLC | F9: 4020-PN-116 | G9: 0 | H9: 0 | I9: 86.6h | J9: 46156.639 | K9: 46176.414 | N9: 1.8
A11: 1.4.12.1 | B11: Configuração de instrumento existente em malha aberta | C11: un | D11: 668 | F11: Testes de Malha - Loop Tests "A Frio" (Conforme Recomendação Everllence) | G11: 0 | H11: 0 | I11: 84.0h | J11: 46181.622 | K11: 46196.685
A12: 1.4.12.1 | B12: Configuração de instrumento existente em malha aberta | C12: un | F12: SIMPLEX | G12: 0 | H12: 0 | I12: 31.0h | J12: 46181.622 | K12: 46188.56 | M12: =668-N13-N14 -> 332
A13: 1.4.12.1 | B13: Configuração de instrumento existente em malha aberta | C13: un | F13: DUPLEX | G13: 0 | H13: 0 | I13: 48.0h | J13: 46188.56 | K13: 46196.685 | N13: 38
A14: 1.4.12.1 | B14: Configuração de instrumento existente em malha aberta | C14: un | F14: Testes de Malha - Loop Tests "A Quente" | G14: 0 | H14: 0 | I14: 89.4h | J14: 46197.354 | K14: 46216.6 | N14: 298
A16: 1.3.45.1 | B16: Interligação de painel de rearranjo | C16: un | D16: 315 | F16: Interligação e Lançamento Cabos | G16: 0 | H16: 0 | I16: 39.0h | J16: 46175.567 | K16: 46184.567 | M16: =D16 -> 315
A17: 1.3.45.2 | B17: Desligamento de painel de rearranjo | C17: un | D17: 315 | F17: Interligação dos Cabos e Multicabos Existentes | G17: 0 | H17: 0 | I17: 20.8h | J17: 46175.567 | K17: 46181.622 | M17: =D17 -> 315
F18: 4020-PN-115 | G18: 0 | H18: 0 | I18: 20.0h | J18: 46175.567 | K18: 46181.588
F19: 4020-PN-116 | G19: 0 | H19: 0 | I19: 17.0h | J19: 46176.414 | K19: 46181.622
A21: 1.3.48.2 | B21: Lançamento de multicabo de 3 até 12 pares | C21: m | D21: 75 | M21: =D21 -> 75
A22: 1.4.5.1 | B22: Com até 200 componentes | C22: un | D22: 26 | M22: =D22 -> 26
F38: ID da Atividade | G38: Programar % Concluída | H38: % de Desempenho Concluída | I38: Dur | J38: Início | K38: Término | M38: Data de Início do Projeto de BL | N38: Data de Término do Projeto de BL | O38: Calendário
F39: Interligação e Lançamento Cabos | G39: 0 | H39: 0 | I39: 39.0h | J39: 46175.567 | K39: 46184.567 | M39: 46175.567 | N39: 46184.567 | O39: Calendário C3 SEG A SEX 6,33h
F40: Interligação dos Cabos e Multicabos Existentes | G40: 0 | H40: 0 | I40: 20.8h | J40: 46175.567 | K40: 46181.622 | M40: 46175.567 | N40: 46181.622 | O40: Calendário C3 SEG A SEX 6,33h
F41: 4020-PN-115 | G41: 0 | H41: 0 | I41: 20.0h | J41: 46175.567 | K41: 46181.588 | M41: 46175.567 | N41: 46181.588 | O41: Calendário C3 SEG A SEX 6,33h
F42: 4020-PN-116 | G42: 0 | H42: 0 | I42: 17.0h | J42: 46176.414 | K42: 46181.622 | M42: 46176.414 | N42: 46181.622 | O42: Calendário C3 SEG A SEX 6,33h

Sheet MC_SS 172
L1: 46174 | M1: 46204 | N1: 46235 | O1: 46266
A2: Item | B2: Nome da Atividade | D2: MC1 | E2: MC2 | F2: Total | H2: ID da Atividade | I2: Duração Original | J2: Data de Início do Projeto de BL | K2: Data de Término do Projeto de BL
H3: Marcos Civil Projeto
H4: Liberação de Projeto
H5: Liberação de projeto para modificação de orçamento e cronograma
H6: P 27-TQ-116 - D | I6: 293.6h | J6: 46188.633 | K6: 46241.679
H7: Acesso TQ-01-D | I7: 279.0h | J7: 46188.633 | K7: 46240.342
H8: Preliminares | I8: 52.8h | J8: 46188.633 | K8: 46197.646
A9: 1.1.1.16 | B9: Levantamento topográfico | C9: hs | H9: Levantamento Topografico | I9: 17.6h | J9: 46197.646 | K9: 46202.4 | L9: =F9 -> 0
H10: Marcação de area | I10: 22.0h | J10: 46202.4 | K10: 46205.379
H11: Regularização de Solo | I11: 79.8h | J11: 46205.379 | K11: 46219.621
A12: 1.1.2.2 | B12: Escavação mecanizada em solo até 3m | C12: m³ | F12: 2.262 | H12: Escavação mecanica e manual de solo | I12: 27.0h | J12: 46205.379 | K12: 46210.608 | M12: =F12 -> 2.262
H13: Regularização de solo | I13: 17.6h | J13: 46210.608 | K13: 46213.363
H14: Compactação de solo | I14: 17.6h | J14: 46213.363 | K14: 46217.471
A15: 1.1.2.14 | B15: Fornecimento, compactação e espalhamento de brita ou bica corrida | C15: m³ | F15: 22.62 | H15: Aplicação de BGS e lona | I15: 17.6h | J15: 46217.471 | K15: 46219.621 | M15: =F15 -> 22.62
A16: 1.1.3.1 | B16: Forma em chapa compensada plastificada | C16: m³ | F16: 0.696 | H16: Forma | I16: 54.0h | J16: 46219.621 | K16: 46230.683 | N16: =F16 -> 0.696
A17: 1.1.3.5 | B17: Armadura Aço CA-50 ou CA-60 | C17: kg | F17: 240.96 | H17: Aço | I17: 17.6h | J17: 46230.683 | K17: 46233.438 | N17: =F17 -> 240.96
A18: 1.1.3.9 | B18: Concreto estrutural fck 30 MPa | C18: m³ | F18: 21.456 | H18: Concreto | I18: 8.8h | J18: 46233.438 | K18: 46234.492 | N18: =F18 -> 21.456
A19: 1.1.3.20 | B19: Junta serrada em piso | C19: m | F19: 29 | N19: =F19 -> 29
A20: 1.1.12.19 | B20: Tubo Dreno em PEAD - Ø8" a Ø10"em leito de brita | C20: m | F20: 12.57 | H20: Desforma | I20: 8.8h | J20: 46234.492 | K20: 46237.588 | N20: =F20 -> 12.57
A21: 1.1.11.2 | B21: Pintura em tinta acrílica | C21: m² | F21: 92.8 | H21: Pintura | I21: 17.6h | J21: 46237.588 | K21: 46240.342 | N21: 32 | O21: =F21-N21 -> 60.8
H22: Bases Plataforma de Acesso
H23: Levantamento Topografico | I23: 17.6h | J23: 46191.387 | K23: 46195.496
H24: Marcação de area | I24: 22.0h | J24: 46195.496 | K24: 46198.475
H25: Regularização de Solo | I25: 52.8h | J25: 46198.475 | K25: 46209.488
A26: 1.1.2.2 | B26: Escavação mecanizada em solo até 3m | C26: m³ | F26: 1.508 | H26: Escavação mecanica e manual de solo | I26: 17.6h | J26: 46198.475 | K26: 46202.625 | M26: =F26 -> 1.508
H27: Regularização de solo | I27: 17.6h | J27: 46202.625 | K27: 46205.379
A28: 1.1.3.7 | B28: Concreto fck 15 MPa | C28: m³ | F28: 2.1 | H28: Compactação de solo | I28: 17.6h | J28: 46205.379 | K28: 46209.488 | M28: =F28 -> 2.1
A29: 1.1.3.1 | B29: Forma em chapa compensada plastificada | C29: m³ | F29: 0.464 | H29: Forma | I29: 36.0h | J29: 46209.488 | K29: 46216.425 | M29: =F29 -> 0.464
A30: 1.1.3.5 | B30: Armadura Aço CA-50 ou CA-60 | C30: kg | F30: 160.64 | H30: Aço | I30: 72.0h | J30: 46216.425 | K30: 46227.654 | M30: =F30 -> 160.64
A31: 1.1.3.9 | B31: Concreto estrutural fck 30 MPa | C31: m³ | F31: 14.304 | H31: Concreto | I31: 58.0h | J31: 46227.654 | K31: 46239.571 | N31: =F31 -> 14.304
A32: 1.1.3.11 | B32: Graute de base cimentícia auto-adensável | C32: m³ | F32: 1.1 | N32: =F32 -> 1.1
A33: 1.1.3.14 | B33: Chumbadores e inserts metálicos embutidos em concreto | C33: kg | F33: 40 | N33: =F33 -> 40
H34: Desforma | I34: 17.6h | J34: 46239.571 | K34: 46241.679
H35: P 27-TQ-116 - F | I35: 269.2h | J35: 46205.629 | K35: 46255.596
H36: Acesso TQ-01-F | I36: 269.2h | J36: 46205.629 | K36: 46255.596
H37: Preliminares | I37: 52.2h | J37: 46205.629 | K37: 46216.617
H38: Levantamento Topografico | I38: 22.0h | J38: 46216.617 | K38: 46219.596
H39: Marcação de area | I39: 26.0h | J39: 46219.596 | K39: 46225.387
H40: Regularização de Solo | I40: 43.6h | J40: 46225.387 | K40: 46232.683
A41: 1.1.2.2 | B41: Escavação mecanizada em solo até 3m | C41: m³ | F41: 2.382 | H41: Escavação mecanica e manual de solo | I41: 26.0h | J41: 46225.387 | K41: 46230.575 | N41: =F41 -> 2.382
H42: Regularização de solo | I42: 17.6h | J42: 46230.575 | K42: 46232.683
H43: Compactação de solo | I43: 17.6h | J43: 46230.575 | K43: 46232.683
A44: 1.1.2.14 | B44: Fornecimento, compactação e espalhamento de brita ou bica corrida | C44: m³ | F44: 23.79 | H44: Aplicação de BGS e lona | I44: 17.6h | J44: 46230.575 | K44: 46232.683 | N44: =F44 -> 23.79
A45: 1.1.3.1 | B45: Forma em chapa compensada plastificada | C45: m³ | F45: 0.702 | H45: Forma | I45: 72.0h | J45: 46232.683 | K45: 46246.558 | N45: =F45 -> 0.702
A46: 1.1.3.5 | B46: Armadura Aço CA-50 ou CA-60 | C46: kg | F46: 232.32 | H46: Aço | I46: 36.0h | J46: 46239.621 | K46: 46246.558 | N46: =F46 -> 232.32
A47: 1.1.3.9 | B47: Concreto estrutural fck 30 MPa | C47: m³ | F47: 14.79 | H47: Concreto | I47: 8.8h | J47: 46246.558 | K47: 46247.613 | N47: =F47 -> 14.79
A48: 1.1.3.20 | B48: Junta serrada em piso | C48: m | F48: 30.5 | N48: =F48 -> 30.5
A49: 1.1.12.19 | B49: Tubo Dreno em PEAD - Ø8" a Ø10"em leito de brita | C49: m | F49: 13.22 | H49: Desforma | I49: 17.6h | J49: 46247.613 | K49: 46252.367 | O49: =F49 -> 13.22
A50: 1.1.11.2 | B50: Pintura em tinta acrílica | C50: m² | F50: 97.6 | H50: Pintura | I50: 27.0h | J50: 46252.367 | K50: 46255.596 | N50: 42 | O50: =F50-N50 -> 55.6
H51: Bases Plataforma de Acesso | I51: 231.8h | J51: 46210.358 | K51: 46252.683
H52: Levantamento Topografico | I52: 17.6h | J52: 46210.358 | K52: 46212.467
H53: Marcação de area | I53: 27.0h | J53: 46212.467 | K53: 46218.342
H54: Regularização de Solo | I54: 52.8h | J54: 46218.342 | K54: 46227.354
A55: 1.1.2.2 | B55: Escavação mecanizada em solo até 3m | C55: m³ | F55: 1.588 | H55: Escavação mecanica e manual de solo | I55: 17.6h | J55: 46218.342 | K55: 46220.45 | M55: =F55 -> 1.588
H56: Regularização de solo | I56: 17.6h | J56: 46220.45 | K56: 46224.6
A57: 1.1.3.7 | B57: Concreto fck 15 MPa | C57: m³ | F57: 3.9 | H57: Compactação de solo | I57: 17.6h | J57: 46224.6 | K57: 46227.354 | M57: =F57 -> 3.9
A58: 1.1.3.1 | B58: Forma em chapa compensada plastificada | C58: m³ | F58: 0.468 | H58: Forma | I58: 36.0h | J58: 46227.354 | K58: 46233.646 | M58: =F58 -> 0.468
A59: 1.1.3.5 | B59: Armadura Aço CA-50 ou CA-60 | C59: kg | F59: 154.88 | H59: Aço | I59: 72.0h | J59: 46233.646 | K59: 46247.479 | M59: =F59 -> 154.88
A60: 1.1.3.9 | B60: Concreto estrutural fck 30 MPa | C60: m³ | F60: 9.86 | H60: Concreto | I60: 17.6h | J60: 46247.479 | K60: 46251.629 | M60: =F60 -> 9.86
A61: 1.1.3.11 | B61: Graute de base cimentícia auto-adensável | C61: m³ | F61: 1.1 | H61: Desforma | I61: 8.8h | J61: 46251.629 | K61: 46252.683 | O61: =F61 -> 1.1
A62: 1.1.3.14 | B62: Chumbadores e inserts metálicos embutidos em concreto | C62: kg | F62: 40 | O62: =F62 -> 40
A64: 1.1.2.6 | B64: Aterro manual sem fornecimento de solo | C64: m³ | F64: 3.1 | O64: =F64 -> 3.1
H65: 27-TQ-116 - D | I65: 186.5h | J65: 46205.379 | K65: 46240.338
A66: 1.7.3.1 | B66: Serviços Técnicos Especializados de Projeto - Hora Normal | C66: Hs | E66: 0.5 | F66: 90 | M66: =F66 -> 90
A67: 1.3.17.3 | B67: Instalação de luminária/projetor em ambiente industrial | C67: un | D67: 24 | F67: 12 | H67: Iluminação | I67: 105.0h | J67: 46205.379 | K67: 46225.379 | N67: =F67 -> 12
A68: 1.3.20.1 | B68: Instalação de eletrodutos aparentes em ambiente industrial até 1 1/2" de diâmetro | C68: m | D68: 180 | F68: 90 | N68: =F68 -> 90
A69: 1.3.25.1 | B69: Lançamento e ligação de circuito de potência em eletroduto subterrâneo (envelope ou banco de dutos) | C69: m | D69: 180 | F69: 90 | N69: =F69 -> 90
A70: 1.3.34.1 | B70: Lançamento de cabo nu diretamente enterrado | C70: m | D70: 400 | F70: 200 | H70: Aterramento | I70: 186.5h | J70: 46205.379 | K70: 46240.338 | N70: =F70 -> 200
A71: 1.3.37.1 | B71: Medição de resistência de aterramento | C71: PONTO | D71: 4 | F71: 2 | N71: =F71-M71 -> 2
A72: 1.3.51.1 | B72: Conexão mecânica para malha de terra | C72: un | D72: 20 | F72: 10 | N72: =F72-M72 -> 10
H73: 27-TQ-116 - F | I73: 216.5h | J73: 46225.387 | K73: 46266.346
A74: 1.3.17.3 | B74: Instalação de luminária/projetor em ambiente industrial | C74: un | D74: =D67 -> 24 | E74: 0.5 | F74: 12 | H74: Iluminação | I74: 105.0h | J74: 46225.387 | K74: 46245.387 | N74: =F74 -> 12
A75: 1.3.20.1 | B75: Instalação de eletrodutos aparentes em ambiente industrial até 1 1/2" de diâmetro | C75: m | D75: =D68 -> 180 | F75: 90 | N75: =F75 -> 90
A76: 1.3.25.1 | B76: Lançamento e ligação de circuito de potência em eletroduto subterrâneo (envelope ou banco de dutos) | C76: m | D76: =D69 -> 180 | F76: 90 | N76: =F76 -> 90
A77: 1.3.34.1 | B77: Lançamento de cabo nu diretamente enterrado | C77: m | D77: =D70 -> 400 | F77: 200 | H77: Aterramento | I77: 216.5h | J77: 46225.387 | K77: 46266.346 | M77: 80 | N77: =200-M77 -> 120 | O77: =F77-M77-N77 -> 0
A78: 1.3.37.1 | B78: Medição de resistência de aterramento | C78: PONTO | D78: =D71 -> 4 | F78: 2 | O78: =F78-M78 -> 2
A79: 1.3.51.1 | B79: Conexão mecânica para malha de terra | C79: un | D79: =D72 -> 20 | F79: 10 | O79: =F79-M79 -> 10

Sheet MC_SS 171
L1: 46174 | M1: 46204 | N1: 46235 | O1: 46266
A2: Item | B2: Nome da Atividade | D2: MC1 | E2: MC2 | F2: Total | H2: ID da Atividade | I2: Duração Original | J2: Data de Início do Projeto de BL | K2: Data de Término do Projeto de BL
H3: Marcos Civil Projeto
H4: Liberação de Projeto
H5: Liberação de projeto para modificação de orçamento e cronograma
H6: P 27-TQ-116 - C | I6: 332.4h | J6: 46170.671 | K6: 46234.417
H7: Acesso TQ-116-C | I7: 332.4h | J7: 46170.671 | K7: 46234.417
H8: Preliminares | I8: 52.8h | J8: 46170.671 | K8: 46182.683
A9: 1.1.1.16 | B9: Levantamento topográfico | C9: hs | F9: 35.6 | H9: Levantamento Topografico | I9: 22.0h | J9: 46182.683 | K9: 46185.662 | L9: =F9 -> 35.6
H10: Marcação de area | I10: 27.0h | J10: 46185.662 | K10: 46191.496
H11: Regularização de Solo | I11: 69.8h | J11: 46191.496 | K11: 46204.633
A12: 1.1.2.2 | B12: Escavação mecanizada em solo até 3m | C12: m³ | F12: 2.226 | H12: Escavação mecanica e manual de solo | I12: 17.6h | J12: 46191.496 | K12: 46195.646 | M12: =F12 -> 2.226
H13: Regularização de solo | I13: 17.6h | J13: 46195.646 | K13: 46198.4
H14: Compactação de solo | I14: 17.0h | J14: 46198.4 | K14: 46202.483
A15: 1.1.2.14 | B15: Fornecimento, compactação e espalhamento de brita ou bica corrida | C15: m³ | F15: 22.23 | H15: Aplicação de BGS e lona | I15: 17.6h | J15: 46202.483 | K15: 46204.633 | M15: =F15 -> 22.23
A16: 1.1.3.1 | B16: Forma em chapa compensada plastificada | C16: m³ | F16: 0.69 | H16: Forma | I16: 72.0h | J16: 46204.633 | K16: 46218.467 | N16: =F16 -> 0.69
A17: 1.1.3.5 | B17: Armadura Aço CA-50 ou CA-60 | C17: kg | F17: 267.84 | H17: Aço | I17: 36.0h | J17: 46218.467 | K17: 46225.404 | N17: =F17 -> 267.84
A18: 1.1.3.9 | B18: Concreto estrutural fck 30 MPa | C18: m³ | F18: 14.322 | H18: Concreto | I18: 8.8h | J18: 46225.404 | K18: 46226.458 | N18: =F18 -> 14.322
A19: 1.1.3.20 | B19: Junta serrada em piso | C19: m | F19: 30 | N19: =F19 -> 30
A20: 1.1.12.19 | B20: Tubo Dreno em PEAD - Ø8" a Ø10"em leito de brita | C20: m | F20: 12.35 | H20: Desforma | I20: 17.0h | J20: 46226.458 | K20: 46230.583 | N20: =F20 -> 12.35
A21: 1.1.11.2 | B21: Pintura em tinta acrílica | C21: m² | F21: 91.2 | H21: Pintura | I21: 27.0h | J21: 46230.583 | K21: 46234.417 | N21: 32 | O21: =F21-N21 -> 59.2
H22: Bases Plataforma de Acesso | I22: 309.4h | J22: 46175.425 | K22: 46233.546
H23: Levantamento Topografico | I23: 27.0h | J23: 46175.425 | K23: 46181.654
H24: Marcação de area | I24: 37.0h | J24: 46181.654 | K24: 46188.633
H25: Regularização de Solo | I25: 72.2h | J25: 46188.633 | K25: 46202.475
A26: 1.1.2.2 | B26: Escavação mecanizada em solo até 3m | C26: m³ | F26: 1.484 | H26: Escavação mecanica e manual de solo | I26: 37.0h | J26: 46188.633 | K26: 46195.613 | M26: =F26 -> 1.484
H27: Regularização de solo | I27: 17.6h | J27: 46195.613 | K27: 46198.367
A28: 1.1.3.7 | B28: Concreto fck 15 MPa | C28: m³ | F28: 2.1 | H28: Compactação de solo | I28: 17.6h | J28: 46198.367 | K28: 46202.475 | M28: =F28 -> 2.1
A29: 1.1.3.1 | B29: Forma em chapa compensada plastificada | C29: m³ | F29: 0.46 | H29: Forma | I29: 36.0h | J29: 46202.475 | K29: 46209.412 | M29: =F29 -> 0.46
A30: 1.1.3.5 | B30: Armadura Aço CA-50 ou CA-60 | C30: kg | F30: 178.56 | H30: Aço | I30: 72.0h | J30: 46209.412 | K30: 46220.642 | M30: =F30 -> 178.56
A31: 1.1.3.9 | B31: Concreto estrutural fck 30 MPa | C31: m³ | F31: 9.548 | H31: Concreto | N31: =F31 -> 9.548
A32: 1.1.3.11 | B32: Graute de base cimentícia auto-adensável | C32: m³ | F32: 1.1 | N32: =F32 -> 1.1
A33: 1.1.3.14 | B33: Chumbadores e inserts metálicos embutidos em concreto | C33: kg | F33: 40 | N33: =F33 -> 40
H34: Desforma | I34: 17.6h | J34: 46220.642 | K34: 46225.396
H35: P 27-TQ-116 - E | I35: 284.6h | J35: 46195.496 | K35: 46247.479
H36: Acesso TQ-01-E | I36: 284.6h | J36: 46195.496 | K36: 46247.479
H37: Preliminares | I37: 52.8h | J37: 46195.496 | K37: 46204.55
H38: Levantamento Topografico | I38: 17.6h | J38: 46202.4 | K38: 46204.55
H39: Marcação de area | I39: 36.0h | J39: 46204.55 | K39: 46211.446
H40: Regularização de Solo | I40: 79.8h | J40: 46204.55 | K40: 46219.396
A41: 1.1.2.2 | B41: Escavação mecanizada em solo até 3m | C41: m³ | F41: 2.46 | H41: Escavação mecanica e manual de solo | I41: 27.0h | J41: 46204.55 | K41: 46210.383 | M41: =F41 -> 2.46
H42: Regularização de solo | I42: 17.6h | J42: 46210.383 | K42: 46212.492
H43: Compactação de solo | I43: 17.6h | J43: 46212.492 | K43: 46216.642
A44: 1.1.2.14 | B44: Fornecimento, compactação e espalhamento de brita ou bica corrida | C44: m³ | F44: 24.57 | H44: Aplicação de BGS e lona | I44: 17.6h | J44: 46216.642 | K44: 46219.396 | M44: =F44 -> 24.57
A45: 1.1.3.1 | B45: Forma em chapa compensada plastificada | C45: m³ | F45: 0.708 | H45: Forma | I45: 72.0h | J45: 46219.396 | K45: 46232.625 | M45: =F45 -> 0.708
A46: 1.1.3.5 | B46: Armadura Aço CA-50 ou CA-60 | C46: kg | F46: 244.56 | H46: Aço | I46: 36.0h | J46: 46232.625 | K46: 46239.562 | M46: =F46 -> 244.56
A47: 1.1.3.9 | B47: Concreto estrutural fck 30 MPa | C47: m³ | F47: 15.024 | H47: Concreto | I47: 8.8h | J47: 46239.562 | K47: 46240.617 | N47: =F47 -> 15.024
A48: 1.1.3.20 | B48: Junta serrada em piso | C48: m | F48: 30 | N48: 30
A49: 1.1.12.19 | B49: Tubo Dreno em PEAD - Ø8" a Ø10"em leito de brita | C49: m | F49: 13.65 | H49: Desforma | I49: 17.6h | J49: 46240.617 | K49: 46245.371 | N49: =F49 -> 13.65
A50: 1.1.11.2 | B50: Pintura em tinta acrílica | C50: m² | F50: 100.8 | H50: Pintura | I50: 17.6h | J50: 46245.371 | K50: 46247.479 | M50: 42 | N50: =F50-M50 -> 58.8
H51: Bases Plataforma de Acesso | I51: 193.6h | J51: 46197.646 | K51: 46233.588
H52: Levantamento Topografico | I52: 17.6h | J52: 46197.646 | K52: 46202.4
H53: Regularização de Solo | I53: 27.0h | J53: 46202.4 | K53: 46205.629
A54: 1.1.2.2 | B54: Escavação mecanizada em solo até 3m | C54: m³ | F54: 1.64 | H54: Escavação mecanica e manual de solo | I54: 62.2h | J54: 46205.629 | K54: 46218.367 | M54: =F54 -> 1.64
